shift_reg/ser.v
module ser(in,clk,reset,out);

input in, clk, reset;
output [7:0] out;

reg [7:0] out;

always @(posedge clk)
	begin
		if (reset) begin
			out <= 8'b0;
		end else begin
			out <= (out << 1) | in;
		end
	end
endmodule //ser

shift_reg/ser_tb.v
module test;

reg in, clk, reset;

wire [3:0] out;

initial begin
	$dumpfile("ser.vcd");
	$dumpvars(0,my_ser);
	$display("reset in out[3-0]");
	$monitor("%b   %b   %b   %b   %b   %b",reset, in, out[3], out[2], out[1], out[0]);
	clk = 0;
	in = 0;
	reset = 0;
	#3 reset = 1;
	#10 reset = 0;
	#5 in = 1;
	#100 $finish;
end

always begin
	#5 clk = ~clk;
end

ser my_ser(in,clk,reset,out);

endmodule //test

shift_reg/ser.vcd
$date
	Sun Jun 21 19:49:04 2015
$end
$version
	Icarus Verilog
$end
$timescale
	1s
$end
$scope module test $end
$scope module my_ser $end
$var wire 1 ! clk $end
$var wire 1 " in $end
$var wire 1 # reset $end
$var reg 8 $ out [7:0] $end
$upscope $end
$upscope $end
$enddefinitions $end
#0
$dumpvars
bx $
0#
0"
0!
$end
#3
1#
#5
b0 $
1!
#10
0!
#13
0#
#15
1!
#18
1"
#20
0!
#25
b1 $
1!
#30
0!
#35
b11 $
1!
#40
0!
#45
b111 $
1!
#50
0!
#55
b1111 $
1!
#60
0!
#65
b11111 $
1!
#70
0!
#75
b111111 $
1!
#80
0!
#85
b1111111 $
1!
#90
0!
#95
b11111111 $
1!
