VIN_SPC/vin_spc.v
/**************************************
* Module: vin_spc
* Date:2016-07-29  
* Author: Saul and Raul     
*
* Description: Serial to Parallel converter used for configuring BIO IC V1
* This block uses 3 control lines: Cfg_in, Clk, and Resetn 
* Cfg_in is sampled at rising edge of Clk. After 14 bits, the data is latched to the paralell outputs
* 
* 
* Configuation word: F3,F2,F1,F0,    IQ,   GS3,GS2,GS1,GS0,  CE,   NS,    GD2,GD1,GD0
* F<3:0>    Frequency selection 0 - 15  (0 highest frequency (VCO freq), 15 lowest frequency)
* IQ        I = 0, Q = 1
* GS<3:0>   Signal Generator Gain [0000, 0001, 0011, 0111, 1111]
* CE        Signal Generator enable 
* NS        Signal Generator number of steps NS = 0 (32 steps), NS = 1 (16 steps)
* GD<2:0>   Demodulator Gain [100, 101, 111, 011] (NOTE: G[2] is active low logic!)
* FS        Filter Selection FS = 0 (fast), FS = 1 (slow)
* RE        Reserve pin
* 
***************************************/
module  vin_spc(
Cfg_in,
Clk,
Resetn,
EnLF,
EnMF,
EnHF,
DN,
DP,
EnRdeg,
EnRdegHF,
CcompSel,
CapSel,
F,
IQ,
GS,
CE,
NS,
GD,
FS,
RE
);

input Cfg_in, Clk, Resetn;

//Filter control
output reg EnLF;
output reg EnMF;
output reg EnHF;
output reg [1:0] DN;
output reg [2:0] DP;
output reg EnRdeg;
output reg [1:0] EnRdegHF;
output reg [1:0] CcompSel;
output reg [3:0] CapSel;

//Implantable control
output reg[3:0] F;
output reg IQ;
output reg [3:0] GS;
output reg CE;
output reg NS;
output reg [2:0] GD;
output reg FS;
output reg RE;


reg [32:0] out; 
reg [5:0] count;

wire strobe;

/*
* Right Shift register with async. reset  
*/
always @(posedge Clk, negedge Resetn)
begin
    if (Resetn == 0) begin
        out <= 0;
        count <= 33;
    end else begin
        //Shift the data
        out[32] <= Cfg_in;        
        out[31] <= out[32];
        out[30] <= out[31];
        out[29] <= out[30];
        out[28] <= out[29];
        out[27] <= out[28];
        out[26] <= out[27];
        out[25] <= out[26];
        out[24] <= out[25];
        out[23] <= out[24];
        out[22] <= out[23];
        out[21] <= out[22];
        out[20] <= out[21];
        out[19] <= out[20];
        out[18] <= out[19];
        out[17] <= out[18];
        out[16] <= out[17];
        //IMP original configuration
        out[15] <= out[16];
        out[14] <= out[15];
        out[13] <= out[14];
        out[12] <= out[13];
        out[11] <= out[12];
        out[10] <= out[11];
        out[9] <= out[10];
        out[8] <= out[9];
        out[7] <= out[8];
        out[6] <= out[7];
        out[5] <= out[6];
        out[4] <= out[5];
        out[3] <= out[4];
        out[2] <= out[3];
        out[1] <= out[2];
        out[0] <= out[1];
        
        //Decrement the counter
        count <= count - 1;
    end    
end

assign strobe = (!count) & (~Clk);

always @(posedge strobe, negedge Resetn)
begin
    if (Resetn == 0) begin
        F[3:0] <= 0;
        IQ <= 0;
        GS[3:0] <= 0;
        CE <= 0;
        NS <= 0;
        GD[2:0] <= 0;
        FS <= 0;
        RE <= 0;
        
        //Filter
        EnLF <= 0;
        EnMF <= 0;
        EnHF <= 0;
        DN[1:0] <= 0;
        DP[2:0] <= 0;
        EnRdeg <= 0;
        EnRdegHF[1:0] <= 0; 
        CcompSel[1:0] <= 0;
        CapSel[3:0] <= 0;
        
    end else begin
        EnLF <= out[32];
        EnMF <= out[31];
        EnHF <= out[30];
        DN[1:0] <= out[29:28];
        DP[2:0] <= out[27:25];
        EnRdeg <= out[24];
        EnRdegHF[1:0] <= out[23:22]; 
        CcompSel[1:0] <= out[21:20];
        CapSel[3:0] <= out[19:16];
        
        F[3:0] <= out[15:12];
        IQ <= out[11];
        GS[3:0] <= out[10:7];
        CE <= out[6];
        NS <= out[5];
        GD[2:0] <= out[4:2];
        FS <= out[1];
        RE <= out[0];
                
        
    end
end

endmodule

VIN_SPC/vin_spc_tb.v
/**********************************************************************
* Module: vin_spc_tb
* Date:2016-07-29  
* Author: saul and raul     
*
* Description: test bench for spc2
* 
* Configuation word: F3,F2,F1,F0,    IQ,   GS3,GS2,GS1,GS0,  CE, NS,  GD2,GD1,GD0
* F<3:0>    Frequency selection 0 - 15  (0 highest frequency (VCO freq), 15 lowest frequency)
* IQ        I = 0, Q = 1
* GS<3:0>   Signal Generator Gain [0000, 0001, 0011, 0111, 1111]
* CE        Signal Generator enable 
* NS        Signal Generator number of steps NS = 0 (32 steps), NS = 1 (16 steps)
* GD<2:0>   Demodulator Gain [100, 101, 111, 011] (NOTE: G[2] is active low logic!)
* FS        Filter Selection FS = 0 (fast), FS = 1 (slow)
* RE        Reserve pin
*  
***********************************************************************/

module  vin_spc_tb(
);

//Lines to drive
//reg Clk, Resetn, Cfg_in, Strobe;
reg Clk, Resetn, Cfg_in;


//Output signals
//wire [3:0] F;
//wire IQ;
//wire [2:0] G;
//wire CE;
//wire [1:0] GCP;

//Filter control
wire EnLF;
wire EnMF;
wire EnHF;
wire [1:0] DN;
wire [2:0] DP;
wire EnRdeg;
wire [1:0] EnRdegHF;
wire [1:0] CcompSel;
wire [3:0] CapSel;

//Implantable
wire [3:0] F;
wire IQ;
wire [3:0] GS;
wire CE;
wire NS;
wire [2:0] GD;
wire FS;
wire RE;

//parameter [15:0] confWord  = 16'b1010_1_1011_0_1_001_0_1; //0x561
//parameter [15:0] confWord2 = 16'b0101_0_0100_1_0_110_1_0; //0x657

parameter [32:0] confWord   = 33'b1_0_1_11_001_0_01_10_0110_1010_1_1011_0_1_001_0_1; //0x561
parameter [32:0] confWord2  = 33'b0_1_0_00_110_1_10_01_1001_0101_0_0100_1_0_110_1_0; //0x561

reg [32:0] conf;
reg [32:0] conf2;


initial begin
    $dumpfile("vin_spc.vcd");
    $dumpvars(0,my_vin_spc);
    
    conf = confWord;
    conf2 = confWord2;
    
    Clk = 0;
    Resetn = 1;
    Cfg_in = 0;
//    Strobe = 0;
    
    #1 Resetn = 0;
    #2 Resetn = 1;
    #1 Cfg_in = conf[0];
    #10 Cfg_in = conf[1];
    #10 Cfg_in = conf[2];
    #10 Cfg_in = conf[3];
    #10 Cfg_in = conf[4];
    #10 Cfg_in = conf[5];
    #10 Cfg_in = conf[6];
    #10 Cfg_in = conf[7];
    #10 Cfg_in = conf[8];
    #10 Cfg_in = conf[9];
    #10 Cfg_in = conf[10];
    #10 Cfg_in = conf[11];
    #10 Cfg_in = conf[12];
    #10 Cfg_in = conf[13];    
    #10 Cfg_in = conf[14];
    #10 Cfg_in = conf[15];
    #10 Cfg_in = conf[16];
    #10 Cfg_in = conf[17];
    #10 Cfg_in = conf[18];
    #10 Cfg_in = conf[19];
    #10 Cfg_in = conf[20];
    #10 Cfg_in = conf[21];
    #10 Cfg_in = conf[22];
    #10 Cfg_in = conf[23];
    #10 Cfg_in = conf[24];
    #10 Cfg_in = conf[25];
    #10 Cfg_in = conf[26];
    #10 Cfg_in = conf[27];
    #10 Cfg_in = conf[28];
    #10 Cfg_in = conf[29];
    #10 Cfg_in = conf[30];
    #10 Cfg_in = conf[31];
    #10 Cfg_in = conf[32];
    
    
    
    
    
    //Second word
    
    #60 Resetn = 0;
    #2 Resetn = 1;
    #1 Cfg_in = conf2[0];
    #10 Cfg_in = conf2[1];
    #10 Cfg_in = conf2[2];
    #10 Cfg_in = conf2[3];
    #10 Cfg_in = conf2[4];
    #10 Cfg_in = conf2[5];
    #10 Cfg_in = conf2[6];
    #10 Cfg_in = conf2[7];
    #10 Cfg_in = conf2[8];
    #10 Cfg_in = conf2[9];
    #10 Cfg_in = conf2[10];
    #10 Cfg_in = conf2[11];
    #10 Cfg_in = conf2[12];
    #10 Cfg_in = conf2[13];
    #10 Cfg_in = conf2[14];
    #10 Cfg_in = conf2[15];
    #10 Cfg_in = conf2[16];
    #10 Cfg_in = conf2[17];
    #10 Cfg_in = conf2[18];
    #10 Cfg_in = conf2[19];
    #10 Cfg_in = conf2[20];
    #10 Cfg_in = conf2[21];
    #10 Cfg_in = conf2[22];
    #10 Cfg_in = conf2[23];
    #10 Cfg_in = conf2[24];
    #10 Cfg_in = conf2[25];
    #10 Cfg_in = conf2[26];
    #10 Cfg_in = conf2[27];
    #10 Cfg_in = conf2[28];
    #10 Cfg_in = conf2[29];
    #10 Cfg_in = conf2[30];
    #10 Cfg_in = conf2[31];
    #10 Cfg_in = conf2[32];
    
    
  //  #5 Strobe = 1;
    #50 $finish;    
    
end

always begin
    #5 Clk = ~Clk;
end

//vin_spc my_vin_spc(Cfg_in,Clk,Resetn,F,IQ,GS,CE,NS,GD,FS,RE);
vin_spc my_vin_spc(Cfg_in,Clk,Resetn,EnLF,EnMF,EnHF,DN,DP,EnRdeg,EnRdegHF,CcompSel,CapSel,F,IQ,GS,CE,NS,GD,FS,RE);


endmodule

VIN_SPC/vin_spc.vcd
$date
	Fri Jul 29 14:58:49 2016
$end
$version
	Icarus Verilog
$end
$timescale
	1s
$end
$scope module vin_spc_tb $end
$scope module my_vin_spc $end
$var wire 1 ! Cfg_in $end
$var wire 1 " Clk $end
$var wire 1 # Resetn $end
$var wire 1 $ strobe $end
$var reg 1 % CE $end
$var reg 4 & CapSel [3:0] $end
$var reg 2 ' CcompSel [1:0] $end
$var reg 2 ( DN [1:0] $end
$var reg 3 ) DP [2:0] $end
$var reg 1 * EnHF $end
$var reg 1 + EnLF $end
$var reg 1 , EnMF $end
$var reg 1 - EnRdeg $end
$var reg 2 . EnRdegHF [1:0] $end
$var reg 4 / F [3:0] $end
$var reg 1 0 FS $end
$var reg 3 1 GD [2:0] $end
$var reg 4 2 GS [3:0] $end
$var reg 1 3 IQ $end
$var reg 1 4 NS $end
$var reg 1 5 RE $end
$var reg 6 6 count [5:0] $end
$var reg 33 7 out [32:0] $end
$upscope $end
$upscope $end
$enddefinitions $end
#0
$dumpvars
bx 7
bx 6
x5
x4
x3
bx 2
bx 1
x0
bx /
bx .
x-
x,
x+
x*
bx )
bx (
bx '
bx &
x%
x$
1#
0"
0!
$end
#1
0$
b0 &
b0 '
b0 .
0-
b0 )
b0 (
0*
0,
0+
05
00
b0 1
04
0%
b0 2
03
b0 /
b100001 6
b0 7
0#
#3
1#
#4
1!
#5
b100000 6
b100000000000000000000000000000000 7
1"
#10
0"
#14
0!
#15
b11111 6
b10000000000000000000000000000000 7
1"
#20
0"
#24
1!
#25
b11110 6
b101000000000000000000000000000000 7
1"
#30
0"
#34
0!
#35
b11101 6
b10100000000000000000000000000000 7
1"
#40
0"
#45
b11100 6
b1010000000000000000000000000000 7
1"
#50
0"
#54
1!
#55
b11011 6
b100101000000000000000000000000000 7
1"
#60
0"
#64
0!
#65
b11010 6
b10010100000000000000000000000000 7
1"
#70
0"
#74
1!
#75
b11001 6
b101001010000000000000000000000000 7
1"
#80
0"
#85
b11000 6
b110100101000000000000000000000000 7
1"
#90
0"
#94
0!
#95
b10111 6
b11010010100000000000000000000000 7
1"
#100
0"
#104
1!
#105
b10110 6
b101101001010000000000000000000000 7
1"
#110
0"
#115
b10101 6
b110110100101000000000000000000000 7
1"
#120
0"
#124
0!
#125
b10100 6
b11011010010100000000000000000000 7
1"
#130
0"
#134
1!
#135
b10011 6
b101101101001010000000000000000000 7
1"
#140
0"
#144
0!
#145
b10010 6
b10110110100101000000000000000000 7
1"
#150
0"
#154
1!
#155
b10001 6
b101011011010010100000000000000000 7
1"
#160
0"
#164
0!
#165
b10000 6
b10101101101001010000000000000000 7
1"
#170
0"
#174
1!
#175
b1111 6
b101010110110100101000000000000000 7
1"
#180
0"
#185
b1110 6
b110101011011010010100000000000000 7
1"
#190
0"
#194
0!
#195
b1101 6
b11010101101101001010000000000000 7
1"
#200
0"
#205
b1100 6
b1101010110110100101000000000000 7
1"
#210
0"
#214
1!
#215
b1011 6
b100110101011011010010100000000000 7
1"
#220
0"
#225
b1010 6
b110011010101101101001010000000000 7
1"
#230
0"
#234
0!
#235
b1001 6
b11001101010110110100101000000000 7
1"
#240
0"
#245
b1000 6
b1100110101011011010010100000000 7
1"
#250
0"
#254
1!
#255
b111 6
b100110011010101101101001010000000 7
1"
#260
0"
#264
0!
#265
b110 6
b10011001101010110110100101000000 7
1"
#270
0"
#275
b101 6
b1001100110101011011010010100000 7
1"
#280
0"
#284
1!
#285
b100 6
b100100110011010101101101001010000 7
1"
#290
0"
#295
b11 6
b110010011001101010110110100101000 7
1"
#300
0"
#305
b10 6
b111001001100110101011011010010100 7
1"
#310
0"
#314
0!
#315
b1 6
b11100100110011010101101101001010 7
1"
#320
0"
#324
1!
#325
b0 6
b101110010011001101010110110100101 7
1"
#330
15
b1 1
14
b1011 2
13
b1010 /
b110 &
b10 '
b1 .
b1 )
b11 (
1*
1+
1$
0"
#335
b111111 6
b110111001001100110101011011010010 7
0$
1"
#340
0"
#345
b111110 6
b111011100100110011010101101101001 7
1"
#350
0"
#355
b111101 6
b111101110010011001101010110110100 7
1"
#360
0"
#365
b111100 6
b111110111001001100110101011011010 7
1"
#370
0"
#375
b111011 6
b111111011100100110011010101101101 7
1"
#380
0"
#384
b0 &
b0 '
b0 .
b0 )
b0 (
0*
0+
05
b0 1
04
b0 2
03
b0 /
b100001 6
b0 7
0#
#385
1"
#386
1#
#387
0!
#390
0"
#395
b100000 6
b0 7
1"
#397
1!
#400
0"
#405
b11111 6
b100000000000000000000000000000000 7
1"
#407
0!
#410
0"
#415
b11110 6
b10000000000000000000000000000000 7
1"
#417
1!
#420
0"
#425
b11101 6
b101000000000000000000000000000000 7
1"
#430
0"
#435
b11100 6
b110100000000000000000000000000000 7
1"
#437
0!
#440
0"
#445
b11011 6
b11010000000000000000000000000000 7
1"
#447
1!
#450
0"
#455
b11010 6
b101101000000000000000000000000000 7
1"
#457
0!
#460
0"
#465
b11001 6
b10110100000000000000000000000000 7
1"
#470
0"
#475
b11000 6
b1011010000000000000000000000000 7
1"
#477
1!
#480
0"
#485
b10111 6
b100101101000000000000000000000000 7
1"
#487
0!
#490
0"
#495
b10110 6
b10010110100000000000000000000000 7
1"
#500
0"
#505
b10101 6
b1001011010000000000000000000000 7
1"
#507
1!
#510
0"
#515
b10100 6
b100100101101000000000000000000000 7
1"
#517
0!
#520
0"
#525
b10011 6
b10010010110100000000000000000000 7
1"
#527
1!
#530
0"
#535
b10010 6
b101001001011010000000000000000000 7
1"
#537
0!
#540
0"
#545
b10001 6
b10100100101101000000000000000000 7
1"
#547
1!
#550
0"
#555
b10000 6
b101010010010110100000000000000000 7
1"
#557
0!
#560
0"
#565
b1111 6
b10101001001011010000000000000000 7
1"
#570
0"
#575
b1110 6
b1010100100101101000000000000000 7
1"
#577
1!
#580
0"
#585
b1101 6
b100101010010010110100000000000000 7
1"
#590
0"
#595
b1100 6
b110010101001001011010000000000000 7
1"
#597
0!
#600
0"
#605
b1011 6
b11001010100100101101000000000000 7
1"
#610
0"
#615
b1010 6
b1100101010010010110100000000000 7
1"
#617
1!
#620
0"
#625
b1001 6
b100110010101001001011010000000000 7
1"
#630
0"
#635
b1000 6
b110011001010100100101101000000000 7
1"
#637
0!
#640
0"
#645
b111 6
b11001100101010010010110100000000 7
1"
#647
1!
#650
0"
#655
b110 6
b101100110010101001001011010000000 7
1"
#660
0"
#665
b101 6
b110110011001010100100101101000000 7
1"
#667
0!
#670
0"
#675
b100 6
b11011001100101010010010110100000 7
1"
#680
0"
#685
b11 6
b1101100110010101001001011010000 7
1"
#690
0"
#695
b10 6
b110110011001010100100101101000 7
1"
#697
1!
#700
0"
#705
b1 6
b100011011001100101010010010110100 7
1"
#707
0!
#710
0"
#715
b0 6
b10001101100110010101001001011010 7
1"
#720
10
b110 1
1%
b100 2
b101 /
b1001 &
b1 '
b10 .
1-
b110 )
1,
1$
0"
#725
b111111 6
b1000110110011001010100100101101 7
0$
1"
#730
0"
#735
b111110 6
b100011011001100101010010010110 7
1"
#740
0"
#745
b111101 6
b10001101100110010101001001011 7
1"
#750
0"
#755
b111100 6
b1000110110011001010100100101 7
1"
