VIN_SPC/vin_spc.v
/**************************************
* Module: vin_spc
* Date:2016-07-29  
* Author: Saul and Raul     
*
* Description: Serial to Parallel converter used for configuring BIO IC V1
* This block uses 3 control lines: Cfg_in, Clk, and Resetn 
* Cfg_in is sampled at rising edge of Clk. After 14 bits, the data is latched to the paralell outputs
* 
* 
* Configuation word: F3,F2,F1,F0,    IQ,   GS3,GS2,GS1,GS0,  CE,   NS,    GD2,GD1,GD0
* F<3:0>    Frequency selection 0 - 15  (0 highest frequency (VCO freq), 15 lowest frequency)
* IQ        I = 0, Q = 1
* GS<3:0>   Signal Generator Gain [0000, 0001, 0011, 0111, 1111]
* CE        Signal Generator enable 
* NS        Signal Generator number of steps NS = 0 (32 steps), NS = 1 (16 steps)
* GD<2:0>   Demodulator Gain [100, 101, 111, 011] (NOTE: G[2] is active low logic!)
* FS        Filter Selection FS = 0 (fast), FS = 1 (slow)
* RE        Reserve pin
* 
***************************************/
module  vin_spc(
Cfg_in,
Clk,
Resetn,
EnLF,
EnMF,
EnHF,
DN,
DP,
EnRdeg,
EnRdegHF,
CcompSel,
CapSel,
F,
IQ,
GS,
CE,
NS,
GD,
FS,
RE
);

input Cfg_in, Clk, Resetn;

//Filter control
output reg EnLF;
output reg EnMF;
output reg EnHF;
output reg [1:0] DN;
output reg [2:0] DP;
output reg EnRdeg;
output reg [1:0] EnRdegHF;
output reg [1:0] CcompSel;
output reg [3:0] CapSel;

//Implantable control
output reg[3:0] F;
output reg IQ;
output reg [3:0] GS;
output reg CE;
output reg NS;
output reg [2:0] GD;
output reg FS;
output reg RE;


reg [32:0] out; 
reg [5:0] count;

wire strobe;

/*
* Right Shift register with async. reset  
*/
always @(posedge Clk, negedge Resetn)
begin
    if (Resetn == 0) begin
        out <= 0;
        count <= 33;
    end else begin
        //Shift the data
        out[32] <= Cfg_in;        
        out[31] <= out[32];
        out[30] <= out[31];
        out[29] <= out[30];
        out[28] <= out[29];
        out[27] <= out[28];
        out[26] <= out[27];
        out[25] <= out[26];
        out[24] <= out[25];
        out[23] <= out[24];
        out[22] <= out[23];
        out[21] <= out[22];
        out[20] <= out[21];
        out[19] <= out[20];
        out[18] <= out[19];
        out[17] <= out[18];
        out[16] <= out[17];
        //IMP original configuration
        out[15] <= out[16];
        out[14] <= out[15];
        out[13] <= out[14];
        out[12] <= out[13];
        out[11] <= out[12];
        out[10] <= out[11];
        out[9] <= out[10];
        out[8] <= out[9];
        out[7] <= out[8];
        out[6] <= out[7];
        out[5] <= out[6];
        out[4] <= out[5];
        out[3] <= out[4];
        out[2] <= out[3];
        out[1] <= out[2];
        out[0] <= out[1];
        
        //Decrement the counter
        count <= count - 1;
    end    
end

assign strobe = (!count) & (~Clk);

always @(posedge strobe, negedge Resetn)
begin
    if (Resetn == 0) begin
        F[3:0] <= 0;
        IQ <= 0;
        GS[3:0] <= 0;
        CE <= 0;
        NS <= 0;
        GD[2:0] <= 0;
        FS <= 0;
        RE <= 0;
        
        //Filter
        EnLF <= 0;
        EnMF <= 0;
        EnHF <= 0;
        DN[1:0] <= 0;
        DP[2:0] <= 0;
        EnRdeg <= 0;
        EnRdegHF[1:0] <= 0; 
        CcompSel[1:0] <= 0;
        CapSel[3:0] <= 0;
        
    end else begin
        EnLF <= out[32];
        EnMF <= out[31];
        EnHF <= out[30];
        DN[1:0] <= out[29:28];
        DP[2:0] <= out[27:25];
        EnRdeg <= out[24];
        EnRdegHF[1:0] <= out[23:22]; 
        CcompSel[1:0] <= out[21:20];
        CapSel[3:0] <= out[19:16];
        
        F[3:0] <= out[15:12];
        IQ <= out[11];
        GS[3:0] <= out[10:7];
        CE <= out[6];
        NS <= out[5];
        GD[2:0] <= out[4:2];
        FS <= out[1];
        RE <= out[0];
                
        
    end
end

endmodule

VIN_SPC/FPGA/project_1/project_1.srcs/sources_1/imports/FPGA/top.v
/*
* PapilioDuo top module of spc2 Vinnova
* top.v
*/

module top(
Cfg_in,
Clk,
Resetn,
DIR_LEFT,
DIR_RIGHT,
DIR_UP,
DIR_DOWN,
LED0,
LED1,
LED2,
LED3,
LED4,
LED5,
LED6,
LED7,
ARDUINO_RESET
);


input Cfg_in, Clk, Resetn, DIR_LEFT, DIR_RIGHT, DIR_UP, DIR_DOWN;


//Filter control Vinnova
wire EnLF;
wire EnMF;
wire EnHF;
wire [1:0] DN;
wire [2:0] DP;
wire EnRdeg;
wire [1:0] EnRdegHF;
wire [1:0] CcompSel;
wire [3:0] CapSel;

//Common with implantable
wire[3:0] F;
wire IQ;
wire [3:0] GS;
wire CE;
wire NS;
wire [2:0] GD;
wire FS;
wire RE;

output reg LED0;
output reg LED1;
output reg LED2;
output reg LED3;
output reg LED4;
output reg LED5;
output reg LED6;
output reg LED7;
output wire ARDUINO_RESET;

assign ARDUINO_RESET = 0;

always @(*) 
begin
	if (DIR_LEFT) begin // BYTE1
	    LED0 = GS[1];
        LED1 = GS[2];
        LED2 = GS[3];
        LED3 = IQ;
        LED4 = F[0];
        LED5 = F[1];
        LED6 = F[2];
        LED7 = F[3]; 
	end else if (DIR_RIGHT) begin // BYTE2
		LED0 = CapSel[0];
        LED1 = CapSel[1];
        LED2 = CapSel[2];
        LED3 = CapSel[3];
        LED4 = CcompSel[0];
        LED5 = CcompSel[1];
        LED6 = EnRdegHF[0];
        LED7 = EnRdegHF[1]; 	
	end else if (DIR_UP) begin // BYTE3
		LED0 = EnRdeg;
        LED1 = DP[0];
        LED2 = DP[1];
        LED3 = DP[2];
        LED4 = DN[0];
        LED5 = DN[1];
        LED6 = EnHF;
        LED7 = EnMF;
	end else if (DIR_DOWN) begin // BYTE4
		LED0 = EnLF;
        LED1 = 0;
        LED2 = 0;
        LED3 = 0;
        LED4 = 0;
        LED5 = 0;
        LED6 = 0;
        LED7 = 0;
	end else begin // Default no button pressed: BYTE0
		LED0 = RE;
        LED1 = FS;
        LED2 = GD[0];
        LED3 = GD[1];
        LED4 = GD[2];
        LED5 = NS;
        LED6 = CE;
        LED7 = GS[0];
	end

end

//spc2 spc2_1(Cfg_in,Clk,Resetn,F,IQ,GS,CE,NS,GD,FS,RE);
vin_spc vin_spc_1(Cfg_in,Clk,Resetn,EnLF,EnMF,EnHF,DN,DP,EnRdeg,EnRdegHF,CcompSel,CapSel,F,IQ,GS,CE,NS,GD,FS,RE);

endmodule

VIN_SPC/FPGA/vin_spc_tb.v
/**********************************************************************
* Module: vin_spc_tb
* Date:2016-07-29  
* Author: saul and raul     
*
* Description: test bench for spc2
* 
* Configuation word: F3,F2,F1,F0,    IQ,   GS3,GS2,GS1,GS0,  CE, NS,  GD2,GD1,GD0
* F<3:0>    Frequency selection 0 - 15  (0 highest frequency (VCO freq), 15 lowest frequency)
* IQ        I = 0, Q = 1
* GS<3:0>   Signal Generator Gain [0000, 0001, 0011, 0111, 1111]
* CE        Signal Generator enable 
* NS        Signal Generator number of steps NS = 0 (32 steps), NS = 1 (16 steps)
* GD<2:0>   Demodulator Gain [100, 101, 111, 011] (NOTE: G[2] is active low logic!)
* FS        Filter Selection FS = 0 (fast), FS = 1 (slow)
* RE        Reserve pin
*  
***********************************************************************/

module  vin_spc_tb(
);

//Lines to drive
//reg Clk, Resetn, Cfg_in, Strobe;
reg Clk, Resetn, Cfg_in, DIR_LEFT, DIR_RIGHT, DIR_UP, DIR_DOWN;


//Output signals
//wire [3:0] F;
//wire IQ;
//wire [2:0] G;
//wire CE;
//wire [1:0] GCP;

//Filter control
wire EnLF;
wire EnMF;
wire EnHF;
wire [1:0] DN;
wire [2:0] DP;
wire EnRdeg;
wire [1:0] EnRdegHF;
wire [1:0] CcompSel;
wire [3:0] CapSel;

//Implantable
wire [3:0] F;
wire IQ;
wire [3:0] GS;
wire CE;
wire NS;
wire [2:0] GD;
wire FS;
wire RE;

//parameter [15:0] confWord  = 16'b1010_1_1011_0_1_001_0_1; //0x561
//parameter [15:0] confWord2 = 16'b0101_0_0100_1_0_110_1_0; //0x657

parameter [32:0] confWord   = 33'b1_0_1_11_001_0_01_10_0110_1010_1_1011_0_1_001_0_1; //0x561
parameter [32:0] confWord2  = 33'b0_1_0_00_110_1_10_01_1001_0101_0_0100_1_0_110_1_0; //0x561

reg [32:0] conf;
reg [32:0] conf2;


initial begin
    $dumpfile("top.vcd");
    $dumpvars(0,my_top);
    
    conf = confWord;
    conf2 = confWord2;
    
    Clk = 0;
    Resetn = 1;
    Cfg_in = 0;
    DIR_LEFT = 0;
    DIR_RIGHT = 0;
    DIR_UP = 0;
    DIR_DOWN = 0;
//    Strobe = 0;
    
    #1 Resetn = 0;
    #2 Resetn = 1;
    #1 Cfg_in = conf[0];
    #10 Cfg_in = conf[1];
    #10 Cfg_in = conf[2];
    #10 Cfg_in = conf[3];
    #10 Cfg_in = conf[4];
    #10 Cfg_in = conf[5];
    #10 Cfg_in = conf[6];
    #10 Cfg_in = conf[7];
    #10 Cfg_in = conf[8];
    #10 Cfg_in = conf[9];
    #10 Cfg_in = conf[10];
    #10 Cfg_in = conf[11];
    #10 Cfg_in = conf[12];
    #10 Cfg_in = conf[13];    
    #10 Cfg_in = conf[14];
    #10 Cfg_in = conf[15];
    #10 Cfg_in = conf[16];
    #10 Cfg_in = conf[17];
    #10 Cfg_in = conf[18];
    #10 Cfg_in = conf[19];
    #10 Cfg_in = conf[20];
    #10 Cfg_in = conf[21];
    #10 Cfg_in = conf[22];
    #10 Cfg_in = conf[23];
    #10 Cfg_in = conf[24];
    #10 Cfg_in = conf[25];
    #10 Cfg_in = conf[26];
    #10 Cfg_in = conf[27];
    #10 Cfg_in = conf[28];
    #10 Cfg_in = conf[29];
    #10 Cfg_in = conf[30];
    #10 Cfg_in = conf[31];
    #10 Cfg_in = conf[32];
    
    
    
    
    
    //Second word
    
    #60 Resetn = 0;
    #2 Resetn = 1;
    #1 Cfg_in = conf2[0];
    #10 Cfg_in = conf2[1];
    #10 Cfg_in = conf2[2];
    #10 Cfg_in = conf2[3];
    #10 Cfg_in = conf2[4];
    #10 Cfg_in = conf2[5];
    #10 Cfg_in = conf2[6];
    #10 Cfg_in = conf2[7];
    #10 Cfg_in = conf2[8];
    #10 Cfg_in = conf2[9];
    #10 Cfg_in = conf2[10];
    #10 Cfg_in = conf2[11];
    #10 Cfg_in = conf2[12];
    #10 Cfg_in = conf2[13];
    #10 Cfg_in = conf2[14];
    #10 Cfg_in = conf2[15];
    #10 Cfg_in = conf2[16];
    #10 Cfg_in = conf2[17];
    #10 Cfg_in = conf2[18];
    #10 Cfg_in = conf2[19];
    #10 Cfg_in = conf2[20];
    #10 Cfg_in = conf2[21];
    #10 Cfg_in = conf2[22];
    #10 Cfg_in = conf2[23];
    #10 Cfg_in = conf2[24];
    #10 Cfg_in = conf2[25];
    #10 Cfg_in = conf2[26];
    #10 Cfg_in = conf2[27];
    #10 Cfg_in = conf2[28];
    #10 Cfg_in = conf2[29];
    #10 Cfg_in = conf2[30];
    #10 Cfg_in = conf2[31];
    #10 Cfg_in = conf2[32];
    
    
  //  #5 Strobe = 1;
    #50 $finish;    
    
end

always begin
    #5 Clk = ~Clk;
end

//vin_spc my_vin_spc(Cfg_in,Clk,Resetn,F,IQ,GS,CE,NS,GD,FS,RE);
top my_top(Cfg_in,Clk,Resetn,DIR_LEFT,DIR_RIGHT,DIR_UP,DIR_DOWN,LED0,LED1,LED2,LED3,LED4,LED5,LED6,LED7,ARDUINO_RESET);


endmodule

VIN_SPC/FPGA/project_1/project_1.sim/sim_1/behav/top.vcd
$date
   Fri Sep 16 16:16:49 2016
$end
$version
  P.20131013
$end
$timescale
  1ps
$end
$scope module vin_spc_tb $end
$scope module my_top $end
$var wire 1 R Cfg_in $end
$var wire 1 S Clk $end
$var wire 1 T Resetn $end
$var wire 1 $ DIR_LEFT $end
$var wire 1 % DIR_RIGHT $end
$var wire 1 & DIR_UP $end
$var wire 1 ' DIR_DOWN $end
$var wire 1 ( EnLF $end
$var wire 1 ) EnMF $end
$var wire 1 * EnHF $end
$var wire 1 + DN [1] $end
$var wire 1 , DN [0] $end
$var wire 1 - DP [2] $end
$var wire 1 . DP [1] $end
$var wire 1 / DP [0] $end
$var wire 1 0 EnRdeg $end
$var wire 1 1 EnRdegHF [1] $end
$var wire 1 2 EnRdegHF [0] $end
$var wire 1 3 CcompSel [1] $end
$var wire 1 4 CcompSel [0] $end
$var wire 1 5 CapSel [3] $end
$var wire 1 6 CapSel [2] $end
$var wire 1 7 CapSel [1] $end
$var wire 1 8 CapSel [0] $end
$var wire 1 9 F [3] $end
$var wire 1 : F [2] $end
$var wire 1 ; F [1] $end
$var wire 1 < F [0] $end
$var wire 1 = IQ $end
$var wire 1 > GS [3] $end
$var wire 1 ? GS [2] $end
$var wire 1 @ GS [1] $end
$var wire 1 A GS [0] $end
$var wire 1 B CE $end
$var wire 1 C NS $end
$var wire 1 D GD [2] $end
$var wire 1 E GD [1] $end
$var wire 1 F GD [0] $end
$var wire 1 G FS $end
$var wire 1 H RE $end
$var wire 1 I ARDUINO_RESET $end
$var reg 1 J LED0 $end
$var reg 1 K LED1 $end
$var reg 1 L LED2 $end
$var reg 1 M LED3 $end
$var reg 1 N LED4 $end
$var reg 1 O LED5 $end
$var reg 1 P LED6 $end
$var reg 1 Q LED7 $end
$scope module vin_spc_1 $end
$var wire 1 R Cfg_in $end
$var wire 1 S Clk $end
$var wire 1 T Resetn $end
$var wire 1 U strobe $end
$var reg 1 V EnLF $end
$var reg 1 W EnMF $end
$var reg 1 X EnHF $end
$var reg 2 Y DN [1:0] $end
$var reg 3 Z DP [2:0] $end
$var reg 1 [ EnRdeg $end
$var reg 2 \ EnRdegHF [1:0] $end
$var reg 2 ] CcompSel [1:0] $end
$var reg 4 ^ CapSel [3:0] $end
$var reg 4 _ F [3:0] $end
$var reg 1 ` IQ $end
$var reg 4 a GS [3:0] $end
$var reg 1 b CE $end
$var reg 1 c NS $end
$var reg 3 d GD [2:0] $end
$var reg 1 e FS $end
$var reg 1 f RE $end
$var reg 33 g out [32:0] $end
$var reg 6 h count [5:0] $end
$upscope $end
$upscope $end
$upscope $end
$enddefinitions $end
#0
$dumpvars
0I
xJ
xK
xL
xM
xN
xO
xP
xQ
x(
x)
x*
x,
x+
x/
x.
x-
x0
x2
x1
x4
x3
x8
x7
x6
x5
x<
x;
x:
x9
x=
xA
x@
x?
x>
xB
xC
xF
xE
xD
xG
xH
xV
xW
xX
bx Y
bx Z
x[
bx \
bx ]
bx ^
bx _
x`
bx a
xb
xc
bx d
xe
xf
bx g
bx h
xU
0R
0S
0%
0&
1T
0$
0'
$end
#1000
0J
0K
0L
0M
0N
0O
0P
0Q
0(
0)
0*
0,
0+
0/
0.
0-
00
02
01
04
03
08
07
06
05
0<
0;
0:
09
0=
0A
0@
0?
0>
0B
0C
0F
0E
0D
0G
0H
0V
0W
0X
b0 Y
b0 Z
0[
b0 \
b0 ]
b0 ^
b0 _
0`
b0 a
0b
0c
b0 d
0e
0f
b0 g
b100001 h
0U
0T
#3000
1T
#4000
1R
#5000
b100000000000000000000000000000000 g
b100000 h
1S
#10000
0S
#14000
0R
#15000
b10000000000000000000000000000000 g
b11111 h
1S
#20000
0S
#24000
1R
#25000
b101000000000000000000000000000000 g
b11110 h
1S
#30000
0S
#34000
0R
#35000
b10100000000000000000000000000000 g
b11101 h
1S
#40000
0S
#45000
b1010000000000000000000000000000 g
b11100 h
1S
#50000
0S
#54000
1R
#55000
b100101000000000000000000000000000 g
b11011 h
1S
#60000
0S
#64000
0R
#65000
b10010100000000000000000000000000 g
b11010 h
1S
#70000
0S
#74000
1R
#75000
b101001010000000000000000000000000 g
b11001 h
1S
#80000
0S
#85000
b110100101000000000000000000000000 g
b11000 h
1S
#90000
0S
#94000
0R
#95000
b11010010100000000000000000000000 g
b10111 h
1S
#100000
0S
#104000
1R
#105000
b101101001010000000000000000000000 g
b10110 h
1S
#110000
0S
#115000
b110110100101000000000000000000000 g
b10101 h
1S
#120000
0S
#124000
0R
#125000
b11011010010100000000000000000000 g
b10100 h
1S
#130000
0S
#134000
1R
#135000
b101101101001010000000000000000000 g
b10011 h
1S
#140000
0S
#144000
0R
#145000
b10110110100101000000000000000000 g
b10010 h
1S
#150000
0S
#154000
1R
#155000
b101011011010010100000000000000000 g
b10001 h
1S
#160000
0S
#164000
0R
#165000
b10101101101001010000000000000000 g
b10000 h
1S
#170000
0S
#174000
1R
#175000
b101010110110100101000000000000000 g
b1111 h
1S
#180000
0S
#185000
b110101011011010010100000000000000 g
b1110 h
1S
#190000
0S
#194000
0R
#195000
b11010101101101001010000000000000 g
b1101 h
1S
#200000
0S
#205000
b1101010110110100101000000000000 g
b1100 h
1S
#210000
0S
#214000
1R
#215000
b100110101011011010010100000000000 g
b1011 h
1S
#220000
0S
#225000
b110011010101101101001010000000000 g
b1010 h
1S
#230000
0S
#234000
0R
#235000
b11001101010110110100101000000000 g
b1001 h
1S
#240000
0S
#245000
b1100110101011011010010100000000 g
b1000 h
1S
#250000
0S
#254000
1R
#255000
b100110011010101101101001010000000 g
b111 h
1S
#260000
0S
#264000
0R
#265000
b10011001101010110110100101000000 g
b110 h
1S
#270000
0S
#275000
b1001100110101011011010010100000 g
b101 h
1S
#280000
0S
#284000
1R
#285000
b100100110011010101101101001010000 g
b100 h
1S
#290000
0S
#295000
b110010011001101010110110100101000 g
b11 h
1S
#300000
0S
#305000
b111001001100110101011011010010100 g
b10 h
1S
#310000
0S
#314000
0R
#315000
b11100100110011010101101101001010 g
b1 h
1S
#320000
0S
#324000
1R
#325000
b101110010011001101010110110100101 g
b0 h
1S
#330000
1J
1L
1O
1Q
1(
1*
1,
1+
1/
12
13
17
16
1;
19
1=
1A
1@
1>
1C
1F
1H
1V
1X
b11 Y
b1 Z
b1 \
b10 ]
b110 ^
b1010 _
1`
b1011 a
1c
b1 d
1f
1U
0S
#335000
b110111001001100110101011011010010 g
b111111 h
0U
1S
#340000
0S
#345000
b111011100100110011010101101101001 g
b111110 h
1S
#350000
0S
#355000
b111101110010011001101010110110100 g
b111101 h
1S
#360000
0S
#365000
b111110111001001100110101011011010 g
b111100 h
1S
#370000
0S
#375000
b111111011100100110011010101101101 g
b111011 h
1S
#380000
0S
#384000
0J
0L
0O
0Q
0(
0*
0,
0+
0/
02
03
07
06
0;
09
0=
0A
0@
0>
0C
0F
0H
0V
0X
b0 Y
b0 Z
b0 \
b0 ]
b0 ^
b0 _
0`
b0 a
0c
b0 d
0f
b0 g
b100001 h
0T
#385000
1S
#386000
1T
#387000
0R
#390000
0S
#395000
b100000 h
1S
#397000
1R
#400000
0S
#405000
b100000000000000000000000000000000 g
b11111 h
1S
#407000
0R
#410000
0S
#415000
b10000000000000000000000000000000 g
b11110 h
1S
#417000
1R
#420000
0S
#425000
b101000000000000000000000000000000 g
b11101 h
1S
#430000
0S
#435000
b110100000000000000000000000000000 g
b11100 h
1S
#437000
0R
#440000
0S
#445000
b11010000000000000000000000000000 g
b11011 h
1S
#447000
1R
#450000
0S
#455000
b101101000000000000000000000000000 g
b11010 h
1S
#457000
0R
#460000
0S
#465000
b10110100000000000000000000000000 g
b11001 h
1S
#470000
0S
#475000
b1011010000000000000000000000000 g
b11000 h
1S
#477000
1R
#480000
0S
#485000
b100101101000000000000000000000000 g
b10111 h
1S
#487000
0R
#490000
0S
#495000
b10010110100000000000000000000000 g
b10110 h
1S
#500000
0S
#505000
b1001011010000000000000000000000 g
b10101 h
1S
#507000
1R
#510000
0S
#515000
b100100101101000000000000000000000 g
b10100 h
1S
#517000
0R
#520000
0S
#525000
b10010010110100000000000000000000 g
b10011 h
1S
#527000
1R
#530000
0S
#535000
b101001001011010000000000000000000 g
b10010 h
1S
#537000
0R
#540000
0S
#545000
b10100100101101000000000000000000 g
b10001 h
1S
#547000
1R
#550000
0S
#555000
b101010010010110100000000000000000 g
b10000 h
1S
#557000
0R
#560000
0S
#565000
b10101001001011010000000000000000 g
b1111 h
1S
#570000
0S
#575000
b1010100100101101000000000000000 g
b1110 h
1S
#577000
1R
#580000
0S
#585000
b100101010010010110100000000000000 g
b1101 h
1S
#590000
0S
#595000
b110010101001001011010000000000000 g
b1100 h
1S
#597000
0R
#600000
0S
#605000
b11001010100100101101000000000000 g
b1011 h
1S
#610000
0S
#615000
b1100101010010010110100000000000 g
b1010 h
1S
#617000
1R
#620000
0S
#625000
b100110010101001001011010000000000 g
b1001 h
1S
#630000
0S
#635000
b110011001010100100101101000000000 g
b1000 h
1S
#637000
0R
#640000
0S
#645000
b11001100101010010010110100000000 g
b111 h
1S
#647000
1R
#650000
0S
#655000
b101100110010101001001011010000000 g
b110 h
1S
#660000
0S
#665000
b110110011001010100100101101000000 g
b101 h
1S
#667000
0R
#670000
0S
#675000
b11011001100101010010010110100000 g
b100 h
1S
#680000
0S
#685000
b1101100110010101001001011010000 g
b11 h
1S
#690000
0S
#695000
b110110011001010100100101101000 g
b10 h
1S
#697000
1R
#700000
0S
#705000
b100011011001100101010010010110100 g
b1 h
1S
#707000
0R
#710000
0S
#715000
b10001101100110010101001001011010 g
b0 h
1S
#720000
1K
1M
1N
1P
1)
1.
1-
10
11
14
18
15
1<
1:
1?
1B
1E
1D
1G
1W
b110 Z
1[
b10 \
b1 ]
b1001 ^
b101 _
b100 a
1b
b110 d
1e
1U
0S
#725000
b1000110110011001010100100101101 g
b111111 h
0U
1S
#730000
0S
#735000
b100011011001100101010010010110 g
b111110 h
1S
#740000
0S
#745000
b10001101100110010101001001011 g
b111101 h
1S
#750000
0S
#755000
b1000110110011001010100100101 g
b111100 h
1S
