NNSENSE_FET_SEL/fet_dec.v
/**************************************
* Module: cur_dec
* Date:2017-08-22  
* Author: saul     
*
* Description: 4-bit decoder for current DAC
***************************************/

module fet_dec(in,out);

input [4:0]in;
output [31:0]out;

reg [31:0]out;

always @(in)
begin	
		out = (1 << in);
end
endmodule

NNSENSE_FET_SEL/fet_dec_tb.v
/**************************************
* Module: cur_dec_tb
* Date:2017-08-22  
* Author: saul     
*
* Description: 4-bit decoder for current DAC
***************************************/

module fet_dec_tb();

//nets to drive
reg [4:0]in;

//output wires
wire [31:0]out;

initial begin
    $dumpfile("fet_dec.vcd");
    $dumpvars(0,my_fet_dec);
    
    in = 0;
    #10 in = in + 1;
    #10 in = in + 1;
    #10 in = in + 1;
    #10 in = in + 1;
    #10 in = in + 1;
    #10 in = in + 1;
    #10 in = in + 1;
    #10 in = in + 1;
    #10 in = in + 1;
    #10 in = in + 1;
    #10 in = in + 1;
    #10 in = in + 1;
    #10 in = in + 1;
    #10 in = in + 1;
    #10 in = in + 1;
    #10 in = in + 1;
    #10 in = in + 1;
    #10 in = in + 1;
    #10 in = in + 1;
    #10 in = in + 1;
    #10 in = in + 1;
    #10 in = in + 1;
    #10 in = in + 1;
    #10 in = in + 1;
    #10 in = in + 1;
    #10 in = in + 1;
    #10 in = in + 1;
    #10 in = in + 1;
    #10 in = in + 1;
    #10 in = in + 1;
    #10 in = in + 1;
    #10 in = in + 1;
    #10 in = in + 1;
    #10 in = in + 1;
        
    #10 $finish;
end

fet_dec my_fet_dec(in,out);


endmodule

NNSENSE_FET_SEL/fet_dec.vcd
$date
	Tue Aug 22 21:31:58 2017
$end
$version
	Icarus Verilog
$end
$timescale
	1s
$end
$scope module fet_dec_tb $end
$scope module my_fet_dec $end
$var wire 5 ! in [4:0] $end
$var reg 32 " out [31:0] $end
$upscope $end
$upscope $end
$enddefinitions $end
#0
$dumpvars
b1 "
b0 !
$end
#10
b10 "
b1 !
#20
b100 "
b10 !
#30
b1000 "
b11 !
#40
b10000 "
b100 !
#50
b100000 "
b101 !
#60
b1000000 "
b110 !
#70
b10000000 "
b111 !
#80
b100000000 "
b1000 !
#90
b1000000000 "
b1001 !
#100
b10000000000 "
b1010 !
#110
b100000000000 "
b1011 !
#120
b1000000000000 "
b1100 !
#130
b10000000000000 "
b1101 !
#140
b100000000000000 "
b1110 !
#150
b1000000000000000 "
b1111 !
#160
b10000000000000000 "
b10000 !
#170
b100000000000000000 "
b10001 !
#180
b1000000000000000000 "
b10010 !
#190
b10000000000000000000 "
b10011 !
#200
b100000000000000000000 "
b10100 !
#210
b1000000000000000000000 "
b10101 !
#220
b10000000000000000000000 "
b10110 !
#230
b100000000000000000000000 "
b10111 !
#240
b1000000000000000000000000 "
b11000 !
#250
b10000000000000000000000000 "
b11001 !
#260
b100000000000000000000000000 "
b11010 !
#270
b1000000000000000000000000000 "
b11011 !
#280
b10000000000000000000000000000 "
b11100 !
#290
b100000000000000000000000000000 "
b11101 !
#300
b1000000000000000000000000000000 "
b11110 !
#310
b10000000000000000000000000000000 "
b11111 !
#320
b1 "
b0 !
#330
b10 "
b1 !
#340
b100 "
b10 !
