ASKA_NPG/aska_npg.v
/********************************/
/* aska_npg.v                   */
/*                              */
/* Author: Saul Rodriguez       */  
/* Date: 2024-05-17             */
/********************************/

module aska_npg (
    input clk,
    input resetn,
    input [11:0] freq,
    input [2:0] phaseDuration,
    input [5:0] ramp,
    input [3:0] up,
    input [3:0] down,
    input enable,
    output reg [3:0] up_switches,
    output reg [3:0] down_switches);


/************************************/
/*  Frequency reference generator   */
/************************************/

reg [5:0]freq_count;
wire freq_count_ready;

always @(posedge clk or negedge resetn) begin
    if (resetn == 1'b0) begin
        freq_count <= 11'b0;
        //freq_count_ready <= 1'b0;

    end else begin
        if (enable) begin
            freq_count <= freq_count + 1;

            if (freq_count == freq) begin
                freq_count <= 11'b0;
            end
        end
    end
end

assign freq_count_ready = (freq_count == freq) ? 1'b1 : 1'b0;

/*********************/
/*  Pulse generator  */
/*********************/

//Positive phase logic

reg [2:0] phase_up_count;
reg phase_up_state;
wire phase_up_count_ready;

always @(posedge clk or negedge resetn) begin
    if (resetn == 1'b0) begin
        phase_up_count <= 3'b0;        
        phase_up_state <= 1'b0;

    end else begin
        if (freq_count_ready) begin
            phase_up_state <= 1'b1;
            phase_up_count <= phase_up_count + 1;
        end else if (phase_up_state == 1'b1) begin
            phase_up_count <= phase_up_count + 1;

            if (phase_up_count == phaseDuration) begin
                phase_up_count <= 3'b0;
                phase_up_state <= 1'b0;
            end
        end
    end
end

assign phase_up_count_ready = (phase_up_count == phaseDuration) ? 1'b1 : 1'b0;

// Pause 1 cycle
reg phase_pause_ready;

always @(posedge clk or negedge resetn) begin
    if (resetn == 1'b0) begin
        phase_pause_ready <= 1'b0;

    end else begin
        if (phase_up_count_ready == 1'b1) begin
            phase_pause_ready <= 1'b1;    
        end else if (phase_pause_ready == 1'b1) begin
            phase_pause_ready <= 1'b0;
        end
    end
end

//Negative phase logic

reg [2:0] phase_down_count;
reg phase_down_state;
wire phase_down_count_ready;

always @(posedge clk or negedge resetn) begin
    if (resetn == 1'b0) begin
        phase_down_count <= 3'b0;        
        phase_down_state <= 1'b0;

    end else begin
        if (phase_pause_ready) begin
            phase_down_state <= 1'b1;
            phase_down_count <= phase_down_count + 1;
        end else if (phase_down_state == 1'b1) begin
            phase_down_count <= phase_down_count + 1;

            if (phase_down_count == phaseDuration) begin
                phase_down_count <= 3'b0;
                phase_down_state <= 1'b0;
            end
        end
    end
end

assign phase_down_count_ready = (phase_down_count == phaseDuration) ? 1'b1 : 1'b0;

// Control enable signals for H bridge UP and DOWN switches

always @(*) begin
    if (phase_up_state) begin
        up_switches = up;
        down_switches = down;
    end else if (phase_down_state) begin
        up_switches = down;
        down_switches = up;    
    end else begin 
        up_switches = 4'b0;        
        down_switches = 4'b0;        
    end  
end

    
endmodule

ASKA_NPG/aska_npg_tb.v
`include "aska_npg.v"

`timescale 1 ns/ 1ps

module aska_npg_stimulus(
    output reg clk,
    output reg resetn,
    output reg [11:0] freq,
    output reg [2:0] phaseDuration,
    output reg [5:0] ramp,
    output reg [3:0] up,
    output reg [3:0] down,
    output reg enable);

// Clock generation
parameter CLK_DELAY = 25000;   // 20 kHz
always #(CLK_DELAY) clk = ~clk;


// Instantiation of UUT
aska_npg UUT (
    .clk(clk),
    .resetn(resetn),
    .freq(freq),
    .phaseDuration(phaseDuration),
    .ramp(ramp),
    .up(up),
    .down(down),
    .enable(enable)
);

// 

initial begin
    // Required for EDA Playground
	$dumpfile("dump.vcd"); 
	$dumpvars;
	$display("************************************");
	$display("Test ASKA NPG");
    
    //start
    clk = 0;
    resetn = 1;
    enable = 0;
    freq = 49; 
    phaseDuration = 3;
    ramp = 0;
    up = 4;
    down = 1;

    //reset async
    #(5*CLK_DELAY);
    resetn = 0;
    #(5*CLK_DELAY);
    resetn = 1;

    //enable
    enable = 1;






    #(500*CLK_DELAY); 
    $display("************************************");
	$finish;

end



endmodule

ASKA_NPG/dump.vcd
$date
	Fri May 17 21:00:47 2024
$end
$version
	Icarus Verilog
$end
$timescale
	1ps
$end
$scope module aska_npg_stimulus $end
$var parameter 32 ! CLK_DELAY $end
$var reg 1 " clk $end
$var reg 4 # down [3:0] $end
$var reg 1 $ enable $end
$var reg 12 % freq [11:0] $end
$var reg 3 & phaseDuration [2:0] $end
$var reg 6 ' ramp [5:0] $end
$var reg 1 ( resetn $end
$var reg 4 ) up [3:0] $end
$scope module UUT $end
$var wire 1 " clk $end
$var wire 4 * down [3:0] $end
$var wire 1 $ enable $end
$var wire 12 + freq [11:0] $end
$var wire 3 , phaseDuration [2:0] $end
$var wire 6 - ramp [5:0] $end
$var wire 1 ( resetn $end
$var wire 4 . up [3:0] $end
$var wire 1 / phase_up_count_ready $end
$var wire 1 0 phase_down_count_ready $end
$var wire 1 1 freq_count_ready $end
$var reg 4 2 down_switches [3:0] $end
$var reg 6 3 freq_count [5:0] $end
$var reg 3 4 phase_down_count [2:0] $end
$var reg 1 5 phase_down_state $end
$var reg 1 6 phase_pause_ready $end
$var reg 3 7 phase_up_count [2:0] $end
$var reg 1 8 phase_up_state $end
$var reg 4 9 up_switches [3:0] $end
$upscope $end
$upscope $end
$enddefinitions $end
$comment Show the parameter values. $end
$dumpall
b110000110101000 !
$end
#0
$dumpvars
b0 9
x8
bx 7
x6
x5
bx 4
bx 3
b0 2
x1
x0
x/
b100 .
b0 -
b11 ,
b110001 +
b1 *
b100 )
1(
b0 '
b11 &
b110001 %
0$
b1 #
0"
$end
#25000000
1"
#50000000
0"
#75000000
1"
#100000000
0"
#125000000
01
0/
00
b0 3
08
b0 7
06
05
b0 4
1"
0(
#150000000
0"
#175000000
1"
#200000000
0"
#225000000
1"
#250000000
0"
1$
1(
#275000000
b1 3
1"
#300000000
0"
#325000000
b10 3
1"
#350000000
0"
#375000000
b11 3
1"
#400000000
0"
#425000000
b100 3
1"
#450000000
0"
#475000000
b101 3
1"
#500000000
0"
#525000000
b110 3
1"
#550000000
0"
#575000000
b111 3
1"
#600000000
0"
#625000000
b1000 3
1"
#650000000
0"
#675000000
b1001 3
1"
#700000000
0"
#725000000
b1010 3
1"
#750000000
0"
#775000000
b1011 3
1"
#800000000
0"
#825000000
b1100 3
1"
#850000000
0"
#875000000
b1101 3
1"
#900000000
0"
#925000000
b1110 3
1"
#950000000
0"
#975000000
b1111 3
1"
#1000000000
0"
#1025000000
b10000 3
1"
#1050000000
0"
#1075000000
b10001 3
1"
#1100000000
0"
#1125000000
b10010 3
1"
#1150000000
0"
#1175000000
b10011 3
1"
#1200000000
0"
#1225000000
b10100 3
1"
#1250000000
0"
#1275000000
b10101 3
1"
#1300000000
0"
#1325000000
b10110 3
1"
#1350000000
0"
#1375000000
b10111 3
1"
#1400000000
0"
#1425000000
b11000 3
1"
#1450000000
0"
#1475000000
b11001 3
1"
#1500000000
0"
#1525000000
b11010 3
1"
#1550000000
0"
#1575000000
b11011 3
1"
#1600000000
0"
#1625000000
b11100 3
1"
#1650000000
0"
#1675000000
b11101 3
1"
#1700000000
0"
#1725000000
b11110 3
1"
#1750000000
0"
#1775000000
b11111 3
1"
#1800000000
0"
#1825000000
b100000 3
1"
#1850000000
0"
#1875000000
b100001 3
1"
#1900000000
0"
#1925000000
b100010 3
1"
#1950000000
0"
#1975000000
b100011 3
1"
#2000000000
0"
#2025000000
b100100 3
1"
#2050000000
0"
#2075000000
b100101 3
1"
#2100000000
0"
#2125000000
b100110 3
1"
#2150000000
0"
#2175000000
b100111 3
1"
#2200000000
0"
#2225000000
b101000 3
1"
#2250000000
0"
#2275000000
b101001 3
1"
#2300000000
0"
#2325000000
b101010 3
1"
#2350000000
0"
#2375000000
b101011 3
1"
#2400000000
0"
#2425000000
b101100 3
1"
#2450000000
0"
#2475000000
b101101 3
1"
#2500000000
0"
#2525000000
b101110 3
1"
#2550000000
0"
#2575000000
b101111 3
1"
#2600000000
0"
#2625000000
b110000 3
1"
#2650000000
0"
#2675000000
11
b110001 3
1"
#2700000000
0"
#2725000000
01
b1 2
b100 9
b0 3
b1 7
18
1"
#2750000000
0"
#2775000000
b10 7
b1 3
1"
#2800000000
0"
#2825000000
1/
b10 3
b11 7
1"
#2850000000
0"
#2875000000
b0 2
b0 9
0/
16
08
b0 7
b11 3
1"
#2900000000
0"
#2925000000
b100 2
b1 9
b100 3
06
b1 4
15
1"
#2950000000
0"
#2975000000
b10 4
b101 3
1"
#3000000000
0"
#3025000000
10
b110 3
b11 4
1"
#3050000000
0"
#3075000000
b0 2
b0 9
00
05
b0 4
b111 3
1"
#3100000000
0"
#3125000000
b1000 3
1"
#3150000000
0"
#3175000000
b1001 3
1"
#3200000000
0"
#3225000000
b1010 3
1"
#3250000000
0"
#3275000000
b1011 3
1"
#3300000000
0"
#3325000000
b1100 3
1"
#3350000000
0"
#3375000000
b1101 3
1"
#3400000000
0"
#3425000000
b1110 3
1"
#3450000000
0"
#3475000000
b1111 3
1"
#3500000000
0"
#3525000000
b10000 3
1"
#3550000000
0"
#3575000000
b10001 3
1"
#3600000000
0"
#3625000000
b10010 3
1"
#3650000000
0"
#3675000000
b10011 3
1"
#3700000000
0"
#3725000000
b10100 3
1"
#3750000000
0"
#3775000000
b10101 3
1"
#3800000000
0"
#3825000000
b10110 3
1"
#3850000000
0"
#3875000000
b10111 3
1"
#3900000000
0"
#3925000000
b11000 3
1"
#3950000000
0"
#3975000000
b11001 3
1"
#4000000000
0"
#4025000000
b11010 3
1"
#4050000000
0"
#4075000000
b11011 3
1"
#4100000000
0"
#4125000000
b11100 3
1"
#4150000000
0"
#4175000000
b11101 3
1"
#4200000000
0"
#4225000000
b11110 3
1"
#4250000000
0"
#4275000000
b11111 3
1"
#4300000000
0"
#4325000000
b100000 3
1"
#4350000000
0"
#4375000000
b100001 3
1"
#4400000000
0"
#4425000000
b100010 3
1"
#4450000000
0"
#4475000000
b100011 3
1"
#4500000000
0"
#4525000000
b100100 3
1"
#4550000000
0"
#4575000000
b100101 3
1"
#4600000000
0"
#4625000000
b100110 3
1"
#4650000000
0"
#4675000000
b100111 3
1"
#4700000000
0"
#4725000000
b101000 3
1"
#4750000000
0"
#4775000000
b101001 3
1"
#4800000000
0"
#4825000000
b101010 3
1"
#4850000000
0"
#4875000000
b101011 3
1"
#4900000000
0"
#4925000000
b101100 3
1"
#4950000000
0"
#4975000000
b101101 3
1"
#5000000000
0"
#5025000000
b101110 3
1"
#5050000000
0"
#5075000000
b101111 3
1"
#5100000000
0"
#5125000000
b110000 3
1"
#5150000000
0"
#5175000000
11
b110001 3
1"
#5200000000
0"
#5225000000
01
b1 2
b100 9
b0 3
b1 7
18
1"
#5250000000
0"
#5275000000
b10 7
b1 3
1"
#5300000000
0"
#5325000000
1/
b10 3
b11 7
1"
#5350000000
0"
#5375000000
b0 2
b0 9
0/
16
08
b0 7
b11 3
1"
#5400000000
0"
#5425000000
b100 2
b1 9
b100 3
06
b1 4
15
1"
#5450000000
0"
#5475000000
b10 4
b101 3
1"
#5500000000
0"
#5525000000
10
b110 3
b11 4
1"
#5550000000
0"
#5575000000
b0 2
b0 9
00
05
b0 4
b111 3
1"
#5600000000
0"
#5625000000
b1000 3
1"
#5650000000
0"
#5675000000
b1001 3
1"
#5700000000
0"
#5725000000
b1010 3
1"
#5750000000
0"
#5775000000
b1011 3
1"
#5800000000
0"
#5825000000
b1100 3
1"
#5850000000
0"
#5875000000
b1101 3
1"
#5900000000
0"
#5925000000
b1110 3
1"
#5950000000
0"
#5975000000
b1111 3
1"
#6000000000
0"
#6025000000
b10000 3
1"
#6050000000
0"
#6075000000
b10001 3
1"
#6100000000
0"
#6125000000
b10010 3
1"
#6150000000
0"
#6175000000
b10011 3
1"
#6200000000
0"
#6225000000
b10100 3
1"
#6250000000
0"
#6275000000
b10101 3
1"
#6300000000
0"
#6325000000
b10110 3
1"
#6350000000
0"
#6375000000
b10111 3
1"
#6400000000
0"
#6425000000
b11000 3
1"
#6450000000
0"
#6475000000
b11001 3
1"
#6500000000
0"
#6525000000
b11010 3
1"
#6550000000
0"
#6575000000
b11011 3
1"
#6600000000
0"
#6625000000
b11100 3
1"
#6650000000
0"
#6675000000
b11101 3
1"
#6700000000
0"
#6725000000
b11110 3
1"
#6750000000
0"
#6775000000
b11111 3
1"
#6800000000
0"
#6825000000
b100000 3
1"
#6850000000
0"
#6875000000
b100001 3
1"
#6900000000
0"
#6925000000
b100010 3
1"
#6950000000
0"
#6975000000
b100011 3
1"
#7000000000
0"
#7025000000
b100100 3
1"
#7050000000
0"
#7075000000
b100101 3
1"
#7100000000
0"
#7125000000
b100110 3
1"
#7150000000
0"
#7175000000
b100111 3
1"
#7200000000
0"
#7225000000
b101000 3
1"
#7250000000
0"
#7275000000
b101001 3
1"
#7300000000
0"
#7325000000
b101010 3
1"
#7350000000
0"
#7375000000
b101011 3
1"
#7400000000
0"
#7425000000
b101100 3
1"
#7450000000
0"
#7475000000
b101101 3
1"
#7500000000
0"
#7525000000
b101110 3
1"
#7550000000
0"
#7575000000
b101111 3
1"
#7600000000
0"
#7625000000
b110000 3
1"
#7650000000
0"
#7675000000
11
b110001 3
1"
#7700000000
0"
#7725000000
01
b1 2
b100 9
b0 3
b1 7
18
1"
#7750000000
0"
#7775000000
b10 7
b1 3
1"
#7800000000
0"
#7825000000
1/
b10 3
b11 7
1"
#7850000000
0"
#7875000000
b0 2
b0 9
0/
16
08
b0 7
b11 3
1"
#7900000000
0"
#7925000000
b100 2
b1 9
b100 3
06
b1 4
15
1"
#7950000000
0"
#7975000000
b10 4
b101 3
1"
#8000000000
0"
#8025000000
10
b110 3
b11 4
1"
#8050000000
0"
#8075000000
b0 2
b0 9
00
05
b0 4
b111 3
1"
#8100000000
0"
#8125000000
b1000 3
1"
#8150000000
0"
#8175000000
b1001 3
1"
#8200000000
0"
#8225000000
b1010 3
1"
#8250000000
0"
#8275000000
b1011 3
1"
#8300000000
0"
#8325000000
b1100 3
1"
#8350000000
0"
#8375000000
b1101 3
1"
#8400000000
0"
#8425000000
b1110 3
1"
#8450000000
0"
#8475000000
b1111 3
1"
#8500000000
0"
#8525000000
b10000 3
1"
#8550000000
0"
#8575000000
b10001 3
1"
#8600000000
0"
#8625000000
b10010 3
1"
#8650000000
0"
#8675000000
b10011 3
1"
#8700000000
0"
#8725000000
b10100 3
1"
#8750000000
0"
#8775000000
b10101 3
1"
#8800000000
0"
#8825000000
b10110 3
1"
#8850000000
0"
#8875000000
b10111 3
1"
#8900000000
0"
#8925000000
b11000 3
1"
#8950000000
0"
#8975000000
b11001 3
1"
#9000000000
0"
#9025000000
b11010 3
1"
#9050000000
0"
#9075000000
b11011 3
1"
#9100000000
0"
#9125000000
b11100 3
1"
#9150000000
0"
#9175000000
b11101 3
1"
#9200000000
0"
#9225000000
b11110 3
1"
#9250000000
0"
#9275000000
b11111 3
1"
#9300000000
0"
#9325000000
b100000 3
1"
#9350000000
0"
#9375000000
b100001 3
1"
#9400000000
0"
#9425000000
b100010 3
1"
#9450000000
0"
#9475000000
b100011 3
1"
#9500000000
0"
#9525000000
b100100 3
1"
#9550000000
0"
#9575000000
b100101 3
1"
#9600000000
0"
#9625000000
b100110 3
1"
#9650000000
0"
#9675000000
b100111 3
1"
#9700000000
0"
#9725000000
b101000 3
1"
#9750000000
0"
#9775000000
b101001 3
1"
#9800000000
0"
#9825000000
b101010 3
1"
#9850000000
0"
#9875000000
b101011 3
1"
#9900000000
0"
#9925000000
b101100 3
1"
#9950000000
0"
#9975000000
b101101 3
1"
#10000000000
0"
#10025000000
b101110 3
1"
#10050000000
0"
#10075000000
b101111 3
1"
#10100000000
0"
#10125000000
b110000 3
1"
#10150000000
0"
#10175000000
11
b110001 3
1"
#10200000000
0"
#10225000000
01
b1 2
b100 9
b0 3
b1 7
18
1"
#10250000000
0"
#10275000000
b10 7
b1 3
1"
#10300000000
0"
#10325000000
1/
b10 3
b11 7
1"
#10350000000
0"
#10375000000
b0 2
b0 9
0/
16
08
b0 7
b11 3
1"
#10400000000
0"
#10425000000
b100 2
b1 9
b100 3
06
b1 4
15
1"
#10450000000
0"
#10475000000
b10 4
b101 3
1"
#10500000000
0"
#10525000000
10
b110 3
b11 4
1"
#10550000000
0"
#10575000000
b0 2
b0 9
00
05
b0 4
b111 3
1"
#10600000000
0"
#10625000000
b1000 3
1"
#10650000000
0"
#10675000000
b1001 3
1"
#10700000000
0"
#10725000000
b1010 3
1"
#10750000000
0"
#10775000000
b1011 3
1"
#10800000000
0"
#10825000000
b1100 3
1"
#10850000000
0"
#10875000000
b1101 3
1"
#10900000000
0"
#10925000000
b1110 3
1"
#10950000000
0"
#10975000000
b1111 3
1"
#11000000000
0"
#11025000000
b10000 3
1"
#11050000000
0"
#11075000000
b10001 3
1"
#11100000000
0"
#11125000000
b10010 3
1"
#11150000000
0"
#11175000000
b10011 3
1"
#11200000000
0"
#11225000000
b10100 3
1"
#11250000000
0"
#11275000000
b10101 3
1"
#11300000000
0"
#11325000000
b10110 3
1"
#11350000000
0"
#11375000000
b10111 3
1"
#11400000000
0"
#11425000000
b11000 3
1"
#11450000000
0"
#11475000000
b11001 3
1"
#11500000000
0"
#11525000000
b11010 3
1"
#11550000000
0"
#11575000000
b11011 3
1"
#11600000000
0"
#11625000000
b11100 3
1"
#11650000000
0"
#11675000000
b11101 3
1"
#11700000000
0"
#11725000000
b11110 3
1"
#11750000000
0"
#11775000000
b11111 3
1"
#11800000000
0"
#11825000000
b100000 3
1"
#11850000000
0"
#11875000000
b100001 3
1"
#11900000000
0"
#11925000000
b100010 3
1"
#11950000000
0"
#11975000000
b100011 3
1"
#12000000000
0"
#12025000000
b100100 3
1"
#12050000000
0"
#12075000000
b100101 3
1"
#12100000000
0"
#12125000000
b100110 3
1"
#12150000000
0"
#12175000000
b100111 3
1"
#12200000000
0"
#12225000000
b101000 3
1"
#12250000000
0"
#12275000000
b101001 3
1"
#12300000000
0"
#12325000000
b101010 3
1"
#12350000000
0"
#12375000000
b101011 3
1"
#12400000000
0"
#12425000000
b101100 3
1"
#12450000000
0"
#12475000000
b101101 3
1"
#12500000000
0"
#12525000000
b101110 3
1"
#12550000000
0"
#12575000000
b101111 3
1"
#12600000000
0"
#12625000000
b110000 3
1"
#12650000000
0"
#12675000000
11
b110001 3
1"
#12700000000
0"
#12725000000
01
b1 2
b100 9
b0 3
b1 7
18
1"
