I2c/I2C.v
/**************************************
* Module: I2C
* Date:2015-06-21  
* Author: saul     
*
* Description: I2C slave
***************************************/


module  I2C(
SDA,
SDAout,
SCL,
RSTN
);

//inout SDA;
input SDA;
output SDAout;
input SCL;
input RSTN; 


wire RST;

assign RST = ~RSTN;

//Start Detection
reg  start_detect;
reg  start_resetter;
wire start_rst = RST | start_resetter;

always @ (posedge start_rst or negedge SDA)
begin
        if (start_rst)
                start_detect <= 1'b0;
        else
                start_detect <= SCL;
end

always @ (posedge RST or posedge SCL)
begin
        if (RST)
                start_resetter <= 1'b0;
        else
                start_resetter <= start_detect;
end

//Stop Detection
reg             stop_detect;
reg             stop_resetter;
wire            stop_rst = RST | stop_resetter;

always @ (posedge stop_rst or posedge SDA)
begin   
        if (stop_rst)
                stop_detect <= 1'b0;
        else
                stop_detect <= SCL;
end

always @ (posedge RST or posedge SCL)
begin   
        if (RST)
                stop_resetter <= 1'b0;
        else
                stop_resetter <= stop_detect;
end

// Counter
reg [3:0] bit_counter;

wire  lsb_bit = (bit_counter == 4'h7) && !start_detect;
wire  ack_bit = (bit_counter == 4'h8) && !start_detect; // 8 bits + ack

always @ (negedge SCL)
begin
        if (ack_bit || start_detect)
                bit_counter <= 4'h0;
        else
                bit_counter <= bit_counter + 4'h1;
end

// Latching the data 
reg [7:0] input_shift;

parameter [6:0] device_address = 7'h55;
wire            address_detect = (input_shift[7:1] == device_address);
wire            read_write_bit = input_shift[0];

always @ (posedge RST or posedge SCL)
        if (!ack_bit)
                input_shift <= {input_shift[6:0], SDA};

// Detection of Master Acknowledgement
reg master_ack;

always @ (posedge SCL)
        if (ack_bit)
                master_ack <= ~SDA;

// State Machine
// States change only whan ack_bit is asserted!
 
parameter [2:0] STATE_IDLE      = 3'h0,
                STATE_DEV_ADDR  = 3'h1,
                STATE_READ      = 3'h2,
                STATE_IDX_PTR   = 3'h3,
                STATE_WRITE     = 3'h4;

reg [2:0]       state;
wire            write_strobe = (state == STATE_WRITE) && ack_bit;

always @ (posedge RST or negedge SCL)
begin
        if (RST)
                state <= STATE_IDLE;
        else if (start_detect)
                state <= STATE_DEV_ADDR;
        else if (ack_bit)
        begin
                case (state)
                STATE_IDLE:
                        state <= STATE_IDLE;

                STATE_DEV_ADDR:
                        if (!address_detect)
                                state <= STATE_IDLE;
                        else if (read_write_bit)
                                state <= STATE_READ;
                        else
                                state <= STATE_IDX_PTR;

                STATE_READ:
                        if (master_ack)
                                state <= STATE_READ;
                        else
                                state <= STATE_IDLE;

                STATE_IDX_PTR:
                        state <= STATE_WRITE;

                STATE_WRITE:
                        state <= STATE_WRITE;
                endcase
        end
end

//Index pointer
// Only changes on ack_bit!

reg [7:0] index_pointer;

always @ (posedge RST or negedge SCL)
begin
        if (RST)
                index_pointer <= 8'h00;
        else if (stop_detect)
                index_pointer <= 8'h00;
        else if (ack_bit)
        begin
                if (state == STATE_IDX_PTR)
                        index_pointer <= input_shift;
                else
                        index_pointer <= index_pointer + 8'h01;
        end
end

//Register writes
reg [7:0]       reg_00;
reg [7:0]       reg_01;
reg [7:0]       reg_02;
reg [7:0]       reg_03;

/*
always @ (posedge RST or negedge SCL)
begin
        if (RST)
                reg_03 <= 8'h00;
        else if (write_strobe && (index_pointer == 8'h03))
                reg_03 <= input_shift;
end
*/

always @ (posedge RST or negedge SCL)
begin
        if (RST) begin
                reg_00 <= 8'h00;
                reg_01 <= 8'h00;
                reg_02 <= 8'h00;
                reg_03 <= 8'h00;
        end
        else if (write_strobe) begin
            case (index_pointer)
                8'h00: reg_00 <= input_shift;
                8'h01: reg_01 <= input_shift;
                8'h02: reg_02 <= input_shift;
                8'h03: reg_03 <= input_shift;                
            endcase
        end
          
end

// Read requests
reg [7:0]       output_shift;

always @ (negedge SCL)
begin   
        if (lsb_bit)
        begin   
                case (index_pointer)
                8'h00: output_shift <= reg_00;
                8'h01: output_shift <= reg_01;
                8'h02: output_shift <= reg_02;
                8'h03: output_shift <= reg_03;
                // ... and so on ...

                endcase
        end
        else
                output_shift <= {output_shift[6:0], 1'b0};
end

//output control

reg             output_control;
assign          SDAout = output_control ? 1'b1 : 1'b0;

always @ (posedge RST or negedge SCL)
begin   
        if (RST)
                output_control <= 1'b1;
                
        else if (start_detect)
                output_control <= 1'b1;
        else if (lsb_bit)
        begin   
                output_control <=
                    !(((state == STATE_DEV_ADDR) && address_detect) ||
                      (state == STATE_IDX_PTR) ||
                      (state == STATE_WRITE));
        end
        else if (ack_bit)
        begin
                // Deliver the first bit of the next slave-to-master
                // transfer, if applicable.
                if (((state == STATE_READ) && master_ack) ||
                    ((state == STATE_DEV_ADDR) &&
                        address_detect && read_write_bit))
                        output_control <= output_shift[7];
                else
                        output_control <= 1'b1;
        end
        else if (state == STATE_READ)
                output_control <= output_shift[7];
        else
                output_control <= 1'b1;
end


endmodule

I2c/top.v
/*
* top.v 
*
* SW1
*
*
*/



module top(SW0,SW1,SW2,SW3);

input  SW0; //SDA
output SW1; //SDA_tri
input  SW2; //SCL
input  SW3; //RESETN

//wire SDA_aux;

wire SDA_out;

tri_buf tri_buf1(.in(SDA_out),.enable(SDA_out),.out(SW1));

I2C my_I2C(.SDA(SW0),.SDAout(SDA_out),.SCL(SW2),.RSTN(SW3));

endmodule


/*
*                 enable        _____
*               |\|            |     |
*       in _____| \____ out ___|GPIO |
*               | /            |     |
*               |/          <--|_____|
*                               
*/

module tri_buf(in,enable,out);
input in, enable;
inout out;

//enable == 1 then GPIO is input
//enable == 0 then GPIO is output
 
assign out = enable ? 1'bz : in; 

endmodule

I2c/I2C_f_tb.v
/**************************************
* Module: I2C_tb
* Date:2015-06-21  
* Author: saul     
*
* Description: 

 

***************************************/
module  I2C_f_tb(
);

//Nets to drive
reg SCL;
reg RSTN;

//reg SDA;
//reg RST;

wire SDAW;

reg SDA;

assign SDAW = (~SDA) ? 1'bz : 1'b0;

//Output wires
wire SDAout;

initial begin
    $dumpfile("I2C.vcd");
    $dumpvars(0,my_top);
    
    RSTN = 1;
    SCL = 1;
    SDA = 1;
    
    #2 RSTN = 0;
    #2 RSTN = 1;
    #40;
    
    `include "write_i2c.inc"
    #40;
    `include "write_i2c_2.inc"
    #40;
    `include "read_i2c.inc"
   
   
   /*
    #6 SDA = 0; // START
    #10 SCL = 0;
    #10 SCL = 1;
    #10 SCL = 0;
    #40 SCL = 1;
    #4 SDA = 1;
    */
    
    #50 $finish;
end

/*
always begin
    #20 SCL = ~ SCL;
end
*/

//I2C my_I2C(SDA,SDAout,SCL,RSTN);
top my_top(.SW0(SDA),.SW1(SDAout),.SW2(SCL),.SW3(RSTN));


endmodule

I2c/I2C.vcd
$date
	Thu Nov 10 14:35:03 2016
$end
$version
	Icarus Verilog
$end
$timescale
	1s
$end
$scope module I2C_f_tb $end
$scope module my_top $end
$var wire 1 ! SDA_out $end
$var wire 1 " SW0 $end
$var wire 1 # SW1 $end
$var wire 1 $ SW2 $end
$var wire 1 % SW3 $end
$scope module tri_buf1 $end
$var wire 1 ! enable $end
$var wire 1 ! in $end
$var wire 1 # out $end
$upscope $end
$scope module my_I2C $end
$var wire 1 & RST $end
$var wire 1 % RSTN $end
$var wire 1 $ SCL $end
$var wire 1 " SDA $end
$var wire 1 ! SDAout $end
$var wire 1 ' ack_bit $end
$var wire 1 ( address_detect $end
$var wire 1 ) lsb_bit $end
$var wire 1 * read_write_bit $end
$var wire 1 + start_rst $end
$var wire 1 , stop_rst $end
$var wire 1 - write_strobe $end
$var reg 4 . bit_counter [3:0] $end
$var reg 8 / index_pointer [7:0] $end
$var reg 8 0 input_shift [7:0] $end
$var reg 1 1 master_ack $end
$var reg 1 2 output_control $end
$var reg 8 3 output_shift [7:0] $end
$var reg 8 4 reg_00 [7:0] $end
$var reg 8 5 reg_01 [7:0] $end
$var reg 8 6 reg_02 [7:0] $end
$var reg 8 7 reg_03 [7:0] $end
$var reg 1 8 start_detect $end
$var reg 1 9 start_resetter $end
$var reg 3 : state [2:0] $end
$var reg 1 ; stop_detect $end
$var reg 1 < stop_resetter $end
$upscope $end
$upscope $end
$upscope $end
$enddefinitions $end
#0
$dumpvars
x<
1;
bx :
x9
x8
bx 7
bx 6
bx 5
bx 4
bx 3
x2
x1
bx 0
bx /
bx .
x-
x,
x+
x*
x)
x(
x'
0&
1%
1$
x#
1"
x!
$end
#2
z#
0-
1!
08
0;
b0 :
b0 /
b0 7
b0 6
b0 5
b0 4
12
0<
09
1+
1,
1&
0%
#4
0+
0,
0&
1%
#50
0)
0'
18
0"
#60
b1 :
b0 .
bx0 3
0$
#62
1"
#72
08
1+
1*
19
bx1 0
1$
#82
bx00 3
b1 .
0$
#84
0"
#94
0*
0+
bx10 0
09
1$
#104
b10 .
bx000 3
0$
#106
1"
#116
0(
1*
bx101 0
1$
#126
bx0000 3
b11 .
0$
#128
0"
#138
x(
0*
bx1010 0
1$
#148
b100 .
bx00000 3
0$
#150
1"
#160
0(
1*
bx10101 0
1$
#170
bx000000 3
b101 .
0$
#172
0"
#182
x(
0*
bx101010 0
1$
#192
b110 .
bx0000000 3
0$
#194
1"
#204
0(
1*
bx1010101 0
1$
#214
1)
b0 3
b111 .
0$
#216
0"
#226
1(
0*
b10101010 0
1$
#236
0#
0!
0)
1'
02
b1000 .
0$
#246
11
1$
#256
z#
1!
0'
b11 :
b1 /
12
b0 .
0$
#268
0(
b1010100 0
1$
#278
b1 .
0$
#290
b10101000 0
1$
#300
b10 .
0$
#312
b1010000 0
1$
#322
b11 .
0$
#334
b10100000 0
1$
#344
b100 .
0$
#356
b1000000 0
1$
#366
b101 .
0$
#378
b10000000 0
1$
#388
b110 .
0$
#400
b0 0
1$
#410
1)
b111 .
0$
#412
1"
#422
1*
b1 0
1$
#432
0#
0!
0)
1'
02
b1000 .
0$
#442
01
1$
#452
z#
1!
0'
12
b100 :
b0 .
0$
#464
b11 0
1$
#474
b1 .
0$
#486
b111 0
1$
#496
b10 .
0$
#498
0"
#508
0*
b1110 0
1$
#518
b11 .
0$
#530
b11100 0
1$
#540
b100 .
0$
#542
1"
#552
1*
b111001 0
1$
#562
b101 .
0$
#564
0"
#574
0*
b1110010 0
1$
#584
b110 .
0$
#586
1"
#596
1*
b11100101 0
1$
#606
1)
b111 .
0$
#608
0"
#618
0*
b11001010 0
1$
#628
0#
1-
0!
0)
1'
02
b1000 .
0$
#638
11
1$
#648
z#
0-
1!
0'
b10 /
b11001010 5
12
b0 .
0$
#660
b10010100 0
1$
#670
b1 .
0$
#682
b101000 0
1$
#692
b10 .
0$
#694
1"
#704
1*
b1010001 0
1$
#714
b11 .
0$
#726
b10100011 0
1$
#736
b100 .
0$
#738
0"
#748
0*
b1000110 0
1$
#758
b101 .
0$
#760
1"
#770
1*
b10001101 0
1$
#780
b110 .
0$
#782
0"
#792
0*
b11010 0
1$
#802
1)
b111 .
0$
#804
1"
#814
1*
b110101 0
1$
#824
0#
1-
0!
0)
1'
02
b1000 .
0$
#834
01
1$
#844
z#
0-
1!
0'
12
b110101 6
b11 /
b0 .
0$
#846
0"
#856
0*
b1101010 0
1$
#860
1;
1"
#916
18
0"
#926
b1 :
b0 /
0$
#928
0;
1"
#938
08
1*
1+
b11010101 0
19
1$
#948
b1 .
0$
#950
0"
#960
0+
1(
0*
09
b10101010 0
1$
#970
b10 .
0$
#972
1"
#982
0(
1*
b1010101 0
1$
#992
b11 .
0$
#994
0"
#1004
1(
0*
b10101010 0
1$
#1014
b100 .
0$
#1016
1"
#1026
0(
1*
b1010101 0
1$
#1036
b101 .
0$
#1038
0"
#1048
1(
0*
b10101010 0
1$
#1058
b110 .
0$
#1060
1"
#1070
0(
1*
b1010101 0
1$
#1080
1)
b111 .
0$
#1082
0"
#1092
1(
0*
b10101010 0
1$
#1102
0#
0!
0)
1'
02
b1000 .
0$
#1112
11
1$
#1122
z#
1!
0'
12
b1 /
b11 :
b0 .
0$
#1134
0(
b1010100 0
1$
#1144
b1 .
0$
#1156
b10101000 0
1$
#1166
b10 .
0$
#1178
b1010000 0
1$
#1188
b11 .
0$
#1200
b10100000 0
1$
#1210
b100 .
0$
#1222
b1000000 0
1$
#1232
b101 .
0$
#1244
b10000000 0
1$
#1254
b110 .
0$
#1266
b0 0
1$
#1276
1)
b111 .
0$
#1278
1"
#1288
1*
b1 0
1$
#1298
0#
0!
0)
1'
02
b1000 .
b11001010 3
0$
#1308
01
1$
#1318
z#
1!
0'
b100 :
12
b10010100 3
b0 .
0$
#1330
b11 0
1$
#1340
b1 .
b101000 3
0$
#1342
0"
#1352
0*
b110 0
1$
#1362
b1010000 3
b10 .
0$
#1374
b1100 0
1$
#1384
b11 .
b10100000 3
0$
#1396
b11000 0
1$
#1406
b1000000 3
b100 .
0$
#1418
b110000 0
1$
#1428
b101 .
b10000000 3
0$
#1440
b1100000 0
1$
#1450
b0 3
b110 .
0$
#1462
b11000000 0
1$
#1472
1)
b111 .
0$
#1474
1"
#1484
1*
b10000001 0
1$
#1494
0#
1-
0!
0)
1'
02
b11001010 3
b1000 .
0$
#1504
1$
#1514
z#
0-
1!
0'
12
b10000001 5
b10 /
b0 .
b10010100 3
0$
#1516
0"
#1526
0*
b10 0
1$
#1536
b101000 3
b1 .
0$
#1538
1"
#1548
1*
b101 0
1$
#1558
b10 .
b1010000 3
0$
#1570
b1011 0
1$
#1580
b10100000 3
b11 .
0$
#1592
b10111 0
1$
#1602
b100 .
b1000000 3
0$
#1604
0"
#1614
0*
b101110 0
1$
#1624
b10000000 3
b101 .
0$
#1636
b1011100 0
1$
#1646
b110 .
b0 3
0$
#1648
1"
#1658
1*
b10111001 0
1$
#1668
1)
b111 .
0$
#1680
b1110011 0
1$
#1690
0#
1-
0!
0)
1'
02
b1000 .
b110101 3
0$
#1700
1$
#1710
z#
0-
1!
0'
b11 /
b1110011 6
12
b1101010 3
b0 .
0$
#1712
0"
#1722
0*
b11100110 0
1$
#1726
1;
1"
#1782
18
0"
#1792
b0 /
b1 :
b11010100 3
0$
#1794
0;
1"
#1804
08
1+
1*
19
b11001101 0
1$
#1814
b10101000 3
b1 .
0$
#1816
0"
#1826
0*
0+
b10011010 0
09
1$
#1836
b10 .
b1010000 3
0$
#1838
1"
#1848
1*
b110101 0
1$
#1858
b10100000 3
b11 .
0$
#1860
0"
#1870
0*
b1101010 0
1$
#1880
b100 .
b1000000 3
0$
#1882
1"
#1892
1*
b11010101 0
1$
#1902
b10000000 3
b101 .
0$
#1904
0"
#1914
1(
0*
b10101010 0
1$
#1924
b110 .
b0 3
0$
#1926
1"
#1936
0(
1*
b1010101 0
1$
#1946
1)
b111 .
0$
#1948
0"
#1958
1(
0*
b10101010 0
1$
#1968
0#
0!
0)
1'
02
b1000 .
0$
#1978
11
1$
#1988
z#
1!
0'
b11 :
b1 /
12
b0 .
0$
#2000
0(
b1010100 0
1$
#2010
b1 .
0$
#2022
b10101000 0
1$
#2032
b10 .
0$
#2044
b1010000 0
1$
#2054
b11 .
0$
#2066
b10100000 0
1$
#2076
b100 .
0$
#2088
b1000000 0
1$
#2098
b101 .
0$
#2110
b10000000 0
1$
#2120
b110 .
0$
#2122
1"
#2132
1*
b1 0
1$
#2142
1)
b111 .
0$
#2144
0"
#2154
0*
b10 0
1$
#2164
0#
0!
0)
1'
02
b10000001 3
b1000 .
0$
#2174
1$
#2184
z#
1!
0'
12
b10 /
b100 :
b0 .
b10 3
0$
#2186
1"
#2196
1*
b101 0
1$
#2206
18
0"
#2216
b1 :
b100 3
0$
#2218
1"
#2228
08
1+
b1011 0
19
1$
#2238
b1 .
b1000 3
0$
#2240
0"
#2250
0+
0*
09
b10110 0
1$
#2260
b10000 3
b10 .
0$
#2262
1"
#2272
1*
b101101 0
1$
#2282
b11 .
b100000 3
0$
#2284
0"
#2294
0*
b1011010 0
1$
#2304
b1000000 3
b100 .
0$
#2306
1"
#2316
1*
b10110101 0
1$
#2326
b101 .
b10000000 3
0$
#2328
0"
#2338
0*
b1101010 0
1$
#2348
b0 3
b110 .
0$
#2350
1"
#2360
1*
b11010101 0
1$
#2370
1)
b111 .
0$
#2382
1(
b10101011 0
1$
#2392
0#
0!
0)
1'
02
b1110011 3
b1000 .
0$
#2402
01
1$
#2412
0'
b11 /
b10 :
b0 .
b11100110 3
0$
#2422
0(
b1010111 0
1$
#2432
z#
1!
12
b11001100 3
b1 .
0$
#2442
b10101111 0
1$
#2452
b10 .
b10011000 3
0$
#2462
b1011111 0
1$
#2472
b110000 3
b11 .
0$
#2482
b10111111 0
1$
#2492
0#
0!
02
b100 .
b1100000 3
0$
#2502
b1111111 0
1$
#2512
b11000000 3
b101 .
0$
#2522
b11111111 0
1$
#2532
z#
1!
12
b110 .
b10000000 3
0$
#2542
1$
#2552
1)
b0 3
b111 .
0$
#2562
1$
#2572
0)
1'
b1000 .
0$
#2584
1$
#2594
0'
b0 :
b100 /
b0 .
0$
#2596
0"
#2606
0*
b11111110 0
1$
#2610
1;
1"
