I2c/I2C.v
/**************************************
* Module: I2C
* Date:2015-06-21  
* Author: saul     
*
* Description: I2C slave
***************************************/
module  I2C(
SDA,
SDAout,
SCL,
RST
);

//inout SDA;
input SDA;
output SDAout;
input SCL;
input RST; 


//Start Detection
reg  start_detect;
reg  start_resetter;
wire start_rst = RST | start_resetter;

always @ (posedge start_rst or negedge SDA)
begin
        if (start_rst)
                start_detect <= 1'b0;
        else
                start_detect <= SCL;
end

always @ (posedge RST or posedge SCL)
begin
        if (RST)
                start_resetter <= 1'b0;
        else
                start_resetter <= start_detect;
end

//Stop Detection
reg             stop_detect;
reg             stop_resetter;
wire            stop_rst = RST | stop_resetter;

always @ (posedge stop_rst or posedge SDA)
begin   
        if (stop_rst)
                stop_detect <= 1'b0;
        else
                stop_detect <= SCL;
end

always @ (posedge RST or posedge SCL)
begin   
        if (RST)
                stop_resetter <= 1'b0;
        else
                stop_resetter <= stop_detect;
end

// Counter
reg [3:0] bit_counter;

wire  lsb_bit = (bit_counter == 4'h7) && !start_detect;
wire  ack_bit = (bit_counter == 4'h8) && !start_detect; // 8 bits + ack

always @ (negedge SCL)
begin
        if (ack_bit || start_detect)
                bit_counter <= 4'h0;
        else
                bit_counter <= bit_counter + 4'h1;
end

// Latching the data 
reg [7:0] input_shift;

parameter [6:0] device_address = 7'h55;
wire            address_detect = (input_shift[7:1] == device_address);
wire            read_write_bit = input_shift[0];

always @ (posedge RST or posedge SCL)
        if (!ack_bit)
                input_shift <= {input_shift[6:0], SDA};

// Detection of Master Acknowledgement
reg master_ack;

always @ (posedge SCL)
        if (ack_bit)
                master_ack <= ~SDA;

// State Machine
// States change only whan ack_bit is asserted!
 
parameter [2:0] STATE_IDLE      = 3'h0,
                STATE_DEV_ADDR  = 3'h1,
                STATE_READ      = 3'h2,
                STATE_IDX_PTR   = 3'h3,
                STATE_WRITE     = 3'h4;

reg [2:0]       state;
wire            write_strobe = (state == STATE_WRITE) && ack_bit;

always @ (posedge RST or negedge SCL)
begin
        if (RST)
                state <= STATE_IDLE;
        else if (start_detect)
                state <= STATE_DEV_ADDR;
        else if (ack_bit)
        begin
                case (state)
                STATE_IDLE:
                        state <= STATE_IDLE;

                STATE_DEV_ADDR:
                        if (!address_detect)
                                state <= STATE_IDLE;
                        else if (read_write_bit)
                                state <= STATE_READ;
                        else
                                state <= STATE_IDX_PTR;

                STATE_READ:
                        if (master_ack)
                                state <= STATE_READ;
                        else
                                state <= STATE_IDLE;

                STATE_IDX_PTR:
                        state <= STATE_WRITE;

                STATE_WRITE:
                        state <= STATE_WRITE;
                endcase
        end
end

//Index pointer
// Only changes on ack_bit!

reg [7:0] index_pointer;

always @ (posedge RST or negedge SCL)
begin
        if (RST)
                index_pointer <= 8'h00;
        else if (stop_detect)
                index_pointer <= 8'h00;
        else if (ack_bit)
        begin
                if (state == STATE_IDX_PTR)
                        index_pointer <= input_shift;
                else
                        index_pointer <= index_pointer + 8'h01;
        end
end

//Register writes
reg [7:0]       reg_00;
reg [7:0]       reg_01;
reg [7:0]       reg_02;
reg [7:0]       reg_03;

/*
always @ (posedge RST or negedge SCL)
begin
        if (RST)
                reg_03 <= 8'h00;
        else if (write_strobe && (index_pointer == 8'h03))
                reg_03 <= input_shift;
end
*/

always @ (posedge RST or negedge SCL)
begin
        if (RST) begin
                reg_00 <= 8'h00;
                reg_01 <= 8'h00;
                reg_02 <= 8'h00;
                reg_03 <= 8'h00;
        end
        else if (write_strobe) begin
            case (index_pointer)
                8'h00: reg_00 <= input_shift;
                8'h01: reg_01 <= input_shift;
                8'h02: reg_02 <= input_shift;
                8'h03: reg_03 <= input_shift;                
            endcase
        end
          
end

// Read requests
reg [7:0]       output_shift;

always @ (negedge SCL)
begin   
        if (lsb_bit)
        begin   
                case (index_pointer)
                8'h00: output_shift <= reg_00;
                8'h01: output_shift <= reg_01;
                8'h02: output_shift <= reg_02;
                8'h03: output_shift <= reg_02;
                // ... and so on ...

                endcase
        end
        else
                output_shift <= {output_shift[6:0], 1'b0};
end

//output control

reg             output_control;
assign          SDAout = output_control ? 1'b1 : 1'b0;

always @ (posedge RST or negedge SCL)
begin   
        if (RST)
                output_control <= 1'b1;
                
        else if (start_detect)
                output_control <= 1'b1;
        else if (lsb_bit)
        begin   
                output_control <=
                    !(((state == STATE_DEV_ADDR) && address_detect) ||
                      (state == STATE_IDX_PTR) ||
                      (state == STATE_WRITE));
        end
        else if (ack_bit)
        begin
                // Deliver the first bit of the next slave-to-master
                // transfer, if applicable.
                if (((state == STATE_READ) && master_ack) ||
                    ((state == STATE_DEV_ADDR) &&
                        address_detect && read_write_bit))
                        output_control <= output_shift[7];
                else
                        output_control <= 1'b1;
        end
        else if (state == STATE_READ)
                output_control <= output_shift[7];
        else
                output_control <= 1'b1;
end


endmodule

I2c/I2C_tb.v
/**************************************
* Module: I2C_tb
* Date:2015-06-21  
* Author: saul     
*
* Description: 
***************************************/
module  I2C_tb(
);

//Nets to drive
reg SCL;
//reg SDA;

reg RST;

wire SDAW;

reg SDA;

assign SDAW = (~SDA) ? 1'bz : 1'b0;

//Output wires
wire SDAout;

initial begin
    $dumpfile("I2C.vcd");
    $dumpvars(0,my_I2C);
    
    RST = 0;
    SCL = 1;
    SDA = 1;
    
    #2 RST = 1;
    #2 RST = 0;
    #6 SDA = 0; // START    
    
    // ADDRESS
    #10 SCL = 0; SDA = 1;
    #10 SCL = 1;
    #10 SCL = 0; SDA = 0;
    #10 SCL = 1;
    #10 SCL = 0; SDA = 1;
    #10 SCL = 1;
    #10 SCL = 0; SDA = 0;
    #10 SCL = 1;
    #10 SCL = 0; SDA = 1;
    #10 SCL = 1;
    #10 SCL = 0; SDA = 0;
    #10 SCL = 1;
    #10 SCL = 0; SDA = 1;
    #10 SCL = 1;
    
    // R/W#
    #10 SCL = 0; SDA = 0;
    #10 SCL = 1;
    
    #10 SCL = 0; 
    #10 SCL = 1; // ACK SAMPLED
    
     //REGISTER ID 
    #10 SCL = 0; SDA = 0;
    #10 SCL = 1; 
    #10 SCL = 0; SDA = 0;
    #10 SCL = 1; 
    #10 SCL = 0; SDA = 0;
    #10 SCL = 1; 
    #10 SCL = 0; SDA = 0;
    #10 SCL = 1;
    #10 SCL = 0; SDA = 0;
    #10 SCL = 1; 
    #10 SCL = 0; SDA = 0;
    #10 SCL = 1; 
    #10 SCL = 0; SDA = 0;
    #10 SCL = 1; 
    #10 SCL = 0; SDA = 1;
    #10 SCL = 1; 
    
    #10 SCL = 0; 
    #10 SCL = 1; // ACK SAMPLED
    
    //DATA 0 0xCA
    #10 SCL = 0; SDA = 1;
    #10 SCL = 1; 
    #10 SCL = 0; SDA = 1;
    #10 SCL = 1; 
    #10 SCL = 0; SDA = 0;
    #10 SCL = 1; 
    #10 SCL = 0; SDA = 0;
    #10 SCL = 1;
    #10 SCL = 0; SDA = 1;
    #10 SCL = 1; 
    #10 SCL = 0; SDA = 0;
    #10 SCL = 1; 
    #10 SCL = 0; SDA = 1;
    #10 SCL = 1; 
    #10 SCL = 0; SDA = 0;
    #10 SCL = 1; 
    
    #10 SCL = 0; 
    #10 SCL = 1; // ACK SAMPLED
    
     //DATA 1 0x35
    #10 SCL = 0; SDA = 0;
    #10 SCL = 1; 
    #10 SCL = 0; SDA = 0;
    #10 SCL = 1; 
    #10 SCL = 0; SDA = 1;
    #10 SCL = 1; 
    #10 SCL = 0; SDA = 1;
    #10 SCL = 1;
    #10 SCL = 0; SDA = 0;
    #10 SCL = 1; 
    #10 SCL = 0; SDA = 1;
    #10 SCL = 1; 
    #10 SCL = 0; SDA = 0;
    #10 SCL = 1; 
    #10 SCL = 0; SDA = 1;
    #10 SCL = 1; 
    
    #10 SCL = 0; 
    #10 SCL = 1; // ACK SAMPLED
    
    
    #10 SCL = 0;
    
    #40 SCL = 1; // STOP
    #4 SDA = 1;
    
    #6 SDA = 0; // START
    #10 SCL = 0;
    #10 SCL = 1;
    #10 SCL = 0;
    #40 SCL = 1;
    #4 SDA = 1;
    
    #50 $finish;
end

/*
always begin
    #20 SCL = ~ SCL;
end
*/

I2C my_I2C(SDA,SDAout,SCL,RST);


endmodule

I2c/I2C.vcd
$date
	Mon Jun 22 11:14:15 2015
$end
$version
	Icarus Verilog
$end
$timescale
	1s
$end
$scope module I2C_tb $end
$scope module my_I2C $end
$var wire 1 ! RST $end
$var wire 1 " SCL $end
$var wire 1 # SDA $end
$var wire 1 $ SDAout $end
$var wire 1 % ack_bit $end
$var wire 1 & address_detect $end
$var wire 1 ' lsb_bit $end
$var wire 1 ( read_write_bit $end
$var wire 1 ) start_rst $end
$var wire 1 * stop_rst $end
$var wire 1 + write_strobe $end
$var reg 4 , bit_counter [3:0] $end
$var reg 8 - index_pointer [7:0] $end
$var reg 8 . input_shift [7:0] $end
$var reg 1 / master_ack $end
$var reg 1 0 output_control $end
$var reg 8 1 output_shift [7:0] $end
$var reg 8 2 reg_00 [7:0] $end
$var reg 8 3 reg_01 [7:0] $end
$var reg 8 4 reg_02 [7:0] $end
$var reg 8 5 reg_03 [7:0] $end
$var reg 1 6 start_detect $end
$var reg 1 7 start_resetter $end
$var reg 3 8 state [2:0] $end
$var reg 1 9 stop_detect $end
$var reg 1 : stop_resetter $end
$upscope $end
$upscope $end
$enddefinitions $end
#0
$dumpvars
x:
19
bx 8
x7
x6
bx 5
bx 4
bx 3
bx 2
bx 1
x0
x/
bx .
bx -
bx ,
x+
x*
x)
x(
x'
x&
x%
x$
1#
1"
0!
$end
#2
0+
1$
06
09
b0 8
b0 -
b0 5
b0 4
b0 3
b0 2
10
0:
07
1)
1*
1!
#4
0)
0*
0!
#10
0'
0%
16
0#
#20
b1 8
b0 ,
bx0 1
1#
0"
#30
06
1)
1(
17
bx1 .
1"
#40
bx00 1
b1 ,
0#
0"
#50
0(
0)
bx10 .
07
1"
#60
b10 ,
bx000 1
1#
0"
#70
0&
1(
bx101 .
1"
#80
bx0000 1
b11 ,
0#
0"
#90
x&
0(
bx1010 .
1"
#100
b100 ,
bx00000 1
1#
0"
#110
0&
1(
bx10101 .
1"
#120
bx000000 1
b101 ,
0#
0"
#130
x&
0(
bx101010 .
1"
#140
b110 ,
bx0000000 1
1#
0"
#150
0&
1(
bx1010101 .
1"
#160
1'
b0 1
b111 ,
0#
0"
#170
1&
0(
b10101010 .
1"
#180
0$
0'
1%
00
b1000 ,
0"
#190
1/
1"
#200
1$
0%
b11 8
b1 -
10
b0 ,
0"
#210
0&
b1010100 .
1"
#220
b1 ,
0"
#230
b10101000 .
1"
#240
b10 ,
0"
#250
b1010000 .
1"
#260
b11 ,
0"
#270
b10100000 .
1"
#280
b100 ,
0"
#290
b1000000 .
1"
#300
b101 ,
0"
#310
b10000000 .
1"
#320
b110 ,
0"
#330
b0 .
1"
#340
1'
b111 ,
1#
0"
#350
1(
b1 .
1"
#360
0$
0'
1%
00
b1000 ,
0"
#370
0/
1"
#380
1$
0%
10
b100 8
b0 ,
0"
#390
b11 .
1"
#400
b1 ,
0"
#410
b111 .
1"
#420
b10 ,
0#
0"
#430
0(
b1110 .
1"
#440
b11 ,
0"
#450
b11100 .
1"
#460
b100 ,
1#
0"
#470
1(
b111001 .
1"
#480
b101 ,
0#
0"
#490
0(
b1110010 .
1"
#500
b110 ,
1#
0"
#510
1(
b11100101 .
1"
#520
1'
b111 ,
0#
0"
#530
0(
b11001010 .
1"
#540
1+
0$
0'
1%
00
b1000 ,
0"
#550
1/
1"
#560
0+
1$
0%
b10 -
b11001010 3
10
b0 ,
0"
#570
b10010100 .
1"
#580
b1 ,
0"
#590
b101000 .
1"
#600
b10 ,
1#
0"
#610
1(
b1010001 .
1"
#620
b11 ,
0"
#630
b10100011 .
1"
#640
b100 ,
0#
0"
#650
0(
b1000110 .
1"
#660
b101 ,
1#
0"
#670
1(
b10001101 .
1"
#680
b110 ,
0#
0"
#690
0(
b11010 .
1"
#700
1'
b111 ,
1#
0"
#710
1(
b110101 .
1"
#720
1+
0$
0'
1%
00
b1000 ,
0"
#730
0/
1"
#740
0+
1$
0%
10
b110101 4
b11 -
b0 ,
0"
#780
b1101011 .
1"
#790
16
0#
#800
b1 8
0"
#810
06
0(
1)
b11010110 .
17
1"
#820
b1 ,
0"
#860
0)
07
b10101100 .
1"
#864
19
1#
