I2c/I2C.v
/**************************************
* Module: I2C
* Date:2015-06-21  
* Author: saul     
*
* Description: I2C slave
***************************************/


module  I2C(
SDA,
SDAout,
SCL,
RSTN
);

//inout SDA;
input SDA;
output SDAout;
input SCL;
input RSTN; 


wire RST;

assign RST = ~RSTN;

//Start Detection
reg  start_detect;
reg  start_resetter;
wire start_rst = RST | start_resetter;

always @ (posedge start_rst or negedge SDA)
begin
        if (start_rst)
                start_detect <= 1'b0;
        else
                start_detect <= SCL;
end

always @ (posedge RST or posedge SCL)
begin
        if (RST)
                start_resetter <= 1'b0;
        else
                start_resetter <= start_detect;
end

//Stop Detection
reg             stop_detect;
reg             stop_resetter;
wire            stop_rst = RST | stop_resetter;

always @ (posedge stop_rst or posedge SDA)
begin   
        if (stop_rst)
                stop_detect <= 1'b0;
        else
                stop_detect <= SCL;
end

always @ (posedge RST or posedge SCL)
begin   
        if (RST)
                stop_resetter <= 1'b0;
        else
                stop_resetter <= stop_detect;
end

// Counter
reg [3:0] bit_counter;

wire  lsb_bit = (bit_counter == 4'h7) && !start_detect;
wire  ack_bit = (bit_counter == 4'h8) && !start_detect; // 8 bits + ack

always @ (negedge SCL)
begin
        if (ack_bit || start_detect)
                bit_counter <= 4'h0;
        else
                bit_counter <= bit_counter + 4'h1;
end

// Latching the data 
reg [7:0] input_shift;

parameter [6:0] device_address = 7'h55;
wire            address_detect = (input_shift[7:1] == device_address);
wire            read_write_bit = input_shift[0];

always @ (posedge RST or posedge SCL)
        if (!ack_bit)
                input_shift <= {input_shift[6:0], SDA};

// Detection of Master Acknowledgement
reg master_ack;

always @ (posedge SCL)
        if (ack_bit)
                master_ack <= ~SDA;

// State Machine
// States change only whan ack_bit is asserted!
 
parameter [2:0] STATE_IDLE      = 3'h0,
                STATE_DEV_ADDR  = 3'h1,
                STATE_READ      = 3'h2,
                STATE_IDX_PTR   = 3'h3,
                STATE_WRITE     = 3'h4;

reg [2:0]       state;
wire            write_strobe = (state == STATE_WRITE) && ack_bit;

always @ (posedge RST or negedge SCL)
begin
        if (RST)
                state <= STATE_IDLE;
        else if (start_detect)
                state <= STATE_DEV_ADDR;
        else if (ack_bit)
        begin
                case (state)
                STATE_IDLE:
                        state <= STATE_IDLE;

                STATE_DEV_ADDR:
                        if (!address_detect)
                                state <= STATE_IDLE;
                        else if (read_write_bit)
                                state <= STATE_READ;
                        else
                                state <= STATE_IDX_PTR;

                STATE_READ:
                        if (master_ack)
                                state <= STATE_READ;
                        else
                                state <= STATE_IDLE;

                STATE_IDX_PTR:
                        state <= STATE_WRITE;

                STATE_WRITE:
                        state <= STATE_WRITE;
                endcase
        end
end

//Index pointer
// Only changes on ack_bit!

reg [7:0] index_pointer;

always @ (posedge RST or negedge SCL)
begin
        if (RST)
                index_pointer <= 8'h00;
        else if (stop_detect)
                index_pointer <= 8'h00;
        else if (ack_bit)
        begin
                if (state == STATE_IDX_PTR)
                        index_pointer <= input_shift;
                else
                        index_pointer <= index_pointer + 8'h01;
        end
end

//Register writes
reg [7:0]       reg_00;
reg [7:0]       reg_01;
reg [7:0]       reg_02;
reg [7:0]       reg_03;

/*
always @ (posedge RST or negedge SCL)
begin
        if (RST)
                reg_03 <= 8'h00;
        else if (write_strobe && (index_pointer == 8'h03))
                reg_03 <= input_shift;
end
*/

always @ (posedge RST or negedge SCL)
begin
        if (RST) begin
                reg_00 <= 8'h00;
                reg_01 <= 8'h00;
                reg_02 <= 8'h00;
                reg_03 <= 8'h00;
        end
        else if (write_strobe) begin
            case (index_pointer)
                8'h00: reg_00 <= input_shift;
                8'h01: reg_01 <= input_shift;
                8'h02: reg_02 <= input_shift;
                8'h03: reg_03 <= input_shift;                
            endcase
        end
          
end

// Read requests
reg [7:0]       output_shift;

always @ (negedge SCL)
begin   
        if (lsb_bit)
        begin   
                case (index_pointer)
                8'h00: output_shift <= reg_00;
                8'h01: output_shift <= reg_01;
                8'h02: output_shift <= reg_02;
                8'h03: output_shift <= reg_03;
                // ... and so on ...

                endcase
        end
        else
                output_shift <= {output_shift[6:0], 1'b0};
end

//output control

reg             output_control;
assign          SDAout = output_control ? 1'b1 : 1'b0;

always @ (posedge RST or negedge SCL)
begin   
        if (RST)
                output_control <= 1'b1;
                
        else if (start_detect)
                output_control <= 1'b1;
        else if (lsb_bit)
        begin   
                output_control <=
                    !(((state == STATE_DEV_ADDR) && address_detect) ||
                      (state == STATE_IDX_PTR) ||
                      (state == STATE_WRITE));
        end
        else if (ack_bit)
        begin
                // Deliver the first bit of the next slave-to-master
                // transfer, if applicable.
                if (((state == STATE_READ) && master_ack) ||
                    ((state == STATE_DEV_ADDR) &&
                        address_detect && read_write_bit))
                        output_control <= output_shift[7];
                else
                        output_control <= 1'b1;
        end
        else if (state == STATE_READ)
                output_control <= output_shift[7];
        else
                output_control <= 1'b1;
end


endmodule

I2c/I2C_tb.v
/**************************************
* Module: I2C_tb
* Date:2015-06-21  
* Author: saul     
*
* Description: 

 

***************************************/
module  I2C_tb(
);

//Nets to drive
reg SCL;
//reg SDA;

reg RST;

wire SDAW;

reg SDA;

assign SDAW = (~SDA) ? 1'bz : 1'b0;

//Output wires
wire SDAout;

initial begin
    $dumpfile("I2C.vcd");
    $dumpvars(0,my_I2C);
    
    RST = 0;
    SCL = 1;
    SDA = 1;
    
    #2 RST = 1;
    #2 RST = 0;
    #40;
    
    `include "write_i2c.inc"
    #40;
    `include "write_i2c_2.inc"
    #40;
    `include "read_i2c.inc"
   
   
   /*
    #6 SDA = 0; // START
    #10 SCL = 0;
    #10 SCL = 1;
    #10 SCL = 0;
    #40 SCL = 1;
    #4 SDA = 1;
    */
    
    #50 $finish;
end

/*
always begin
    #20 SCL = ~ SCL;
end
*/

I2C my_I2C(SDA,SDAout,SCL,RST);


endmodule

I2c/I2C.vcd
$date
	Thu May 25 13:28:52 2017
$end
$version
	Icarus Verilog
$end
$timescale
	1s
$end
$scope module I2C_tb $end
$scope module my_I2C $end
$var wire 1 ! RST $end
$var wire 1 " RSTN $end
$var wire 1 # SCL $end
$var wire 1 $ SDA $end
$var wire 1 % ack_bit $end
$var wire 1 & lsb_bit $end
$var wire 1 ' start_rst $end
$var wire 1 ( stop_rst $end
$var wire 1 ) write_strobe $end
$var wire 1 * read_write_bit $end
$var wire 1 + address_detect $end
$var wire 1 , SDAout $end
$var reg 4 - bit_counter [3:0] $end
$var reg 8 . index_pointer [7:0] $end
$var reg 8 / input_shift [7:0] $end
$var reg 1 0 master_ack $end
$var reg 1 1 output_control $end
$var reg 8 2 output_shift [7:0] $end
$var reg 8 3 reg_00 [7:0] $end
$var reg 8 4 reg_01 [7:0] $end
$var reg 8 5 reg_02 [7:0] $end
$var reg 8 6 reg_03 [7:0] $end
$var reg 1 7 start_detect $end
$var reg 1 8 start_resetter $end
$var reg 3 9 state [2:0] $end
$var reg 1 : stop_detect $end
$var reg 1 ; stop_resetter $end
$upscope $end
$upscope $end
$enddefinitions $end
#0
$dumpvars
x;
1:
bx 9
x8
x7
bx 6
bx 5
bx 4
bx 3
bx 2
x1
x0
bx /
bx .
bx -
x,
x+
x*
x)
x(
x'
x&
x%
1$
1#
1"
0!
$end
#2
0)
1,
07
0:
b0 9
b0 .
b0 6
b0 5
b0 4
b0 3
11
0;
08
1'
1(
1!
0"
#4
0'
0(
0!
1"
#50
0&
0%
17
0$
#60
b1 9
b0 -
bx0 2
0#
#62
1$
#72
07
1'
1*
18
bx1 /
1#
#82
bx00 2
b1 -
0#
#84
0$
#94
0*
0'
bx10 /
08
1#
#104
b10 -
bx000 2
0#
#106
1$
#116
0+
1*
bx101 /
1#
#126
bx0000 2
b11 -
0#
#128
0$
#138
x+
0*
bx1010 /
1#
#148
b100 -
bx00000 2
0#
#150
1$
#160
0+
1*
bx10101 /
1#
#170
bx000000 2
b101 -
0#
#172
0$
#182
x+
0*
bx101010 /
1#
#192
b110 -
bx0000000 2
0#
#194
1$
#204
0+
1*
bx1010101 /
1#
#214
1&
b0 2
b111 -
0#
#216
0$
#226
1+
0*
b10101010 /
1#
#236
0,
0&
1%
01
b1000 -
0#
#246
10
1#
#256
1,
0%
b11 9
b1 .
11
b0 -
0#
#268
0+
b1010100 /
1#
#278
b1 -
0#
#290
b10101000 /
1#
#300
b10 -
0#
#312
b1010000 /
1#
#322
b11 -
0#
#334
b10100000 /
1#
#344
b100 -
0#
#356
b1000000 /
1#
#366
b101 -
0#
#378
b10000000 /
1#
#388
b110 -
0#
#400
b0 /
1#
#410
1&
b111 -
0#
#412
1$
#422
1*
b1 /
1#
#432
0,
0&
1%
01
b1000 -
0#
#442
00
1#
#452
1,
0%
11
b100 9
b0 -
0#
#464
b11 /
1#
#474
b1 -
0#
#486
b111 /
1#
#496
b10 -
0#
#498
0$
#508
0*
b1110 /
1#
#518
b11 -
0#
#530
b11100 /
1#
#540
b100 -
0#
#542
1$
#552
1*
b111001 /
1#
#562
b101 -
0#
#564
0$
#574
0*
b1110010 /
1#
#584
b110 -
0#
#586
1$
#596
1*
b11100101 /
1#
#606
1&
b111 -
0#
#608
0$
#618
0*
b11001010 /
1#
#628
1)
0,
0&
1%
01
b1000 -
0#
#638
10
1#
#648
0)
1,
0%
b10 .
b11001010 4
11
b0 -
0#
#660
b10010100 /
1#
#670
b1 -
0#
#682
b101000 /
1#
#692
b10 -
0#
#694
1$
#704
1*
b1010001 /
1#
#714
b11 -
0#
#726
b10100011 /
1#
#736
b100 -
0#
#738
0$
#748
0*
b1000110 /
1#
#758
b101 -
0#
#760
1$
#770
1*
b10001101 /
1#
#780
b110 -
0#
#782
0$
#792
0*
b11010 /
1#
#802
1&
b111 -
0#
#804
1$
#814
1*
b110101 /
1#
#824
1)
0,
0&
1%
01
b1000 -
0#
#834
00
1#
#844
0)
1,
0%
11
b110101 5
b11 .
b0 -
0#
#846
0$
#856
0*
b1101010 /
1#
#860
1:
1$
#916
17
0$
#926
b1 9
b0 .
0#
#928
0:
1$
#938
07
1*
1'
b11010101 /
18
1#
#948
b1 -
0#
#950
0$
#960
0'
1+
0*
08
b10101010 /
1#
#970
b10 -
0#
#972
1$
#982
0+
1*
b1010101 /
1#
#992
b11 -
0#
#994
0$
#1004
1+
0*
b10101010 /
1#
#1014
b100 -
0#
#1016
1$
#1026
0+
1*
b1010101 /
1#
#1036
b101 -
0#
#1038
0$
#1048
1+
0*
b10101010 /
1#
#1058
b110 -
0#
#1060
1$
#1070
0+
1*
b1010101 /
1#
#1080
1&
b111 -
0#
#1082
0$
#1092
1+
0*
b10101010 /
1#
#1102
0,
0&
1%
01
b1000 -
0#
#1112
10
1#
#1122
1,
0%
11
b1 .
b11 9
b0 -
0#
#1134
0+
b1010100 /
1#
#1144
b1 -
0#
#1156
b10101000 /
1#
#1166
b10 -
0#
#1178
b1010000 /
1#
#1188
b11 -
0#
#1200
b10100000 /
1#
#1210
b100 -
0#
#1222
b1000000 /
1#
#1232
b101 -
0#
#1244
b10000000 /
1#
#1254
b110 -
0#
#1266
b0 /
1#
#1276
1&
b111 -
0#
#1278
1$
#1288
1*
b1 /
1#
#1298
0,
0&
1%
01
b1000 -
b11001010 2
0#
#1308
00
1#
#1318
1,
0%
b100 9
11
b10010100 2
b0 -
0#
#1330
b11 /
1#
#1340
b1 -
b101000 2
0#
#1342
0$
#1352
0*
b110 /
1#
#1362
b1010000 2
b10 -
0#
#1374
b1100 /
1#
#1384
b11 -
b10100000 2
0#
#1396
b11000 /
1#
#1406
b1000000 2
b100 -
0#
#1418
b110000 /
1#
#1428
b101 -
b10000000 2
0#
#1440
b1100000 /
1#
#1450
b0 2
b110 -
0#
#1462
b11000000 /
1#
#1472
1&
b111 -
0#
#1474
1$
#1484
1*
b10000001 /
1#
#1494
1)
0,
0&
1%
01
b11001010 2
b1000 -
0#
#1504
1#
#1514
0)
1,
0%
11
b10000001 4
b10 .
b0 -
b10010100 2
0#
#1516
0$
#1526
0*
b10 /
1#
#1536
b101000 2
b1 -
0#
#1538
1$
#1548
1*
b101 /
1#
#1558
b10 -
b1010000 2
0#
#1570
b1011 /
1#
#1580
b10100000 2
b11 -
0#
#1592
b10111 /
1#
#1602
b100 -
b1000000 2
0#
#1604
0$
#1614
0*
b101110 /
1#
#1624
b10000000 2
b101 -
0#
#1636
b1011100 /
1#
#1646
b110 -
b0 2
0#
#1648
1$
#1658
1*
b10111001 /
1#
#1668
1&
b111 -
0#
#1680
b1110011 /
1#
#1690
1)
0,
0&
1%
01
b1000 -
b110101 2
0#
#1700
1#
#1710
0)
1,
0%
b11 .
b1110011 5
11
b1101010 2
b0 -
0#
#1712
0$
#1722
0*
b11100110 /
1#
#1726
1:
1$
#1782
17
0$
#1792
b0 .
b1 9
b11010100 2
0#
#1794
0:
1$
#1804
07
1'
1*
18
b11001101 /
1#
#1814
b10101000 2
b1 -
0#
#1816
0$
#1826
0*
0'
b10011010 /
08
1#
#1836
b10 -
b1010000 2
0#
#1838
1$
#1848
1*
b110101 /
1#
#1858
b10100000 2
b11 -
0#
#1860
0$
#1870
0*
b1101010 /
1#
#1880
b100 -
b1000000 2
0#
#1882
1$
#1892
1*
b11010101 /
1#
#1902
b10000000 2
b101 -
0#
#1904
0$
#1914
1+
0*
b10101010 /
1#
#1924
b110 -
b0 2
0#
#1926
1$
#1936
0+
1*
b1010101 /
1#
#1946
1&
b111 -
0#
#1948
0$
#1958
1+
0*
b10101010 /
1#
#1968
0,
0&
1%
01
b1000 -
0#
#1978
10
1#
#1988
1,
0%
b11 9
b1 .
11
b0 -
0#
#2000
0+
b1010100 /
1#
#2010
b1 -
0#
#2022
b10101000 /
1#
#2032
b10 -
0#
#2044
b1010000 /
1#
#2054
b11 -
0#
#2066
b10100000 /
1#
#2076
b100 -
0#
#2088
b1000000 /
1#
#2098
b101 -
0#
#2110
b10000000 /
1#
#2120
b110 -
0#
#2122
1$
#2132
1*
b1 /
1#
#2142
1&
b111 -
0#
#2144
0$
#2154
0*
b10 /
1#
#2164
0,
0&
1%
01
b10000001 2
b1000 -
0#
#2174
1#
#2184
1,
0%
11
b10 .
b100 9
b0 -
b10 2
0#
#2186
1$
#2196
1*
b101 /
1#
#2206
17
0$
#2216
b1 9
b100 2
0#
#2218
1$
#2228
07
1'
b1011 /
18
1#
#2238
b1 -
b1000 2
0#
#2240
0$
#2250
0'
0*
08
b10110 /
1#
#2260
b10000 2
b10 -
0#
#2262
1$
#2272
1*
b101101 /
1#
#2282
b11 -
b100000 2
0#
#2284
0$
#2294
0*
b1011010 /
1#
#2304
b1000000 2
b100 -
0#
#2306
1$
#2316
1*
b10110101 /
1#
#2326
b101 -
b10000000 2
0#
#2328
0$
#2338
0*
b1101010 /
1#
#2348
b0 2
b110 -
0#
#2350
1$
#2360
1*
b11010101 /
1#
#2370
1&
b111 -
0#
#2382
1+
b10101011 /
1#
#2392
0,
0&
1%
01
b1110011 2
b1000 -
0#
#2402
00
1#
#2412
0%
b11 .
b10 9
b0 -
b11100110 2
0#
#2422
0+
b1010111 /
1#
#2432
1,
11
b11001100 2
b1 -
0#
#2442
b10101111 /
1#
#2452
b10 -
b10011000 2
0#
#2462
b1011111 /
1#
#2472
b110000 2
b11 -
0#
#2482
b10111111 /
1#
#2492
0,
01
b100 -
b1100000 2
0#
#2502
b1111111 /
1#
#2512
b11000000 2
b101 -
0#
#2522
b11111111 /
1#
#2532
1,
11
b110 -
b10000000 2
0#
#2542
1#
#2552
1&
b0 2
b111 -
0#
#2562
1#
#2572
0&
1%
b1000 -
0#
#2584
1#
#2594
0%
b0 9
b100 .
b0 -
0#
#2596
0$
#2606
0*
b11111110 /
1#
#2610
1:
1$
