I2c/I2C.v
/**************************************
* Module: I2C
* Date:2015-06-21  
* Author: saul     
*
* Description: I2C slave
***************************************/
module  I2C(
SDA,
SDAout,
SCL,
RST
);

//inout SDA;
input SDA;
output SDAout;
input SCL;
input RST; 


//Start Detection
reg  start_detect;
reg  start_resetter;
wire start_rst = RST | start_resetter;

always @ (posedge start_rst or negedge SDA)
begin
        if (start_rst)
                start_detect <= 1'b0;
        else
                start_detect <= SCL;
end

always @ (posedge RST or posedge SCL)
begin
        if (RST)
                start_resetter <= 1'b0;
        else
                start_resetter <= start_detect;
end

//Stop Detection
reg             stop_detect;
reg             stop_resetter;
wire            stop_rst = RST | stop_resetter;

always @ (posedge stop_rst or posedge SDA)
begin   
        if (stop_rst)
                stop_detect <= 1'b0;
        else
                stop_detect <= SCL;
end

always @ (posedge RST or posedge SCL)
begin   
        if (RST)
                stop_resetter <= 1'b0;
        else
                stop_resetter <= stop_detect;
end

// Counter
reg [3:0] bit_counter;

wire  lsb_bit = (bit_counter == 4'h7) && !start_detect;
wire  ack_bit = (bit_counter == 4'h8) && !start_detect; // 8 bits + ack

always @ (negedge SCL)
begin
        if (ack_bit || start_detect)
                bit_counter <= 4'h0;
        else
                bit_counter <= bit_counter + 4'h1;
end

// Latching the data 
reg [7:0] input_shift;

parameter [6:0] device_address = 7'h55;
wire            address_detect = (input_shift[7:1] == device_address);
wire            read_write_bit = input_shift[0];

always @ (posedge RST or posedge SCL)
        if (!ack_bit)
                input_shift <= {input_shift[6:0], SDA};

// Detection of Master Acknowledgement
reg master_ack;

always @ (posedge SCL)
        if (ack_bit)
                master_ack <= ~SDA;

// State Machine
// States change only whan ack_bit is asserted!
 
parameter [2:0] STATE_IDLE      = 3'h0,
                STATE_DEV_ADDR  = 3'h1,
                STATE_READ      = 3'h2,
                STATE_IDX_PTR   = 3'h3,
                STATE_WRITE     = 3'h4;

reg [2:0]       state;
wire            write_strobe = (state == STATE_WRITE) && ack_bit;

always @ (posedge RST or negedge SCL)
begin
        if (RST)
                state <= STATE_IDLE;
        else if (start_detect)
                state <= STATE_DEV_ADDR;
        else if (ack_bit)
        begin
                case (state)
                STATE_IDLE:
                        state <= STATE_IDLE;

                STATE_DEV_ADDR:
                        if (!address_detect)
                                state <= STATE_IDLE;
                        else if (read_write_bit)
                                state <= STATE_READ;
                        else
                                state <= STATE_IDX_PTR;

                STATE_READ:
                        if (master_ack)
                                state <= STATE_READ;
                        else
                                state <= STATE_IDLE;

                STATE_IDX_PTR:
                        state <= STATE_WRITE;

                STATE_WRITE:
                        state <= STATE_WRITE;
                endcase
        end
end

//Index pointer
// Only changes on ack_bit!

reg [7:0] index_pointer;

always @ (posedge RST or negedge SCL)
begin
        if (RST)
                index_pointer <= 8'h00;
        else if (stop_detect)
                index_pointer <= 8'h00;
        else if (ack_bit)
        begin
                if (state == STATE_IDX_PTR)
                        index_pointer <= input_shift;
                else
                        index_pointer <= index_pointer + 8'h01;
        end
end

//Register writes
reg [7:0]       reg_00;
reg [7:0]       reg_01;
reg [7:0]       reg_02;
reg [7:0]       reg_03;

/*
always @ (posedge RST or negedge SCL)
begin
        if (RST)
                reg_03 <= 8'h00;
        else if (write_strobe && (index_pointer == 8'h03))
                reg_03 <= input_shift;
end
*/

always @ (posedge RST or negedge SCL)
begin
        if (RST) begin
                reg_00 <= 8'h00;
                reg_01 <= 8'h00;
                reg_02 <= 8'h00;
                reg_03 <= 8'h00;
        end
        else if (write_strobe) begin
            case (index_pointer)
                8'h00: reg_00 <= input_shift;
                8'h01: reg_01 <= input_shift;
                8'h02: reg_02 <= input_shift;
                8'h03: reg_03 <= input_shift;                
            endcase
        end
          
end

// Read requests
reg [7:0]       output_shift;

always @ (negedge SCL)
begin   
        if (lsb_bit)
        begin   
                case (index_pointer)
                8'h00: output_shift <= reg_00;
                8'h01: output_shift <= reg_01;
                8'h02: output_shift <= reg_02;
                8'h03: output_shift <= reg_03;
                // ... and so on ...

                endcase
        end
        else
                output_shift <= {output_shift[6:0], 1'b0};
end

//output control

reg             output_control;
assign          SDAout = output_control ? 1'b1 : 1'b0;

always @ (posedge RST or negedge SCL)
begin   
        if (RST)
                output_control <= 1'b1;
                
        else if (start_detect)
                output_control <= 1'b1;
        else if (lsb_bit)
        begin   
                output_control <=
                    !(((state == STATE_DEV_ADDR) && address_detect) ||
                      (state == STATE_IDX_PTR) ||
                      (state == STATE_WRITE));
        end
        else if (ack_bit)
        begin
                // Deliver the first bit of the next slave-to-master
                // transfer, if applicable.
                if (((state == STATE_READ) && master_ack) ||
                    ((state == STATE_DEV_ADDR) &&
                        address_detect && read_write_bit))
                        output_control <= output_shift[7];
                else
                        output_control <= 1'b1;
        end
        else if (state == STATE_READ)
                output_control <= output_shift[7];
        else
                output_control <= 1'b1;
end


endmodule

I2c/I2C_tb.v
/**************************************
* Module: I2C_tb
* Date:2015-06-21  
* Author: saul     
*
* Description: 

 

***************************************/
module  I2C_tb(
);

//Nets to drive
reg SCL;
//reg SDA;

reg RST;

wire SDAW;

reg SDA;

assign SDAW = (~SDA) ? 1'bz : 1'b0;

//Output wires
wire SDAout;

initial begin
    $dumpfile("I2C.vcd");
    $dumpvars(0,my_I2C);
    
    RST = 0;
    SCL = 1;
    SDA = 1;
    
    #2 RST = 1;
    #2 RST = 0;
    #40;
    
    `include "write_i2c.inc"
    #40;
    `include "write_i2c_2.inc"
    #40;
    `include "read_i2c.inc"
   
   
   /*
    #6 SDA = 0; // START
    #10 SCL = 0;
    #10 SCL = 1;
    #10 SCL = 0;
    #40 SCL = 1;
    #4 SDA = 1;
    */
    
    #50 $finish;
end

/*
always begin
    #20 SCL = ~ SCL;
end
*/

I2C my_I2C(SDA,SDAout,SCL,RST);


endmodule

I2c/I2C.vcd
$date
	Fri Sep 25 10:05:22 2015
$end
$version
	Icarus Verilog
$end
$timescale
	1s
$end
$scope module I2C_tb $end
$scope module my_I2C $end
$var wire 1 ! RST $end
$var wire 1 " SCL $end
$var wire 1 # SDA $end
$var wire 1 $ SDAout $end
$var wire 1 % ack_bit $end
$var wire 1 & address_detect $end
$var wire 1 ' lsb_bit $end
$var wire 1 ( read_write_bit $end
$var wire 1 ) start_rst $end
$var wire 1 * stop_rst $end
$var wire 1 + write_strobe $end
$var reg 4 , bit_counter [3:0] $end
$var reg 8 - index_pointer [7:0] $end
$var reg 8 . input_shift [7:0] $end
$var reg 1 / master_ack $end
$var reg 1 0 output_control $end
$var reg 8 1 output_shift [7:0] $end
$var reg 8 2 reg_00 [7:0] $end
$var reg 8 3 reg_01 [7:0] $end
$var reg 8 4 reg_02 [7:0] $end
$var reg 8 5 reg_03 [7:0] $end
$var reg 1 6 start_detect $end
$var reg 1 7 start_resetter $end
$var reg 3 8 state [2:0] $end
$var reg 1 9 stop_detect $end
$var reg 1 : stop_resetter $end
$upscope $end
$upscope $end
$enddefinitions $end
#0
$dumpvars
x:
19
bx 8
x7
x6
bx 5
bx 4
bx 3
bx 2
bx 1
x0
x/
bx .
bx -
bx ,
x+
x*
x)
x(
x'
x&
x%
x$
1#
1"
0!
$end
#2
0+
1$
06
09
b0 8
b0 -
b0 5
b0 4
b0 3
b0 2
10
0:
07
1)
1*
1!
#4
0)
0*
0!
#50
0'
0%
16
0#
#60
b1 8
b0 ,
bx0 1
1#
0"
#70
06
1)
1(
17
bx1 .
1"
#80
bx00 1
b1 ,
0#
0"
#90
0(
0)
bx10 .
07
1"
#100
b10 ,
bx000 1
1#
0"
#110
0&
1(
bx101 .
1"
#120
bx0000 1
b11 ,
0#
0"
#130
x&
0(
bx1010 .
1"
#140
b100 ,
bx00000 1
1#
0"
#150
0&
1(
bx10101 .
1"
#160
bx000000 1
b101 ,
0#
0"
#170
x&
0(
bx101010 .
1"
#180
b110 ,
bx0000000 1
1#
0"
#190
0&
1(
bx1010101 .
1"
#200
1'
b0 1
b111 ,
0#
0"
#210
1&
0(
b10101010 .
1"
#220
0$
0'
1%
00
b1000 ,
0"
#230
1/
1"
#240
1$
0%
b11 8
b1 -
10
b0 ,
0"
#250
0&
b1010100 .
1"
#260
b1 ,
0"
#270
b10101000 .
1"
#280
b10 ,
0"
#290
b1010000 .
1"
#300
b11 ,
0"
#310
b10100000 .
1"
#320
b100 ,
0"
#330
b1000000 .
1"
#340
b101 ,
0"
#350
b10000000 .
1"
#360
b110 ,
0"
#370
b0 .
1"
#380
1'
b111 ,
1#
0"
#390
1(
b1 .
1"
#400
0$
0'
1%
00
b1000 ,
0"
#410
0/
1"
#420
1$
0%
10
b100 8
b0 ,
0"
#430
b11 .
1"
#440
b1 ,
0"
#450
b111 .
1"
#460
b10 ,
0#
0"
#470
0(
b1110 .
1"
#480
b11 ,
0"
#490
b11100 .
1"
#500
b100 ,
1#
0"
#510
1(
b111001 .
1"
#520
b101 ,
0#
0"
#530
0(
b1110010 .
1"
#540
b110 ,
1#
0"
#550
1(
b11100101 .
1"
#560
1'
b111 ,
0#
0"
#570
0(
b11001010 .
1"
#580
1+
0$
0'
1%
00
b1000 ,
0"
#590
1/
1"
#600
0+
1$
0%
b10 -
b11001010 3
10
b0 ,
0"
#610
b10010100 .
1"
#620
b1 ,
0"
#630
b101000 .
1"
#640
b10 ,
1#
0"
#650
1(
b1010001 .
1"
#660
b11 ,
0"
#670
b10100011 .
1"
#680
b100 ,
0#
0"
#690
0(
b1000110 .
1"
#700
b101 ,
1#
0"
#710
1(
b10001101 .
1"
#720
b110 ,
0#
0"
#730
0(
b11010 .
1"
#740
1'
b111 ,
1#
0"
#750
1(
b110101 .
1"
#760
1+
0$
0'
1%
00
b1000 ,
0"
#770
0/
1"
#780
0+
1$
0%
10
b110101 4
b11 -
b0 ,
0#
0"
#790
0(
b1101010 .
1"
#794
19
1#
#850
16
0#
#860
09
b1 8
b0 -
1#
0"
#870
06
1(
1)
b11010101 .
17
1"
#880
b1 ,
0#
0"
#890
0)
1&
0(
07
b10101010 .
1"
#900
b10 ,
1#
0"
#910
0&
1(
b1010101 .
1"
#920
b11 ,
0#
0"
#930
1&
0(
b10101010 .
1"
#940
b100 ,
1#
0"
#950
0&
1(
b1010101 .
1"
#960
b101 ,
0#
0"
#970
1&
0(
b10101010 .
1"
#980
b110 ,
1#
0"
#990
0&
1(
b1010101 .
1"
#1000
1'
b111 ,
0#
0"
#1010
1&
0(
b10101010 .
1"
#1020
0$
0'
1%
00
b1000 ,
0"
#1030
1/
1"
#1040
1$
0%
10
b1 -
b11 8
b0 ,
0"
#1050
0&
b1010100 .
1"
#1060
b1 ,
0"
#1070
b10101000 .
1"
#1080
b10 ,
0"
#1090
b1010000 .
1"
#1100
b11 ,
0"
#1110
b10100000 .
1"
#1120
b100 ,
0"
#1130
b1000000 .
1"
#1140
b101 ,
0"
#1150
b10000000 .
1"
#1160
b110 ,
0"
#1170
b0 .
1"
#1180
1'
b111 ,
1#
0"
#1190
1(
b1 .
1"
#1200
0$
0'
1%
00
b1000 ,
b11001010 1
0"
#1210
0/
1"
#1220
1$
0%
b100 8
10
b10010100 1
b0 ,
0"
#1230
b11 .
1"
#1240
b1 ,
b101000 1
0#
0"
#1250
0(
b110 .
1"
#1260
b1010000 1
b10 ,
0"
#1270
b1100 .
1"
#1280
b11 ,
b10100000 1
0"
#1290
b11000 .
1"
#1300
b1000000 1
b100 ,
0"
#1310
b110000 .
1"
#1320
b101 ,
b10000000 1
0"
#1330
b1100000 .
1"
#1340
b0 1
b110 ,
0"
#1350
b11000000 .
1"
#1360
1'
b111 ,
1#
0"
#1370
1(
b10000001 .
1"
#1380
1+
0$
0'
1%
00
b11001010 1
b1000 ,
0"
#1390
1"
#1400
0+
1$
0%
10
b10000001 3
b10 -
b0 ,
b10010100 1
0#
0"
#1410
0(
b10 .
1"
#1420
b101000 1
b1 ,
1#
0"
#1430
1(
b101 .
1"
#1440
b10 ,
b1010000 1
0"
#1450
b1011 .
1"
#1460
b10100000 1
b11 ,
0"
#1470
b10111 .
1"
#1480
b100 ,
b1000000 1
0#
0"
#1490
0(
b101110 .
1"
#1500
b10000000 1
b101 ,
0"
#1510
b1011100 .
1"
#1520
b110 ,
b0 1
1#
0"
#1530
1(
b10111001 .
1"
#1540
1'
b111 ,
0"
#1550
b1110011 .
1"
#1560
1+
0$
0'
1%
00
b1000 ,
b110101 1
0"
#1570
1"
#1580
0+
1$
0%
b11 -
b1110011 4
10
b1101010 1
b0 ,
0#
0"
#1590
0(
b11100110 .
1"
#1594
19
1#
#1650
16
0#
#1660
09
b0 -
b1 8
b11010100 1
1#
0"
#1670
06
1)
1(
17
b11001101 .
1"
#1680
b10101000 1
b1 ,
0#
0"
#1690
0(
0)
b10011010 .
07
1"
#1700
b10 ,
b1010000 1
1#
0"
#1710
1(
b110101 .
1"
#1720
b10100000 1
b11 ,
0#
0"
#1730
0(
b1101010 .
1"
#1740
b100 ,
b1000000 1
1#
0"
#1750
1(
b11010101 .
1"
#1760
b10000000 1
b101 ,
0#
0"
#1770
1&
0(
b10101010 .
1"
#1780
b110 ,
b0 1
1#
0"
#1790
0&
1(
b1010101 .
1"
#1800
1'
b111 ,
0#
0"
#1810
1&
0(
b10101010 .
1"
#1820
0$
0'
1%
00
b1000 ,
0"
#1830
1/
1"
#1840
1$
0%
b11 8
b1 -
10
b0 ,
0"
#1850
0&
b1010100 .
1"
#1860
b1 ,
0"
#1870
b10101000 .
1"
#1880
b10 ,
0"
#1890
b1010000 .
1"
#1900
b11 ,
0"
#1910
b10100000 .
1"
#1920
b100 ,
0"
#1930
b1000000 .
1"
#1940
b101 ,
0"
#1950
b10000000 .
1"
#1960
b110 ,
0"
#1970
b0 .
1"
#1980
1'
b111 ,
1#
0"
#1990
1(
b1 .
1"
#2000
0$
0'
1%
00
b10000001 1
b1000 ,
0"
#2010
0/
1"
#2020
1$
0%
10
b100 8
b0 ,
b10 1
0"
#2030
b11 .
1"
#2040
16
0#
#2050
b1 8
b100 1
1#
0"
#2060
06
1)
b111 .
17
1"
#2070
b1 ,
b1000 1
0#
0"
#2080
0)
0(
07
b1110 .
1"
#2090
b10000 1
b10 ,
1#
0"
#2100
1(
b11101 .
1"
#2110
b11 ,
b100000 1
0#
0"
#2120
0(
b111010 .
1"
#2130
b1000000 1
b100 ,
1#
0"
#2140
1(
b1110101 .
1"
#2150
b101 ,
b10000000 1
0#
0"
#2160
0(
b11101010 .
1"
#2170
b0 1
b110 ,
1#
0"
#2180
1(
b11010101 .
1"
#2190
1'
b111 ,
0"
#2200
1&
b10101011 .
1"
#2210
0$
0'
1%
00
b10000001 1
b1000 ,
0"
#2220
1"
#2230
1$
0%
10
b10 -
b10 8
b0 ,
b10 1
0"
#2240
0&
b1010111 .
1"
#2250
0$
00
b100 1
b1 ,
0"
#2260
b10101111 .
1"
#2270
b10 ,
b1000 1
0"
#2280
b1011111 .
1"
#2290
b10000 1
b11 ,
0"
#2300
b10111111 .
1"
#2310
b100 ,
b100000 1
0"
#2320
b1111111 .
1"
#2330
b1000000 1
b101 ,
0"
#2340
b11111111 .
1"
#2350
b110 ,
b10000000 1
0"
#2360
1"
#2370
1$
1'
10
b0 1
b111 ,
0"
#2380
1"
#2390
0'
1%
b1000 ,
b1110011 1
0"
#2400
1"
#2410
0%
b0 8
b11 -
b11100110 1
b0 ,
0#
0"
#2420
0(
b11111110 .
1"
#2424
19
1#
