SAR5/sar5.v
/**************************************
* Module: SAR5
* Date:2017-05-25  
* Author: saul     
*
* Description: Succesive Approximation Register 5 bits
* 
* INPUTS:
* clk = system's clock. Registers change with posedge. The master controller should sample the outputs (sar, ready, sar_serial) with nededge 
* comp = This is the output of the analog comparator (Vin > Vdac) ? 1:0
* resetn = reset registers, active low (L)
*
* OUTPUTS:
* sar = N-bit output register to control the DAC, active high (H).
* start_ready = is set, active high (H), when the sar output contains the complete converted solution (N bits). It also flags that a
          new conversion started, and that in the next cycle sar_serial will have the MSB value available.           
* sar_serial = serial output from MSB to LSB
***************************************/

module sar5(
clk,
comp,
resetn,
sar,
sar_serial,
start_ready);

input clk;
input comp;
input resetn;
output [4:0] sar;
output sar_serial;
output start_ready;

reg [2:0] counter; 
reg [4:0] dac_test;
reg [4:0] dac;
reg sar_serial;

wire ready;

always @(posedge clk or negedge resetn) 
begin
	if (!resetn) begin
		dac <= 0;
		counter <= 5;		
	end else begin
		if (counter == 0) begin
			dac <= 0;
			counter <= 5;			
		end else begin 
			counter <= counter - 1;
			if (comp) begin
				dac[counter - 1] <= 1;
				sar_serial <= 1;
			end else begin
				dac[counter - 1] <= 0;			
				sar_serial <= 0;
			end
		end
	end
end
 
assign start_ready = (counter == 3'b101);

//dac_test 
always @(counter)
begin
	case(counter)
		3'b101:  dac_test = 5'b10000;
		3'b100:  dac_test = 5'b01000;
		3'b011:  dac_test = 5'b00100;
		3'b010:  dac_test = 5'b00010;
		3'b001:  dac_test = 5'b00001;	
		default: dac_test = 5'b00000;	
	endcase
end

assign sar = dac_test | dac;

endmodule

SAR5/sar5_tb.v
/**************************************
* Module: SAR5_tb
* Date:2017-05-25  
* Author: saul     
*
* Description: Succesive Approximation Register 5 bits
***************************************/

module sar5_tb();

//nets to drive
reg clk;
reg comp;
reg resetn;

//output wires
wire [4:0] out;

initial begin
    $dumpfile("sar5.vcd");
    $dumpvars(0,my_sar5);
    
    clk = 0;
    resetn = 0;
    comp = 0;
    #2 resetn = 1;
    #30 comp = 1;
    #80 comp = 0;
    #120 comp = 1;
    #400 $finish;
    
    
    
end


always begin
    #10 clk = ~ clk;
end


sar5 my_sar5(clk,comp,resetn,out);


endmodule

SAR5/sar5.vcd
$date
	Sat May 27 14:36:02 2017
$end
$version
	Icarus Verilog
$end
$timescale
	1s
$end
$scope module sar5_tb $end
$scope module my_sar5 $end
$var wire 1 ! clk $end
$var wire 1 " comp $end
$var wire 1 # resetn $end
$var wire 5 $ sar [4:0] $end
$var wire 1 % start_ready $end
$var reg 3 & counter [2:0] $end
$var reg 5 ' dac [4:0] $end
$var reg 5 ( dac_test [4:0] $end
$var reg 1 ) sar_serial $end
$upscope $end
$upscope $end
$enddefinitions $end
#0
$dumpvars
x)
b10000 (
b0 '
b101 &
1%
b10000 $
0#
0"
0!
$end
#2
1#
#10
b1000 $
b1000 (
0)
0%
b100 &
1!
#20
0!
#30
b100 $
b100 (
b11 &
1!
#32
1"
#40
0!
#50
b110 $
b10 (
1)
b100 '
b10 &
1!
#60
0!
#70
b111 $
b1 (
b110 '
b1 &
1!
#80
0!
#90
b0 (
b111 '
b0 &
1!
#100
0!
#110
b10000 (
b10000 $
1%
b101 &
b0 '
1!
#112
0"
#120
0!
#130
b1000 $
b1000 (
0)
0%
b100 &
1!
#140
0!
#150
b100 $
b100 (
b11 &
1!
#160
0!
#170
b10 $
b10 (
b10 &
1!
#180
0!
#190
b1 $
b1 (
b1 &
1!
#200
0!
#210
b0 $
b0 (
b0 &
1!
#220
0!
#230
b10000 $
b10000 (
1%
b101 &
1!
#232
1"
#240
0!
#250
b11000 $
b1000 (
1)
b10000 '
0%
b100 &
1!
#260
0!
#270
b11100 $
b100 (
b11000 '
b11 &
1!
#280
0!
#290
b11110 $
b10 (
b11100 '
b10 &
1!
#300
0!
#310
b11111 $
b1 (
b11110 '
b1 &
1!
#320
0!
#330
b0 (
b11111 '
b0 &
1!
#340
0!
#350
b10000 (
b10000 $
1%
b101 &
b0 '
1!
#360
0!
#370
b11000 $
b1000 (
b10000 '
0%
b100 &
1!
#380
0!
#390
b11100 $
b100 (
b11000 '
b11 &
1!
#400
0!
#410
b11110 $
b10 (
b11100 '
b10 &
1!
#420
0!
#430
b11111 $
b1 (
b11110 '
b1 &
1!
#440
0!
#450
b0 (
b11111 '
b0 &
1!
#460
0!
#470
b10000 (
b10000 $
1%
b101 &
b0 '
1!
#480
0!
#490
b11000 $
b1000 (
b10000 '
0%
b100 &
1!
#500
0!
#510
b11100 $
b100 (
b11000 '
b11 &
1!
#520
0!
#530
b11110 $
b10 (
b11100 '
b10 &
1!
#540
0!
#550
b11111 $
b1 (
b11110 '
b1 &
1!
#560
0!
#570
b0 (
b11111 '
b0 &
1!
#580
0!
#590
b10000 (
b10000 $
1%
b101 &
b0 '
1!
#600
0!
#610
b11000 $
b1000 (
b10000 '
0%
b100 &
1!
#620
0!
#630
b11100 $
b100 (
b11000 '
b11 &
1!
