Papilio/counter/counter.v
/*
*	counter example for PapilioDuo
*	Author: Saul Rodriguez
*	Date: 2016-09-13
*/

module counter(resetn,clk,en,out);

input resetn,clk,en;
output reg [25:0] out;

always @(posedge clk, negedge resetn) begin
	if (resetn == 0)
		out <= 0;
	else if (en) begin
		if (out == 5)
			out <= 0;
		else
			out <= out + 1;
	end 	
end

endmodule

Papilio/counter/counter_tb.v
/*
 * counter_tb
 */
 
 
module counter_tb();

//lines to drive
reg resetn,clk,en;

//output signals
wire [25:0] out;

initial begin
    $dumpfile("counter.vcd");
    $dumpvars(0,my_counter);
    
    resetn = 1;
    en = 0;
    clk = 0;
    
    #1 resetn = 0;
    #2 resetn = 1;
    #3 en = 1;
    #150 $finish;   
    
end

always begin
    #5 clk = ~clk;
end

counter my_counter(resetn,clk,en,out);

endmodule

Papilio/counter/counter.vcd
$date
	Tue Sep 13 20:26:44 2016
$end
$version
	Icarus Verilog
$end
$timescale
	1s
$end
$scope module counter_tb $end
$scope module my_counter $end
$var wire 1 ! clk $end
$var wire 1 " en $end
$var wire 1 # resetn $end
$var reg 26 $ out [25:0] $end
$upscope $end
$upscope $end
$enddefinitions $end
#0
$dumpvars
bx $
1#
0"
0!
$end
#1
b0 $
0#
#3
1#
#5
1!
#6
1"
#10
0!
#15
b1 $
1!
#20
0!
#25
b10 $
1!
#30
0!
#35
b11 $
1!
#40
0!
#45
b100 $
1!
#50
0!
#55
b101 $
1!
#60
0!
#65
b0 $
1!
#70
0!
#75
b1 $
1!
#80
0!
#85
b10 $
1!
#90
0!
#95
b11 $
1!
#100
0!
#105
b100 $
1!
#110
0!
#115
b101 $
1!
#120
0!
#125
b0 $
1!
#130
0!
#135
b1 $
1!
#140
0!
#145
b10 $
1!
#150
0!
#155
b11 $
1!
