Papilio/counter/counter.v
/*
*	counter example for PapilioDuo
*	Author: Saul Rodriguez
*	Date: 2016-09-13
*/

module counter(resetn,clk,en,out);

input resetn,clk,en;
output reg [25:0] out;

always @(posedge clk, negedge resetn) begin
	if (resetn == 0)
		out <= 0;
	else if (en) begin
		if (out == 5)
			out <= 0;
		else
			out <= out + 1;
	end 	
end

endmodule

Papilio/counter/FPGA/project_1/project_1.srcs/sources_1/new/top.v
`timescale 1ns / 1ps
//////////////////////////////////////////////////////////////////////////////////
// Company: 
// Engineer: 
// 
// Create Date: 09/13/2016 10:22:32 PM
// Design Name: 
// Module Name: top
// Project Name: 
// Target Devices: 
// Tool Versions: 
// Description: 
// 
// Dependencies: 
// 
// Revision:
// Revision 0.01 - File Created
// Additional Comments:
// 
//////////////////////////////////////////////////////////////////////////////////


module top(
    input RESETN,
    input CLK,
    input EN,
    output LED0,
    output LED1,
    output LED2,
    output LED3,
    output LED4,
    output LED5,
    output LED6,
    output LED7,
    output ARDUINO_RESET
    );
    
wire [25:0] aux_out;

assign ARDUINO_RESET = 0;

counter counter1(RESETN,CLK,EN,aux_out);

assign LED7 = aux_out[25];
assign LED6 = aux_out[24];
assign LED5 = aux_out[23];
assign LED4 = aux_out[22];
assign LED3 = aux_out[21];
assign LED2 = aux_out[20];
assign LED1 = aux_out[19];
assign LED0 = aux_out[18];


endmodule

Papilio/counter/FPGA/project_1/project_1.srcs/sim_1/imports/counter/counter_tb.v
/*
 * counter_tb
 */
 
 
module counter_tb();

//lines to drive
reg RESETN,CLK,EN;

//output signals
//wire [25:0] out;
wire LED0;
wire LED1;
wire LED2;
wire LED3;
wire LED4;
wire LED5;
wire LED6;
wire LED7;
wire ARDUINO_RESET;

initial begin
    $dumpfile("top.vcd");
    $dumpvars(0,my_top);
    
    RESETN = 1;
    EN = 0;
    CLK = 0;
    
    #1 RESETN = 0;
    #2 RESETN = 1;
    #3 EN = 1;
    //#640000 $finish;   
    
end

always begin
    #2 CLK = ~CLK;
end

//counter my_counter(resetn,clk,en,out);
top my_top(RESETN,CLK,EN,LED0,LED1,LED2,LED3,LED4,LED5,LED6,LED7,ARDUINO_RESET);

endmodule

Papilio/counter/FPGA/project_1/project_1.sim/sim_1/behav/top.vcd
$date
   Tue Sep 13 23:02:32 2016
$end
$version
  P.20131013
$end
$timescale
  1ps
$end
$scope module counter_tb $end
$scope module my_top $end
$var wire 1 G RESETN $end
$var wire 1 H CLK $end
$var wire 1 I EN $end
$var wire 1 $ LED0 $end
$var wire 1 % LED1 $end
$var wire 1 & LED2 $end
$var wire 1 ' LED3 $end
$var wire 1 ( LED4 $end
$var wire 1 ) LED5 $end
$var wire 1 * LED6 $end
$var wire 1 + LED7 $end
$var wire 1 , ARDUINO_RESET $end
$var wire 1 - aux_out [25] $end
$var wire 1 . aux_out [24] $end
$var wire 1 / aux_out [23] $end
$var wire 1 0 aux_out [22] $end
$var wire 1 1 aux_out [21] $end
$var wire 1 2 aux_out [20] $end
$var wire 1 3 aux_out [19] $end
$var wire 1 4 aux_out [18] $end
$var wire 1 5 aux_out [17] $end
$var wire 1 6 aux_out [16] $end
$var wire 1 7 aux_out [15] $end
$var wire 1 8 aux_out [14] $end
$var wire 1 9 aux_out [13] $end
$var wire 1 : aux_out [12] $end
$var wire 1 ; aux_out [11] $end
$var wire 1 < aux_out [10] $end
$var wire 1 = aux_out [9] $end
$var wire 1 > aux_out [8] $end
$var wire 1 ? aux_out [7] $end
$var wire 1 @ aux_out [6] $end
$var wire 1 A aux_out [5] $end
$var wire 1 B aux_out [4] $end
$var wire 1 C aux_out [3] $end
$var wire 1 D aux_out [2] $end
$var wire 1 E aux_out [1] $end
$var wire 1 F aux_out [0] $end
$scope module counter1 $end
$var wire 1 G resetn $end
$var wire 1 H clk $end
$var wire 1 I en $end
$var reg 26 J out [25:0] $end
$upscope $end
$upscope $end
$upscope $end
$enddefinitions $end
#0
$dumpvars
x*
x+
0,
xF
xE
xD
xC
xB
xA
x@
x?
x>
x=
x<
x;
x:
x9
x8
x7
x6
x5
x4
x3
x2
x1
x0
x/
x.
x-
bx J
0I
x$
x%
x&
x'
x(
x)
0H
1G
$end
#1000
0*
0+
0F
0E
0D
0C
0B
0A
0@
0?
0>
0=
0<
0;
0:
09
08
07
06
05
04
03
02
01
00
0/
0.
0-
b0 J
0$
0%
0&
0'
0(
0)
0G
#2000
1H
#3000
1G
#4000
0H
#6000
1F
b1 J
1I
1H
#8000
0H
#10000
0F
1E
b10 J
1H
#12000
0H
#14000
1F
b11 J
1H
#16000
0H
#18000
0F
0E
1D
b100 J
1H
#20000
0H
#22000
1F
b101 J
1H
#24000
0H
#26000
0F
1E
b110 J
1H
#28000
0H
#30000
1F
b111 J
1H
#32000
0H
#34000
0F
0E
0D
1C
b1000 J
1H
#36000
0H
#38000
1F
b1001 J
1H
#40000
0H
#42000
0F
1E
b1010 J
1H
#44000
0H
#46000
1F
b1011 J
1H
#48000
0H
#50000
0F
0E
1D
b1100 J
1H
#52000
0H
#54000
1F
b1101 J
1H
#56000
0H
#58000
0F
1E
b1110 J
1H
#60000
0H
#62000
1F
b1111 J
1H
#64000
0H
#66000
0F
0E
0D
0C
1B
b10000 J
1H
#68000
0H
#70000
1F
b10001 J
1H
#72000
0H
#74000
0F
1E
b10010 J
1H
#76000
0H
#78000
1F
b10011 J
1H
#80000
0H
#82000
0F
0E
1D
b10100 J
1H
#84000
0H
#86000
1F
b10101 J
1H
#88000
0H
#90000
0F
1E
b10110 J
1H
#92000
0H
#94000
1F
b10111 J
1H
#96000
0H
#98000
0F
0E
0D
1C
b11000 J
1H
#100000
0H
#102000
1F
b11001 J
1H
#104000
0H
#106000
0F
1E
b11010 J
1H
#108000
0H
#110000
1F
b11011 J
1H
#112000
0H
#114000
0F
0E
1D
b11100 J
1H
#116000
0H
#118000
1F
b11101 J
1H
#120000
0H
#122000
0F
1E
b11110 J
1H
#124000
0H
#126000
1F
b11111 J
1H
#128000
0H
#130000
0F
0E
0D
0C
0B
1A
b100000 J
1H
#132000
0H
#134000
1F
b100001 J
1H
#136000
0H
#138000
0F
1E
b100010 J
1H
#140000
0H
#142000
1F
b100011 J
1H
#144000
0H
#146000
0F
0E
1D
b100100 J
1H
#148000
0H
#150000
1F
b100101 J
1H
#152000
0H
#154000
0F
1E
b100110 J
1H
#156000
0H
#158000
1F
b100111 J
1H
#160000
0H
#162000
0F
0E
0D
1C
b101000 J
1H
#164000
0H
#166000
1F
b101001 J
1H
#168000
0H
#170000
0F
1E
b101010 J
1H
#172000
0H
#174000
1F
b101011 J
1H
#176000
0H
#178000
0F
0E
1D
b101100 J
1H
#180000
0H
#182000
1F
b101101 J
1H
#184000
0H
#186000
0F
1E
b101110 J
1H
#188000
0H
#190000
1F
b101111 J
1H
#192000
0H
#194000
0F
0E
0D
0C
1B
b110000 J
1H
#196000
0H
#198000
1F
b110001 J
1H
#200000
0H
#202000
0F
1E
b110010 J
1H
#204000
0H
#206000
1F
b110011 J
1H
#208000
0H
#210000
0F
0E
1D
b110100 J
1H
#212000
0H
#214000
1F
b110101 J
1H
#216000
0H
#218000
0F
1E
b110110 J
1H
#220000
0H
#222000
1F
b110111 J
1H
#224000
0H
#226000
0F
0E
0D
1C
b111000 J
1H
#228000
0H
#230000
1F
b111001 J
1H
#232000
0H
#234000
0F
1E
b111010 J
1H
#236000
0H
#238000
1F
b111011 J
1H
#240000
0H
#242000
0F
0E
1D
b111100 J
1H
#244000
0H
#246000
1F
b111101 J
1H
#248000
0H
#250000
0F
1E
b111110 J
1H
#252000
0H
#254000
1F
b111111 J
1H
#256000
0H
#258000
0F
0E
0D
0C
0B
0A
1@
b1000000 J
1H
#260000
0H
#262000
1F
b1000001 J
1H
#264000
0H
#266000
0F
1E
b1000010 J
1H
#268000
0H
#270000
1F
b1000011 J
1H
#272000
0H
#274000
0F
0E
1D
b1000100 J
1H
#276000
0H
#278000
1F
b1000101 J
1H
#280000
0H
#282000
0F
1E
b1000110 J
1H
#284000
0H
#286000
1F
b1000111 J
1H
#288000
0H
#290000
0F
0E
0D
1C
b1001000 J
1H
#292000
0H
#294000
1F
b1001001 J
1H
#296000
0H
#298000
0F
1E
b1001010 J
1H
#300000
0H
#302000
1F
b1001011 J
1H
#304000
0H
#306000
0F
0E
1D
b1001100 J
1H
#308000
0H
#310000
1F
b1001101 J
1H
#312000
0H
#314000
0F
1E
b1001110 J
1H
#316000
0H
#318000
1F
b1001111 J
1H
#320000
0H
#322000
0F
0E
0D
0C
1B
b1010000 J
1H
#324000
0H
#326000
1F
b1010001 J
1H
#328000
0H
#330000
0F
1E
b1010010 J
1H
#332000
0H
#334000
1F
b1010011 J
1H
#336000
0H
#338000
0F
0E
1D
b1010100 J
1H
#340000
0H
#342000
1F
b1010101 J
1H
#344000
0H
#346000
0F
1E
b1010110 J
1H
#348000
0H
#350000
1F
b1010111 J
1H
#352000
0H
#354000
0F
0E
0D
1C
b1011000 J
1H
#356000
0H
#358000
1F
b1011001 J
1H
#360000
0H
#362000
0F
1E
b1011010 J
1H
#364000
0H
#366000
1F
b1011011 J
1H
#368000
0H
#370000
0F
0E
1D
b1011100 J
1H
#372000
0H
#374000
1F
b1011101 J
1H
#376000
0H
#378000
0F
1E
b1011110 J
1H
#380000
0H
#382000
1F
b1011111 J
1H
#384000
0H
#386000
0F
0E
0D
0C
0B
1A
b1100000 J
1H
#388000
0H
#390000
1F
b1100001 J
1H
#392000
0H
#394000
0F
1E
b1100010 J
1H
#396000
0H
#398000
1F
b1100011 J
1H
#400000
0H
#402000
0F
0E
1D
b1100100 J
1H
#404000
0H
#406000
1F
b1100101 J
1H
#408000
0H
#410000
0F
1E
b1100110 J
1H
#412000
0H
#414000
1F
b1100111 J
1H
#416000
0H
#418000
0F
0E
0D
1C
b1101000 J
1H
#420000
0H
#422000
1F
b1101001 J
1H
#424000
0H
#426000
0F
1E
b1101010 J
1H
#428000
0H
#430000
1F
b1101011 J
1H
#432000
0H
#434000
0F
0E
1D
b1101100 J
1H
#436000
0H
#438000
1F
b1101101 J
1H
#440000
0H
#442000
0F
1E
b1101110 J
1H
#444000
0H
#446000
1F
b1101111 J
1H
#448000
0H
#450000
0F
0E
0D
0C
1B
b1110000 J
1H
#452000
0H
#454000
1F
b1110001 J
1H
#456000
0H
#458000
0F
1E
b1110010 J
1H
#460000
0H
#462000
1F
b1110011 J
1H
#464000
0H
#466000
0F
0E
1D
b1110100 J
1H
#468000
0H
#470000
1F
b1110101 J
1H
#472000
0H
#474000
0F
1E
b1110110 J
1H
#476000
0H
#478000
1F
b1110111 J
1H
#480000
0H
#482000
0F
0E
0D
1C
b1111000 J
1H
#484000
0H
#486000
1F
b1111001 J
1H
#488000
0H
#490000
0F
1E
b1111010 J
1H
#492000
0H
#494000
1F
b1111011 J
1H
#496000
0H
#498000
0F
0E
1D
b1111100 J
1H
#500000
0H
#502000
1F
b1111101 J
1H
#504000
0H
#506000
0F
1E
b1111110 J
1H
#508000
0H
#510000
1F
b1111111 J
1H
#512000
0H
#514000
0F
0E
0D
0C
0B
0A
0@
1?
b10000000 J
1H
#516000
0H
#518000
1F
b10000001 J
1H
#520000
0H
#522000
0F
1E
b10000010 J
1H
#524000
0H
#526000
1F
b10000011 J
1H
#528000
0H
#530000
0F
0E
1D
b10000100 J
1H
#532000
0H
#534000
1F
b10000101 J
1H
#536000
0H
#538000
0F
1E
b10000110 J
1H
#540000
0H
#542000
1F
b10000111 J
1H
#544000
0H
#546000
0F
0E
0D
1C
b10001000 J
1H
#548000
0H
#550000
1F
b10001001 J
1H
#552000
0H
#554000
0F
1E
b10001010 J
1H
#556000
0H
#558000
1F
b10001011 J
1H
#560000
0H
#562000
0F
0E
1D
b10001100 J
1H
#564000
0H
#566000
1F
b10001101 J
1H
#568000
0H
#570000
0F
1E
b10001110 J
1H
#572000
0H
#574000
1F
b10001111 J
1H
#576000
0H
#578000
0F
0E
0D
0C
1B
b10010000 J
1H
#580000
0H
#582000
1F
b10010001 J
1H
#584000
0H
#586000
0F
1E
b10010010 J
1H
#588000
0H
#590000
1F
b10010011 J
1H
#592000
0H
#594000
0F
0E
1D
b10010100 J
1H
#596000
0H
#598000
1F
b10010101 J
1H
#600000
0H
#602000
0F
1E
b10010110 J
1H
#604000
0H
#606000
1F
b10010111 J
1H
#608000
0H
#610000
0F
0E
0D
1C
b10011000 J
1H
#612000
0H
#614000
1F
b10011001 J
1H
#616000
0H
#618000
0F
1E
b10011010 J
1H
#620000
0H
#622000
1F
b10011011 J
1H
#624000
0H
#626000
0F
0E
1D
b10011100 J
1H
#628000
0H
#630000
1F
b10011101 J
1H
#632000
0H
#634000
0F
1E
b10011110 J
1H
#636000
0H
#638000
1F
b10011111 J
1H
#640000
0H
#642000
0F
0E
0D
0C
0B
1A
b10100000 J
1H
#644000
0H
#646000
1F
b10100001 J
1H
#648000
0H
#650000
0F
1E
b10100010 J
1H
#652000
0H
#654000
1F
b10100011 J
1H
#656000
0H
#658000
0F
0E
1D
b10100100 J
1H
#660000
0H
#662000
1F
b10100101 J
1H
#664000
0H
#666000
0F
1E
b10100110 J
1H
#668000
0H
#670000
1F
b10100111 J
1H
#672000
0H
#674000
0F
0E
0D
1C
b10101000 J
1H
#676000
0H
#678000
1F
b10101001 J
1H
#680000
0H
#682000
0F
1E
b10101010 J
1H
#684000
0H
#686000
1F
b10101011 J
1H
#688000
0H
#690000
0F
0E
1D
b10101100 J
1H
#692000
0H
#694000
1F
b10101101 J
1H
#696000
0H
#698000
0F
1E
b10101110 J
1H
#700000
0H
#702000
1F
b10101111 J
1H
#704000
0H
#706000
0F
0E
0D
0C
1B
b10110000 J
1H
#708000
0H
#710000
1F
b10110001 J
1H
#712000
0H
#714000
0F
1E
b10110010 J
1H
#716000
0H
#718000
1F
b10110011 J
1H
#720000
0H
#722000
0F
0E
1D
b10110100 J
1H
#724000
0H
#726000
1F
b10110101 J
1H
#728000
0H
#730000
0F
1E
b10110110 J
1H
#732000
0H
#734000
1F
b10110111 J
1H
#736000
0H
#738000
0F
0E
0D
1C
b10111000 J
1H
#740000
0H
#742000
1F
b10111001 J
1H
#744000
0H
#746000
0F
1E
b10111010 J
1H
#748000
0H
#750000
1F
b10111011 J
1H
#752000
0H
#754000
0F
0E
1D
b10111100 J
1H
#756000
0H
#758000
1F
b10111101 J
1H
#760000
0H
#762000
0F
1E
b10111110 J
1H
#764000
0H
#766000
1F
b10111111 J
1H
#768000
0H
#770000
0F
0E
0D
0C
0B
0A
1@
b11000000 J
1H
#772000
0H
#774000
1F
b11000001 J
1H
#776000
0H
#778000
0F
1E
b11000010 J
1H
#780000
0H
#782000
1F
b11000011 J
1H
#784000
0H
#786000
0F
0E
1D
b11000100 J
1H
#788000
0H
#790000
1F
b11000101 J
1H
#792000
0H
#794000
0F
1E
b11000110 J
1H
#796000
0H
#798000
1F
b11000111 J
1H
#800000
0H
#802000
0F
0E
0D
1C
b11001000 J
1H
#804000
0H
#806000
1F
b11001001 J
1H
#808000
0H
#810000
0F
1E
b11001010 J
1H
#812000
0H
#814000
1F
b11001011 J
1H
#816000
0H
#818000
0F
0E
1D
b11001100 J
1H
#820000
0H
#822000
1F
b11001101 J
1H
#824000
0H
#826000
0F
1E
b11001110 J
1H
#828000
0H
#830000
1F
b11001111 J
1H
#832000
0H
#834000
0F
0E
0D
0C
1B
b11010000 J
1H
#836000
0H
#838000
1F
b11010001 J
1H
#840000
0H
#842000
0F
1E
b11010010 J
1H
#844000
0H
#846000
1F
b11010011 J
1H
#848000
0H
#850000
0F
0E
1D
b11010100 J
1H
#852000
0H
#854000
1F
b11010101 J
1H
#856000
0H
#858000
0F
1E
b11010110 J
1H
#860000
0H
#862000
1F
b11010111 J
1H
#864000
0H
#866000
0F
0E
0D
1C
b11011000 J
1H
#868000
0H
#870000
1F
b11011001 J
1H
#872000
0H
#874000
0F
1E
b11011010 J
1H
#876000
0H
#878000
1F
b11011011 J
1H
#880000
0H
#882000
0F
0E
1D
b11011100 J
1H
#884000
0H
#886000
1F
b11011101 J
1H
#888000
0H
#890000
0F
1E
b11011110 J
1H
#892000
0H
#894000
1F
b11011111 J
1H
#896000
0H
#898000
0F
0E
0D
0C
0B
1A
b11100000 J
1H
#900000
0H
#902000
1F
b11100001 J
1H
#904000
0H
#906000
0F
1E
b11100010 J
1H
#908000
0H
#910000
1F
b11100011 J
1H
#912000
0H
#914000
0F
0E
1D
b11100100 J
1H
#916000
0H
#918000
1F
b11100101 J
1H
#920000
0H
#922000
0F
1E
b11100110 J
1H
#924000
0H
#926000
1F
b11100111 J
1H
#928000
0H
#930000
0F
0E
0D
1C
b11101000 J
1H
#932000
0H
#934000
1F
b11101001 J
1H
#936000
0H
#938000
0F
1E
b11101010 J
1H
#940000
0H
#942000
1F
b11101011 J
1H
#944000
0H
#946000
0F
0E
1D
b11101100 J
1H
#948000
0H
#950000
1F
b11101101 J
1H
#952000
0H
#954000
0F
1E
b11101110 J
1H
#956000
0H
#958000
1F
b11101111 J
1H
#960000
0H
#962000
0F
0E
0D
0C
1B
b11110000 J
1H
#964000
0H
#966000
1F
b11110001 J
1H
#968000
0H
#970000
0F
1E
b11110010 J
1H
#972000
0H
#974000
1F
b11110011 J
1H
#976000
0H
#978000
0F
0E
1D
b11110100 J
1H
#980000
0H
#982000
1F
b11110101 J
1H
#984000
0H
#986000
0F
1E
b11110110 J
1H
#988000
0H
#990000
1F
b11110111 J
1H
#992000
0H
#994000
0F
0E
0D
1C
b11111000 J
1H
#996000
0H
#998000
1F
b11111001 J
1H
#1000000
0H
#1002000
0F
1E
b11111010 J
1H
#1004000
0H
#1006000
1F
b11111011 J
1H
#1008000
0H
#1010000
0F
0E
1D
b11111100 J
1H
#1012000
0H
#1014000
1F
b11111101 J
1H
#1016000
0H
#1018000
0F
1E
b11111110 J
1H
#1020000
0H
#1022000
1F
b11111111 J
1H
#1024000
0H
#1026000
0F
0E
0D
0C
0B
0A
0@
0?
1>
b100000000 J
1$
1H
#1028000
0H
#1030000
1F
b100000001 J
1H
#1032000
0H
#1034000
0F
1E
b100000010 J
1H
#1036000
0H
#1038000
1F
b100000011 J
1H
#1040000
0H
#1042000
0F
0E
1D
b100000100 J
1H
#1044000
0H
#1046000
1F
b100000101 J
1H
#1048000
0H
#1050000
0F
1E
b100000110 J
1H
#1052000
0H
#1054000
1F
b100000111 J
1H
#1056000
0H
#1058000
0F
0E
0D
1C
b100001000 J
1H
#1060000
0H
#1062000
1F
b100001001 J
1H
#1064000
0H
#1066000
0F
1E
b100001010 J
1H
#1068000
0H
#1070000
1F
b100001011 J
1H
#1072000
0H
#1074000
0F
0E
1D
b100001100 J
1H
#1076000
0H
#1078000
1F
b100001101 J
1H
#1080000
0H
#1082000
0F
1E
b100001110 J
1H
#1084000
0H
#1086000
1F
b100001111 J
1H
#1088000
0H
#1090000
0F
0E
0D
0C
1B
b100010000 J
1H
#1092000
0H
#1094000
1F
b100010001 J
1H
#1096000
0H
#1098000
0F
1E
b100010010 J
1H
#1100000
0H
#1102000
1F
b100010011 J
1H
#1104000
0H
#1106000
0F
0E
1D
b100010100 J
1H
#1108000
0H
#1110000
1F
b100010101 J
1H
#1112000
0H
#1114000
0F
1E
b100010110 J
1H
#1116000
0H
#1118000
1F
b100010111 J
1H
#1120000
0H
#1122000
0F
0E
0D
1C
b100011000 J
1H
#1124000
0H
#1126000
1F
b100011001 J
1H
#1128000
0H
#1130000
0F
1E
b100011010 J
1H
#1132000
0H
#1134000
1F
b100011011 J
1H
#1136000
0H
#1138000
0F
0E
1D
b100011100 J
1H
#1140000
0H
#1142000
1F
b100011101 J
1H
#1144000
0H
#1146000
0F
1E
b100011110 J
1H
#1148000
0H
#1150000
1F
b100011111 J
1H
#1152000
0H
#1154000
0F
0E
0D
0C
0B
1A
b100100000 J
1H
#1156000
0H
#1158000
1F
b100100001 J
1H
#1160000
0H
#1162000
0F
1E
b100100010 J
1H
#1164000
0H
#1166000
1F
b100100011 J
1H
#1168000
0H
#1170000
0F
0E
1D
b100100100 J
1H
#1172000
0H
#1174000
1F
b100100101 J
1H
#1176000
0H
#1178000
0F
1E
b100100110 J
1H
#1180000
0H
#1182000
1F
b100100111 J
1H
#1184000
0H
#1186000
0F
0E
0D
1C
b100101000 J
1H
#1188000
0H
#1190000
1F
b100101001 J
1H
#1192000
0H
#1194000
0F
1E
b100101010 J
1H
#1196000
0H
#1198000
1F
b100101011 J
1H
#1200000
0H
#1202000
0F
0E
1D
b100101100 J
1H
#1204000
0H
#1206000
1F
b100101101 J
1H
#1208000
0H
#1210000
0F
1E
b100101110 J
1H
#1212000
0H
#1214000
1F
b100101111 J
1H
#1216000
0H
#1218000
0F
0E
0D
0C
1B
b100110000 J
1H
#1220000
0H
#1222000
1F
b100110001 J
1H
#1224000
0H
#1226000
0F
1E
b100110010 J
1H
#1228000
0H
#1230000
1F
b100110011 J
1H
#1232000
0H
#1234000
0F
0E
1D
b100110100 J
1H
#1236000
0H
#1238000
1F
b100110101 J
1H
#1240000
0H
#1242000
0F
1E
b100110110 J
1H
#1244000
0H
#1246000
1F
b100110111 J
1H
#1248000
0H
#1250000
0F
0E
0D
1C
b100111000 J
1H
#1252000
0H
#1254000
1F
b100111001 J
1H
#1256000
0H
#1258000
0F
1E
b100111010 J
1H
#1260000
0H
#1262000
1F
b100111011 J
1H
#1264000
0H
#1266000
0F
0E
1D
b100111100 J
1H
#1268000
0H
#1270000
1F
b100111101 J
1H
#1272000
0H
#1274000
0F
1E
b100111110 J
1H
#1276000
0H
#1278000
1F
b100111111 J
1H
#1280000
0H
#1282000
0F
0E
0D
0C
0B
0A
1@
b101000000 J
1H
#1284000
0H
#1286000
1F
b101000001 J
1H
#1288000
0H
#1290000
0F
1E
b101000010 J
1H
#1292000
0H
#1294000
1F
b101000011 J
1H
#1296000
0H
#1298000
0F
0E
1D
b101000100 J
1H
#1300000
0H
#1302000
1F
b101000101 J
1H
#1304000
0H
#1306000
0F
1E
b101000110 J
1H
#1308000
0H
#1310000
1F
b101000111 J
1H
#1312000
0H
#1314000
0F
0E
0D
1C
b101001000 J
1H
#1316000
0H
#1318000
1F
b101001001 J
1H
#1320000
0H
#1322000
0F
1E
b101001010 J
1H
#1324000
0H
#1326000
1F
b101001011 J
1H
#1328000
0H
#1330000
0F
0E
1D
b101001100 J
1H
#1332000
0H
#1334000
1F
b101001101 J
1H
#1336000
0H
#1338000
0F
1E
b101001110 J
1H
#1340000
0H
#1342000
1F
b101001111 J
1H
#1344000
0H
#1346000
0F
0E
0D
0C
1B
b101010000 J
1H
#1348000
0H
#1350000
1F
b101010001 J
1H
#1352000
0H
#1354000
0F
1E
b101010010 J
1H
#1356000
0H
#1358000
1F
b101010011 J
1H
#1360000
0H
#1362000
0F
0E
1D
b101010100 J
1H
#1364000
0H
#1366000
1F
b101010101 J
1H
#1368000
0H
#1370000
0F
1E
b101010110 J
1H
#1372000
0H
#1374000
1F
b101010111 J
1H
#1376000
0H
#1378000
0F
0E
0D
1C
b101011000 J
1H
#1380000
0H
#1382000
1F
b101011001 J
1H
#1384000
0H
#1386000
0F
1E
b101011010 J
1H
#1388000
0H
#1390000
1F
b101011011 J
1H
#1392000
0H
#1394000
0F
0E
1D
b101011100 J
1H
#1396000
0H
#1398000
1F
b101011101 J
1H
#1400000
0H
#1402000
0F
1E
b101011110 J
1H
#1404000
0H
#1406000
1F
b101011111 J
1H
#1408000
0H
#1410000
0F
0E
0D
0C
0B
1A
b101100000 J
1H
#1412000
0H
#1414000
1F
b101100001 J
1H
#1416000
0H
#1418000
0F
1E
b101100010 J
1H
#1420000
0H
#1422000
1F
b101100011 J
1H
#1424000
0H
#1426000
0F
0E
1D
b101100100 J
1H
#1428000
0H
#1430000
1F
b101100101 J
1H
#1432000
0H
#1434000
0F
1E
b101100110 J
1H
#1436000
0H
#1438000
1F
b101100111 J
1H
#1440000
0H
#1442000
0F
0E
0D
1C
b101101000 J
1H
#1444000
0H
#1446000
1F
b101101001 J
1H
#1448000
0H
#1450000
0F
1E
b101101010 J
1H
#1452000
0H
#1454000
1F
b101101011 J
1H
#1456000
0H
#1458000
0F
0E
1D
b101101100 J
1H
#1460000
0H
#1462000
1F
b101101101 J
1H
#1464000
0H
#1466000
0F
1E
b101101110 J
1H
#1468000
0H
#1470000
1F
b101101111 J
1H
#1472000
0H
#1474000
0F
0E
0D
0C
1B
b101110000 J
1H
#1476000
0H
#1478000
1F
b101110001 J
1H
#1480000
0H
#1482000
0F
1E
b101110010 J
1H
#1484000
0H
#1486000
1F
b101110011 J
1H
#1488000
0H
#1490000
0F
0E
1D
b101110100 J
1H
#1492000
0H
#1494000
1F
b101110101 J
1H
#1496000
0H
#1498000
0F
1E
b101110110 J
1H
#1500000
0H
#1502000
1F
b101110111 J
1H
#1504000
0H
#1506000
0F
0E
0D
1C
b101111000 J
1H
#1508000
0H
#1510000
1F
b101111001 J
1H
#1512000
0H
#1514000
0F
1E
b101111010 J
1H
#1516000
0H
#1518000
1F
b101111011 J
1H
#1520000
0H
#1522000
0F
0E
1D
b101111100 J
1H
#1524000
0H
#1526000
1F
b101111101 J
1H
#1528000
0H
#1530000
0F
1E
b101111110 J
1H
#1532000
0H
#1534000
1F
b101111111 J
1H
#1536000
0H
#1538000
0F
0E
0D
0C
0B
0A
0@
1?
b110000000 J
1H
#1540000
0H
#1542000
1F
b110000001 J
1H
#1544000
0H
#1546000
0F
1E
b110000010 J
1H
#1548000
0H
#1550000
1F
b110000011 J
1H
#1552000
0H
#1554000
0F
0E
1D
b110000100 J
1H
#1556000
0H
#1558000
1F
b110000101 J
1H
#1560000
0H
#1562000
0F
1E
b110000110 J
1H
#1564000
0H
#1566000
1F
b110000111 J
1H
#1568000
0H
#1570000
0F
0E
0D
1C
b110001000 J
1H
#1572000
0H
#1574000
1F
b110001001 J
1H
#1576000
0H
#1578000
0F
1E
b110001010 J
1H
#1580000
0H
#1582000
1F
b110001011 J
1H
#1584000
0H
#1586000
0F
0E
1D
b110001100 J
1H
#1588000
0H
#1590000
1F
b110001101 J
1H
#1592000
0H
#1594000
0F
1E
b110001110 J
1H
#1596000
0H
#1598000
1F
b110001111 J
1H
#1600000
0H
#1602000
0F
0E
0D
0C
1B
b110010000 J
1H
#1604000
0H
#1606000
1F
b110010001 J
1H
#1608000
0H
#1610000
0F
1E
b110010010 J
1H
#1612000
0H
#1614000
1F
b110010011 J
1H
#1616000
0H
#1618000
0F
0E
1D
b110010100 J
1H
#1620000
0H
#1622000
1F
b110010101 J
1H
#1624000
0H
#1626000
0F
1E
b110010110 J
1H
#1628000
0H
#1630000
1F
b110010111 J
1H
#1632000
0H
#1634000
0F
0E
0D
1C
b110011000 J
1H
#1636000
0H
#1638000
1F
b110011001 J
1H
#1640000
0H
#1642000
0F
1E
b110011010 J
1H
#1644000
0H
#1646000
1F
b110011011 J
1H
#1648000
0H
#1650000
0F
0E
1D
b110011100 J
1H
#1652000
0H
#1654000
1F
b110011101 J
1H
#1656000
0H
#1658000
0F
1E
b110011110 J
1H
#1660000
0H
#1662000
1F
b110011111 J
1H
#1664000
0H
#1666000
0F
0E
0D
0C
0B
1A
b110100000 J
1H
#1668000
0H
#1670000
1F
b110100001 J
1H
#1672000
0H
#1674000
0F
1E
b110100010 J
1H
#1676000
0H
#1678000
1F
b110100011 J
1H
#1680000
0H
#1682000
0F
0E
1D
b110100100 J
1H
#1684000
0H
#1686000
1F
b110100101 J
1H
#1688000
0H
#1690000
0F
1E
b110100110 J
1H
#1692000
0H
#1694000
1F
b110100111 J
1H
#1696000
0H
#1698000
0F
0E
0D
1C
b110101000 J
1H
#1700000
0H
#1702000
1F
b110101001 J
1H
#1704000
0H
#1706000
0F
1E
b110101010 J
1H
#1708000
0H
#1710000
1F
b110101011 J
1H
#1712000
0H
#1714000
0F
0E
1D
b110101100 J
1H
#1716000
0H
#1718000
1F
b110101101 J
1H
#1720000
0H
#1722000
0F
1E
b110101110 J
1H
#1724000
0H
#1726000
1F
b110101111 J
1H
#1728000
0H
#1730000
0F
0E
0D
0C
1B
b110110000 J
1H
#1732000
0H
#1734000
1F
b110110001 J
1H
#1736000
0H
#1738000
0F
1E
b110110010 J
1H
#1740000
0H
#1742000
1F
b110110011 J
1H
#1744000
0H
#1746000
0F
0E
1D
b110110100 J
1H
#1748000
0H
#1750000
1F
b110110101 J
1H
#1752000
0H
#1754000
0F
1E
b110110110 J
1H
#1756000
0H
#1758000
1F
b110110111 J
1H
#1760000
0H
#1762000
0F
0E
0D
1C
b110111000 J
1H
#1764000
0H
#1766000
1F
b110111001 J
1H
#1768000
0H
#1770000
0F
1E
b110111010 J
1H
#1772000
0H
#1774000
1F
b110111011 J
1H
#1776000
0H
#1778000
0F
0E
1D
b110111100 J
1H
#1780000
0H
#1782000
1F
b110111101 J
1H
#1784000
0H
#1786000
0F
1E
b110111110 J
1H
#1788000
0H
#1790000
1F
b110111111 J
1H
#1792000
0H
#1794000
0F
0E
0D
0C
0B
0A
1@
b111000000 J
1H
#1796000
0H
#1798000
1F
b111000001 J
1H
#1800000
0H
#1802000
0F
1E
b111000010 J
1H
#1804000
0H
#1806000
1F
b111000011 J
1H
#1808000
0H
#1810000
0F
0E
1D
b111000100 J
1H
#1812000
0H
#1814000
1F
b111000101 J
1H
#1816000
0H
#1818000
0F
1E
b111000110 J
1H
#1820000
0H
#1822000
1F
b111000111 J
1H
#1824000
0H
#1826000
0F
0E
0D
1C
b111001000 J
1H
#1828000
0H
#1830000
1F
b111001001 J
1H
#1832000
0H
#1834000
0F
1E
b111001010 J
1H
#1836000
0H
#1838000
1F
b111001011 J
1H
#1840000
0H
#1842000
0F
0E
1D
b111001100 J
1H
#1844000
0H
