IMP_PLL_PFD/PFD.v
/**************************************
* Module: PFD
* Date:2015-06-30  
* Author: saul     
*
* Description: 
***************************************/
module  PFD(
A,
B,
Resetn,
QAN,
QB
);

//inputs
input A;
input B;
input Resetn;

//outputs
output QAN;
output QB;

reg QA, QAN;
reg QB;


wire res;

assign res = Resetn & ~(QA & QB);

always @(posedge A,negedge res)
begin
    if(res == 0) begin
        QA <= 0;
        QAN <= 1;
    end else begin
        QA <= 1;
        QAN <= 0;    
    end
end

always @(posedge B,negedge res)
begin
    if(res == 0) begin
        QB <= 0;        
    end else begin        
        QAN <= 1;    
    end
end


 





endmodule

IMP_PLL_PFD/PFD_tb.v
/**************************************
* Module: PFD_tb
* Date:2015-06-30  
* Author: saul     
*
* Description: 
***************************************/
module  PFD_tb(
);

//nets to drive
reg A;
reg B;
reg Resetn;

//output nets
wire QAN;
wire QB;

initial begin
    $dumpfile("PFD.vcd");
    $dumpvars(0,my_PFD);
    
    A = 0;
    B = 0;
    Resetn = 1;
    
    #2 Resetn = 0;
    #5 Resetn = 1;
    
    //A Before B
    #5 A = ~A;
    #1 B = ~B;
    #5 A = ~A;
    #1 B = ~B;
    #5 A = ~A;
    #1 B = ~B;
    #5 A = ~A;
    #1 B = ~B;
    #5 A = ~A;
    #1 B = ~B;
    #5 A = ~A;
    #1 B = ~B;
    
    //B Before A
    #5 B = ~B;
    #1 A = ~A;
    #5 B = ~B;
    #1 A = ~A;
    #5 B = ~B;
    #1 A = ~A;
    #5 B = ~B;
    #1 A = ~A;
    #5 B = ~B;
    #1 A = ~A;
    #5 B = ~B;
    #1 A = ~A;
    
    #200 $finish;
    
end

// A Active
/*
always begin
    #5 A = ~A;
    #1 B = ~B;
end
*/


// B Active
/*
always begin
    #5 B = ~B;
    #1 A = ~A;
end
*/

PFD my_PFD(A,B,Resetn,QAN,QB);


endmodule

IMP_PLL_PFD/PFD.vcd
$date
	Tue Jun 30 20:59:12 2015
$end
$version
	Icarus Verilog
$end
$timescale
	1s
$end
$scope module PFD_tb $end
$scope module my_PFD $end
$var wire 1 ! A $end
$var wire 1 " B $end
$var wire 1 # Resetn $end
$var wire 1 $ res $end
$var reg 1 % QA $end
$var reg 1 & QAN $end
$var reg 1 ' QB $end
$upscope $end
$upscope $end
$enddefinitions $end
#0
$dumpvars
x'
x&
x%
x$
1#
0"
0!
$end
#2
0'
1&
0%
0$
0#
#7
1$
1#
#12
0&
1%
1!
#13
1&
0%
1$
0'
1"
#18
0!
#19
0"
#24
0&
1%
1!
#25
1&
0%
1$
0'
1"
#30
0!
#31
0"
#36
0&
1%
1!
#37
1&
0%
1$
0'
1"
#42
0!
#43
0"
#48
1'
1"
#49
0'
1$
1&
0%
1!
#54
0"
#55
0!
#60
1'
1"
#61
0'
1$
1&
0%
1!
#66
0"
#67
0!
#72
1'
1"
#73
0'
1$
1&
0%
1!
#78
0"
#79
0!
