ASKA_SPI/aska_spi.v
`ifndef SPI_SLAVE_V
	`define SPI_SLAVE_V
	
	// MODE 0 SPI Slave V2.0
	// Author: Saul Rodriguez
	// Date: 2024-05-31

	// NOTE: This version implements an asynchronous SPI slave block 
	// Usage:
	
	// Async resetn (L) will reset the module. Once SPI_CS goes (L) the module will receive and transmit bits through the SPI_MOSI and 
	// SPI_MISO lines. Once N bytes have been received at the SPI_MOSI line, the Rx_DV output flag goes (H). The received byte 
	// is available in the register Rx_Byte. 
	// The transmit byte is copied from Ty_Byte input when SPI_CS goes (L) or in falling edge of 
	// the 8th SPI_CLK.  

    `define N 40
    `define M 32

	module aska_spi (
			//input clk,
			input resetn, // Reset async. (L)
			input SPI_CS, // chip select  (L)
			input SPI_Clk, // Mode 0, data is sampled at the rising edge
			input SPI_MOSI, // Master output  Slave Input
			//output SPI_MISO,
			//output Rx_DV, // pulse high, one cycle, when 8 bits have been received 
			//output reg [`M-1:0] Rx_data [1:0]// N bit received data
						//input [7:0] Tx_Byte // 8 bit data to transmit			
			output reg [`M-1:0] conf0,
			output reg [`M-1:0] conf1,
			output reg [`M-1:0] ele1,
			output reg [`M-1:0] ele2

			);
		
	/******************************************************/
    /* Recover the SPI_MOSI data only when SPI_CS is (L)  */
	/******************************************************/
		
		reg [`N-1:0] Rx_data_temp;
				
		always @(posedge SPI_Clk or negedge resetn) begin
			if (resetn == 1'b0) begin
				//Rx_count <= 5'b0_0000;
                Rx_data_temp <= 0;				
			end else begin
                if (SPI_CS == 1'b0) begin                   
                    Rx_data_temp <= {Rx_data_temp[`N-2:0],SPI_MOSI};	                                        
                end
			end		
		end

    /****************************************************************/
    /* Count the numbed of bits being received while SPI_CS is (L)  */
	/****************************************************************/

        reg [5:0] Rx_count;
        always @(posedge SPI_Clk or posedge SPI_CS) begin
			if (SPI_CS == 1'b1) begin
				Rx_count <= 5'b0_0000;                
			end else begin
                Rx_count <= Rx_count + 1;
			end		
		end

    /*********************************************/
    /* Copy the temp data to the output registers */
    /*********************************************/

        wire [1:0]addr;
		assign addr = Rx_data_temp[33:32];
        //assign addr[0] = Rx_data_temp[32];
        //assign addr[1] = Rx_data_temp[33];

        always @(posedge SPI_CS or negedge resetn) begin
            if (resetn == 1'b0) begin
				conf0 <= 0;
				conf1 <= 0;
				ele1 <= 0;
				ele2 <= 0;                
            end else begin
                // Copy data only if 40 bits (5 bytes) have been completely received
                if (Rx_count == `N) begin 
					case (addr)
						2'b00 : conf0 <= Rx_data_temp[31:0];
						2'b01 : conf1 <= Rx_data_temp[31:0];
						2'b10 : ele1 <= Rx_data_temp[31:0];
						2'b11 : ele2 <= Rx_data_temp[31:0];  						
					endcase                                                      
                end                
            end
        end


	endmodule
		
`endif

ASKA_SPI/aska_spi_tb.v
//Verilog HDL for "SPI_SLAVE_STIMULUS", "SPI_stimulus" "functional"

//`include "constants.vams"
//`include "disciplines.vams"

`include "aska_spi.v"

`timescale 1 ns/ 1ps

module SPI_stimulus(SPI_Clk,
		SPI_MOSI,
		SPI_CS,
		SPI_MISO,
		reset_l,
		d_Clk,
		SPI_Slave_RX,
		SPI_Slave_DV,
		SPI_Slave_TX);

	output reg SPI_Clk;
	output reg SPI_MOSI;
	output reg SPI_CS;
	output reg reset_l;
	output SPI_MISO;
	output d_Clk;
	output reg [7:0] SPI_Slave_RX;
	output SPI_Slave_DV;
	output reg [7:0] SPI_Slave_TX;
	
	reg r_Clk;

	parameter CLKS_PER_HALF_BIT = 4;  // 6.25 MHz (SPI_CLK = 3.125 MHz)
	parameter MAIN_CLK_DELAY = 20;  // 25 MHz
	parameter SPI_CLK_DELAY = MAIN_CLK_DELAY*MAIN_CLK_DELAY;

	// Clock Generators:
	always #(MAIN_CLK_DELAY) r_Clk = ~r_Clk;
	assign #6 d_Clk = r_Clk;   //delayed clock

	reg [7:0] TX_data; // Data to send through MOSI
	//reg [7:0] TX_data_old; // previous data sent through MOSI
	reg [7:0] RX_data; // Data received through MISO (circular buffer) 
	reg [7:0] SPI_Master_RX; // Data received through MISO  

	wire [`M-1:0] conf0;
	wire [`M-1:0] conf1;
	wire [`M-1:0] ele1;
	wire [`M-1:0] ele2;
	
	aska_spi aska_spi_UUT
		(
			//.clk(d_Clk),
			.resetn(reset_l),
			.SPI_CS(SPI_CS),
			.SPI_Clk(SPI_Clk),
			.SPI_MOSI(SPI_MOSI),			 
			.conf0(conf0),
			.conf1(conf1),
			.ele1(ele1),
			.ele2(ele2)
		);
		

	initial begin

		// Required for EDA Playground
		$dumpfile("dump.vcd"); 
		$dumpvars;
		$display("************************************");
		$display("Test ASKA SPI Slave");

		//Initial State
		r_Clk = 0;
		TX_data = 8'h00;
		reset_l = 1'b1;
		SPI_CS = 1'b1;
		SPI_Clk = 1'b0;
		SPI_MOSI = 1'b0;
		SPI_Slave_TX = 8'h00;
 
		//Reset
		#(10*MAIN_CLK_DELAY) reset_l = 1'b0;
		#(10*MAIN_CLK_DELAY) reset_l = 1'b1;
		#(10*MAIN_CLK_DELAY);
 

		send_ASKA(8'h00,32'haabbccdd);
		#(20*MAIN_CLK_DELAY);
		send_ASKA_error(8'h03,32'h554466aa); // send incomplete command!
		#(20*MAIN_CLK_DELAY);
		send_ASKA(8'h01,32'h3377eeff);
		#(20*MAIN_CLK_DELAY);
		send_ASKA(8'h02,32'hbebecaca);
		#(20*MAIN_CLK_DELAY);
		send_ASKA(8'h03,32'hcafebaba);

		/*
			//Test send single byte MOSI
			//send_byte_CS(8'hC1); 
 
			//#(10*MAIN_CLK_DELAY);
			// Test send double byte MOSI
			//send_byte_CS(8'hBE);
			//send_byte_CS(8'hEF);
  
			// Test Send single bytes MOSI and receive MISO 
		send_and_receive_byte_CS(8'hC1, 8'hAA);
		#(10*MAIN_CLK_DELAY);
  
		send_and_receive_byte_CS(8'hBE, 8'h33);
		#(10*MAIN_CLK_DELAY);
  
		send_and_receive_byte_CS(8'hEF, 8'h54);
		#(10*MAIN_CLK_DELAY);
  
			// Test Send double bytes MOSI and receive MISO 
		send_and_receive_byte_CS(8'hA1, 8'hEE);
		send_and_receive_byte_CS(8'h5C, 8'h1D);  
		#(10*MAIN_CLK_DELAY);
   
			// Test Send double bytes MOSI and receive MISO 
		send_and_receive_byte_CS(8'h25, 8'h83);
		send_and_receive_byte_CS(8'h38, 8'h41);

		*/  
   
		#(100*SPI_CLK_DELAY); 
		$display("************************************");
		$finish;
 
	end

	initial begin
		//    $sdf_annotate ("/home/saul/projects/TEST_LIB2/innovus/output/typ_functional_1_8V_25C.sdf",I3,, "sdf.log", "MAXIMUM");
	end

	task send_byte_CS(input [7:0] data);
		begin
			SPI_CS = 1'b0;
			#(4*MAIN_CLK_DELAY); // models delay between CS and SPI master 
			send_byte(data);
			#(4*MAIN_CLK_DELAY); // models delay between CS and SPI master 
			SPI_CS = 1'b1;	
		end
	endtask

	task send_ASKA(input [7:0] add, input [31:0] data);
		begin
			SPI_CS = 1'b0;
			#(4*MAIN_CLK_DELAY); // models delay between CS and SPI master 
			
			send_byte(add);
			send_byte(data[31:24]);
			send_byte(data[23:16]);
			send_byte(data[15:8]);
			send_byte(data[7:0]);

			
			#(4*MAIN_CLK_DELAY); // models delay between CS and SPI master 
			SPI_CS = 1'b1;	
			
			//Check values
			#(4*MAIN_CLK_DELAY);

			case (add)
				8'h00: $display("sent conf0 0x%X, received 0x%X", data, conf0);						
				8'h01: $display("sent conf1 0x%X, received 0x%X", data, conf1);
				8'h02: $display("sent ele1 0x%X, received 0x%X", data, ele1);
				8'h03: $display("sent ele2 0x%X, received 0x%X", data, ele2); 				
			endcase
			
			
		end
	endtask

	task send_ASKA_error(input [7:0] add, input [31:0] data);
		begin
			SPI_CS = 1'b0;
			#(4*MAIN_CLK_DELAY); // models delay between CS and SPI master 
			
			send_byte(add);
			send_byte(data[31:24]);
			send_byte(data[23:16]);
			send_byte(data[15:8]);
			//send_byte(data[7:0]);

			
			#(4*MAIN_CLK_DELAY); // models delay between CS and SPI master 
			SPI_CS = 1'b1;	
			
		end
	endtask

	task send_double_byte_CS(input [7:0] data1, input [7:0] data2);
		begin
			SPI_CS = 1'b0;
			send_byte(data1);
			send_byte(data2);		
			SPI_CS = 1'b1;	
		end
	endtask

	task send_and_receive_byte_CS(input [7:0] data1, input [7:0] data2);
		begin
			SPI_Slave_TX = data2;
			SPI_CS = 1'b0;
			send_byte(data1);
			//#SPI_CLK_DELAY;
			SPI_CS = 1'b1;	
		end
	endtask


	task send_byte(input [7:0] data);
		begin
			TX_data = data;			
			//#(4*MAIN_CLK_DELAY); // models delay between CS and SPI master 
			SPI_Clk = 1'b0;
			SPI_MOSI = TX_data[7];
			RX_data = 8'h00;
			
			#SPI_CLK_DELAY;		
			SPI_Clk = 1'b1;
			RX_data = RX_data << 1;
			RX_data[0] = SPI_MISO;
			#SPI_CLK_DELAY;
			SPI_Clk = 1'b0;
			SPI_MOSI = TX_data[6];
		
			#SPI_CLK_DELAY;
			SPI_Clk = 1'b1;
			RX_data = RX_data << 1;
			RX_data[0] = SPI_MISO;
			#SPI_CLK_DELAY;
			SPI_Clk = 1'b0;
			SPI_MOSI = TX_data[5];
				
			#SPI_CLK_DELAY;
			SPI_Clk = 1'b1;
			RX_data = RX_data << 1;
			RX_data[0] = SPI_MISO;
			#SPI_CLK_DELAY;
			SPI_Clk = 1'b0;
			SPI_MOSI = TX_data[4];

			#SPI_CLK_DELAY;
			SPI_Clk = 1'b1;
			RX_data = RX_data << 1;
			RX_data[0] = SPI_MISO;
			#SPI_CLK_DELAY;
			SPI_Clk = 1'b0;
			SPI_MOSI = TX_data[3];
		
			#SPI_CLK_DELAY;
			SPI_Clk = 1'b1;
			RX_data = RX_data << 1;
			RX_data[0] = SPI_MISO;
			#SPI_CLK_DELAY;
			SPI_Clk = 1'b0;
			SPI_MOSI = TX_data[2];

			#SPI_CLK_DELAY;
			SPI_Clk = 1'b1;
			RX_data = RX_data << 1;
			RX_data[0] = SPI_MISO;
			#SPI_CLK_DELAY;
			SPI_Clk = 1'b0;
			SPI_MOSI = TX_data[1];

			#SPI_CLK_DELAY;
			SPI_Clk = 1'b1;
			RX_data = RX_data << 1;
			RX_data[0] = SPI_MISO;
			#SPI_CLK_DELAY;
			SPI_Clk = 1'b0;
			SPI_MOSI = TX_data[0];
		
			#SPI_CLK_DELAY;
			SPI_Clk = 1'b1;
			RX_data = RX_data << 1;
			RX_data[0] = SPI_MISO;
			SPI_Master_RX = RX_data;		

			#SPI_CLK_DELAY;
			SPI_Clk = 1'b0;
						
		end
	endtask

endmodule

ASKA_SPI/dump.vcd
$date
	Fri May 31 17:40:21 2024
$end
$version
	Icarus Verilog
$end
$timescale
	1ps
$end
$scope module SPI_stimulus $end
$var wire 1 ! SPI_MISO $end
$var wire 1 " SPI_Slave_DV $end
$var wire 1 # d_Clk $end
$var wire 32 $ ele2 [31:0] $end
$var wire 32 % ele1 [31:0] $end
$var wire 32 & conf1 [31:0] $end
$var wire 32 ' conf0 [31:0] $end
$var parameter 32 ( CLKS_PER_HALF_BIT $end
$var parameter 32 ) MAIN_CLK_DELAY $end
$var parameter 64 * SPI_CLK_DELAY $end
$var reg 8 + RX_data [7:0] $end
$var reg 1 , SPI_CS $end
$var reg 1 - SPI_Clk $end
$var reg 1 . SPI_MOSI $end
$var reg 8 / SPI_Master_RX [7:0] $end
$var reg 8 0 SPI_Slave_RX [7:0] $end
$var reg 8 1 SPI_Slave_TX [7:0] $end
$var reg 8 2 TX_data [7:0] $end
$var reg 1 3 r_Clk $end
$var reg 1 4 reset_l $end
$scope module aska_spi_UUT $end
$var wire 1 , SPI_CS $end
$var wire 1 - SPI_Clk $end
$var wire 1 . SPI_MOSI $end
$var wire 1 4 resetn $end
$var wire 2 5 addr [1:0] $end
$var reg 6 6 Rx_count [5:0] $end
$var reg 40 7 Rx_data_temp [39:0] $end
$var reg 32 8 conf0 [31:0] $end
$var reg 32 9 conf1 [31:0] $end
$var reg 32 : ele1 [31:0] $end
$var reg 32 ; ele2 [31:0] $end
$upscope $end
$scope task send_ASKA $end
$var reg 8 < add [7:0] $end
$var reg 32 = data [31:0] $end
$upscope $end
$scope task send_ASKA_error $end
$var reg 8 > add [7:0] $end
$var reg 32 ? data [31:0] $end
$upscope $end
$scope task send_and_receive_byte_CS $end
$var reg 8 @ data1 [7:0] $end
$var reg 8 A data2 [7:0] $end
$upscope $end
$scope task send_byte $end
$var reg 8 B data [7:0] $end
$upscope $end
$scope task send_byte_CS $end
$var reg 8 C data [7:0] $end
$upscope $end
$scope task send_double_byte_CS $end
$var reg 8 D data1 [7:0] $end
$var reg 8 E data2 [7:0] $end
$upscope $end
$upscope $end
$enddefinitions $end
$comment Show the parameter values. $end
$dumpall
b110010000 *
b10100 )
b100 (
$end
#0
$dumpvars
bx E
bx D
bx C
bx B
bx A
bx @
bx ?
bx >
bx =
bx <
bx ;
bx :
bx 9
bx 8
bx 7
b0 6
bx 5
14
03
b0 2
b0 1
bx 0
bx /
0.
0-
1,
bx +
bx '
bx &
bx %
bx $
x#
z"
z!
$end
#6000
0#
#20000
13
#26000
1#
#40000
03
#46000
0#
#60000
13
#66000
1#
#80000
03
#86000
0#
#100000
13
#106000
1#
#120000
03
#126000
0#
#140000
13
#146000
1#
#160000
03
#166000
0#
#180000
13
#186000
1#
#200000
b0 5
b0 $
b0 ;
b0 %
b0 :
b0 &
b0 9
b0 '
b0 8
b0 7
03
04
#206000
0#
#220000
13
#226000
1#
#240000
03
#246000
0#
#260000
13
#266000
1#
#280000
03
#286000
0#
#300000
13
#306000
1#
#320000
03
#326000
0#
#340000
13
#346000
1#
#360000
03
#366000
0#
#380000
13
#386000
1#
#400000
03
14
#406000
0#
#420000
13
#426000
1#
#440000
03
#446000
0#
#460000
13
#466000
1#
#480000
03
#486000
0#
#500000
13
#506000
1#
#520000
03
#526000
0#
#540000
13
#546000
1#
#560000
03
#566000
0#
#580000
13
#586000
1#
#600000
03
0,
b10101010101110111100110011011101 =
b0 <
#606000
0#
#620000
13
#626000
1#
#640000
03
#646000
0#
#660000
13
#666000
1#
#680000
03
b0 +
b0 B
#686000
0#
#700000
13
#706000
1#
#720000
03
#726000
0#
#740000
13
#746000
1#
#760000
03
#766000
0#
#780000
13
#786000
1#
#800000
03
#806000
0#
#820000
13
#826000
1#
#840000
03
#846000
0#
#860000
13
#866000
1#
#880000
03
#886000
0#
#900000
13
#906000
1#
#920000
03
#926000
0#
#940000
13
#946000
1#
#960000
03
#966000
0#
#980000
13
#986000
1#
#1000000
03
#1006000
0#
#1020000
13
#1026000
1#
#1040000
03
#1046000
0#
#1060000
13
#1066000
1#
#1080000
b1 6
03
b0z +
1-
#1086000
0#
#1100000
13
#1106000
1#
#1120000
03
#1126000
0#
#1140000
13
#1146000
1#
#1160000
03
#1166000
0#
#1180000
13
#1186000
1#
#1200000
03
#1206000
0#
#1220000
13
#1226000
1#
#1240000
03
#1246000
0#
#1260000
13
#1266000
1#
#1280000
03
#1286000
0#
#1300000
13
#1306000
1#
#1320000
03
#1326000
0#
#1340000
13
#1346000
1#
#1360000
03
#1366000
0#
#1380000
13
#1386000
1#
#1400000
03
#1406000
0#
#1420000
13
#1426000
1#
#1440000
03
#1446000
0#
#1460000
13
#1466000
1#
#1480000
03
0-
#1486000
0#
#1500000
13
#1506000
1#
#1520000
03
#1526000
0#
#1540000
13
#1546000
1#
#1560000
03
#1566000
0#
#1580000
13
#1586000
1#
#1600000
03
#1606000
0#
#1620000
13
#1626000
1#
#1640000
03
#1646000
0#
#1660000
13
#1666000
1#
#1680000
03
#1686000
0#
#1700000
13
#1706000
1#
#1720000
03
#1726000
0#
#1740000
13
#1746000
1#
#1760000
03
#1766000
0#
#1780000
13
#1786000
1#
#1800000
03
#1806000
0#
#1820000
13
#1826000
1#
#1840000
03
#1846000
0#
#1860000
13
#1866000
1#
#1880000
b10 6
03
b0zz +
1-
#1886000
0#
#1900000
13
#1906000
1#
#1920000
03
#1926000
0#
#1940000
13
#1946000
1#
#1960000
03
#1966000
0#
#1980000
13
#1986000
1#
#2000000
03
#2006000
0#
#2020000
13
#2026000
1#
#2040000
03
#2046000
0#
#2060000
13
#2066000
1#
#2080000
03
#2086000
0#
#2100000
13
#2106000
1#
#2120000
03
#2126000
0#
#2140000
13
#2146000
1#
#2160000
03
#2166000
0#
#2180000
13
#2186000
1#
#2200000
03
#2206000
0#
#2220000
13
#2226000
1#
#2240000
03
#2246000
0#
#2260000
13
#2266000
1#
#2280000
03
0-
#2286000
0#
#2300000
13
#2306000
1#
#2320000
03
#2326000
0#
#2340000
13
#2346000
1#
#2360000
03
#2366000
0#
#2380000
13
#2386000
1#
#2400000
03
#2406000
0#
#2420000
13
#2426000
1#
#2440000
03
#2446000
0#
#2460000
13
#2466000
1#
#2480000
03
#2486000
0#
#2500000
13
#2506000
1#
#2520000
03
#2526000
0#
#2540000
13
#2546000
1#
#2560000
03
#2566000
0#
#2580000
13
#2586000
1#
#2600000
03
#2606000
0#
#2620000
13
#2626000
1#
#2640000
03
#2646000
0#
#2660000
13
#2666000
1#
#2680000
b11 6
03
b0zzz +
1-
