spi-slave-ASIC/Verilog_stim/SPI_Master_TB_stim.sv
//Verilog HDL for "SPI_SLAVE_STIMULUS", "SPI_stimulus" "functional"

//`include "constants.vams"
//`include "disciplines.vams"

`timescale 1 ns/ 1ps

module SPI_stimulus(SPI_Clk,
	SPI_MOSI,
	SPI_CS,
	SPI_MISO,
	reset_l,
	d_Clk);

output reg SPI_Clk;
output reg SPI_MOSI;
output reg SPI_CS;
output reg reset_l;
input SPI_MISO;
output d_Clk;

/*
reg SPI_Clk;
reg SPI_MOSI;
reg SPI_CS;
reg reset_l;
wire SPI_MISO;
reg d_Clk;
*/
reg r_Clk;

//parameter SPI_MODE = 0; // CPOL = 1, CPHA = 1
parameter CLKS_PER_HALF_BIT = 4;  // 6.25 MHz (SPI_CLK = 3.125 MHz)
parameter MAIN_CLK_DELAY = 20;  // 25 MHz
parameter SPI_CLK_DELAY = MAIN_CLK_DELAY*MAIN_CLK_DELAY;


// Clock Generators:
always #(MAIN_CLK_DELAY) r_Clk = ~r_Clk;
assign #6 d_Clk = r_Clk;   //delayed clock

reg [7:0] TX_data;

initial begin

// Required for EDA Playground
 $dumpfile("dump.vcd"); 
 $dumpvars;

//Initial State
 r_Clk = 0;
 TX_data = 8'h00;
 reset_l = 1'b1;
 SPI_CS = 1'b1;
 SPI_Clk = 1'b0;
 SPI_MOSI = 1'b0;
 
 //Reset
 #(10*MAIN_CLK_DELAY) reset_l = 1'b0;
 #(10*MAIN_CLK_DELAY) reset_l = 1'b1;
 #(10*MAIN_CLK_DELAY);
 
 // Test send single byte MOSI
 send_byte_CS(8'hC1); 
 
 #(10*MAIN_CLK_DELAY);
  // Test send double byte MOSI
 send_byte_CS(8'hBE);
 send_byte_CS(8'hEF);
  
 #(100*SPI_CLK_DELAY) $finish;
 
end

task send_byte_CS(input [7:0] data);
begin
	SPI_CS = 1'b0;
	send_byte(data);
	SPI_CS = 1'b1;	
end
endtask


task send_double_byte_CS(input [7:0] data1, input [7:0] data2);
begin
	SPI_CS = 1'b0;
	send_byte(data1);
	send_byte(data2);		
	SPI_CS = 1'b1;	
end
endtask

task send_byte(input [7:0] data);
begin
	TX_data = data;
	#(4*MAIN_CLK_DELAY); // models delay between CS and SPI master 
	    SPI_Clk = 1'b0;
		SPI_MOSI = TX_data[7];

	#SPI_CLK_DELAY;
		SPI_Clk = 1'b1;
	#SPI_CLK_DELAY;
	    SPI_Clk = 1'b0;
		SPI_MOSI = TX_data[6];
		
	#SPI_CLK_DELAY;
		SPI_Clk = 1'b1;
	#SPI_CLK_DELAY;
	    SPI_Clk = 1'b0;
		SPI_MOSI = TX_data[5];
				
	#SPI_CLK_DELAY;
		SPI_Clk = 1'b1;
	#SPI_CLK_DELAY;
	    SPI_Clk = 1'b0;
		SPI_MOSI = TX_data[4];

	#SPI_CLK_DELAY;
		SPI_Clk = 1'b1;
	#SPI_CLK_DELAY;
	    SPI_Clk = 1'b0;
		SPI_MOSI = TX_data[3];
		
	#SPI_CLK_DELAY;
		SPI_Clk = 1'b1;
	#SPI_CLK_DELAY;
	    SPI_Clk = 1'b0;
		SPI_MOSI = TX_data[2];

	#SPI_CLK_DELAY;
		SPI_Clk = 1'b1;
	#SPI_CLK_DELAY;
	    SPI_Clk = 1'b0;
		SPI_MOSI = TX_data[1];

	#SPI_CLK_DELAY;
		SPI_Clk = 1'b1;
	#SPI_CLK_DELAY;
	    SPI_Clk = 1'b0;
		SPI_MOSI = TX_data[0];
		
	#SPI_CLK_DELAY;
		SPI_Clk = 1'b1;
	#SPI_CLK_DELAY;
		SPI_Clk = 1'b0;
end
endtask

endmodule

spi-slave-ASIC/Verilog_stim/dump.vcd
$date
	Fri Jan 20 14:39:03 2023
$end
$version
	Icarus Verilog
$end
$timescale
	1ps
$end
$scope module SPI_stimulus $end
$var wire 1 ! SPI_MISO $end
$var wire 1 " d_Clk $end
$var parameter 32 # CLKS_PER_HALF_BIT $end
$var parameter 32 $ MAIN_CLK_DELAY $end
$var parameter 64 % SPI_CLK_DELAY $end
$var reg 1 & SPI_CS $end
$var reg 1 ' SPI_Clk $end
$var reg 1 ( SPI_MOSI $end
$var reg 8 ) TX_data [7:0] $end
$var reg 1 * r_Clk $end
$var reg 1 + reset_l $end
$scope task send_byte $end
$var reg 8 , data [7:0] $end
$upscope $end
$scope task send_byte_CS $end
$var reg 8 - data [7:0] $end
$upscope $end
$scope task send_double_byte_CS $end
$var reg 8 . data1 [7:0] $end
$var reg 8 / data2 [7:0] $end
$upscope $end
$upscope $end
$enddefinitions $end
$comment Show the parameter values. $end
$dumpall
b110010000 %
b10100 $
b100 #
$end
#0
$dumpvars
bx /
bx .
bx -
bx ,
1+
0*
b0 )
0(
0'
1&
x"
z!
$end
#6000
0"
#20000
1*
#26000
1"
#40000
0*
#46000
0"
#60000
1*
#66000
1"
#80000
0*
#86000
0"
#100000
1*
#106000
1"
#120000
0*
#126000
0"
#140000
1*
#146000
1"
#160000
0*
#166000
0"
#180000
1*
#186000
1"
#200000
0*
0+
#206000
0"
#220000
1*
#226000
1"
#240000
0*
#246000
0"
#260000
1*
#266000
1"
#280000
0*
#286000
0"
#300000
1*
#306000
1"
#320000
0*
#326000
0"
#340000
1*
#346000
1"
#360000
0*
#366000
0"
#380000
1*
#386000
1"
#400000
0*
1+
#406000
0"
#420000
1*
#426000
1"
#440000
0*
#446000
0"
#460000
1*
#466000
1"
#480000
0*
#486000
0"
#500000
1*
#506000
1"
#520000
0*
#526000
0"
#540000
1*
#546000
1"
#560000
0*
#566000
0"
#580000
1*
#586000
1"
#600000
0*
b11000001 )
b11000001 ,
0&
b11000001 -
#606000
0"
#620000
1*
#626000
1"
#640000
0*
#646000
0"
#660000
1*
#666000
1"
#680000
0*
1(
#686000
0"
#700000
1*
#706000
1"
#720000
0*
#726000
0"
#740000
1*
#746000
1"
#760000
0*
#766000
0"
#780000
1*
#786000
1"
#800000
0*
#806000
0"
#820000
1*
#826000
1"
#840000
0*
#846000
0"
#860000
1*
#866000
1"
#880000
0*
#886000
0"
#900000
1*
#906000
1"
#920000
0*
#926000
0"
#940000
1*
#946000
1"
#960000
0*
#966000
0"
#980000
1*
#986000
1"
#1000000
0*
#1006000
0"
#1020000
1*
#1026000
1"
#1040000
0*
#1046000
0"
#1060000
1*
#1066000
1"
#1080000
0*
1'
#1086000
0"
#1100000
1*
#1106000
1"
#1120000
0*
#1126000
0"
#1140000
1*
#1146000
1"
#1160000
0*
#1166000
0"
#1180000
1*
#1186000
1"
#1200000
0*
#1206000
0"
#1220000
1*
#1226000
1"
#1240000
0*
#1246000
0"
#1260000
1*
#1266000
1"
#1280000
0*
#1286000
0"
#1300000
1*
#1306000
1"
#1320000
0*
#1326000
0"
#1340000
1*
#1346000
1"
#1360000
0*
#1366000
0"
#1380000
1*
#1386000
1"
#1400000
0*
#1406000
0"
#1420000
1*
#1426000
1"
#1440000
0*
#1446000
0"
#1460000
1*
#1466000
1"
#1480000
0*
0'
#1486000
0"
#1500000
1*
#1506000
1"
#1520000
0*
#1526000
0"
#1540000
1*
#1546000
1"
#1560000
0*
#1566000
0"
#1580000
1*
#1586000
1"
#1600000
0*
#1606000
0"
#1620000
1*
#1626000
1"
#1640000
0*
#1646000
0"
#1660000
1*
#1666000
1"
#1680000
0*
#1686000
0"
#1700000
1*
#1706000
1"
#1720000
0*
#1726000
0"
#1740000
1*
#1746000
1"
#1760000
0*
#1766000
0"
#1780000
1*
#1786000
1"
#1800000
0*
#1806000
0"
#1820000
1*
#1826000
1"
#1840000
0*
#1846000
0"
#1860000
1*
#1866000
1"
#1880000
0*
1'
#1886000
0"
#1900000
1*
#1906000
1"
#1920000
0*
#1926000
0"
#1940000
1*
#1946000
1"
#1960000
0*
#1966000
0"
#1980000
1*
#1986000
1"
#2000000
0*
#2006000
0"
#2020000
1*
#2026000
1"
#2040000
0*
#2046000
0"
#2060000
1*
#2066000
1"
#2080000
0*
#2086000
0"
#2100000
1*
#2106000
1"
#2120000
0*
#2126000
0"
#2140000
1*
#2146000
1"
#2160000
0*
#2166000
0"
#2180000
1*
#2186000
1"
#2200000
0*
#2206000
0"
#2220000
1*
#2226000
1"
#2240000
0*
#2246000
0"
#2260000
1*
#2266000
1"
#2280000
0*
0(
0'
#2286000
0"
#2300000
1*
#2306000
1"
#2320000
0*
#2326000
0"
#2340000
1*
#2346000
1"
#2360000
0*
#2366000
0"
#2380000
1*
#2386000
1"
#2400000
0*
#2406000
0"
#2420000
1*
#2426000
1"
#2440000
0*
#2446000
0"
#2460000
1*
#2466000
1"
#2480000
0*
#2486000
0"
#2500000
1*
#2506000
1"
#2520000
0*
#2526000
0"
#2540000
1*
#2546000
1"
#2560000
0*
#2566000
0"
#2580000
1*
#2586000
1"
#2600000
0*
#2606000
0"
#2620000
1*
#2626000
1"
#2640000
0*
#2646000
0"
#2660000
1*
#2666000
1"
#2680000
0*
1'
#2686000
0"
#2700000
1*
#2706000
1"
#2720000
0*
#2726000
0"
#2740000
1*
#2746000
1"
#2760000
0*
#2766000
0"
#2780000
1*
#2786000
1"
#2800000
0*
#2806000
0"
#2820000
1*
#2826000
1"
#2840000
0*
#2846000
0"
#2860000
1*
#2866000
1"
#2880000
0*
#2886000
0"
#2900000
1*
#2906000
1"
#2920000
0*
#2926000
0"
#2940000
1*
#2946000
1"
#2960000
0*
#2966000
0"
#2980000
1*
#2986000
1"
#3000000
0*
#3006000
0"
#3020000
1*
#3026000
1"
#3040000
0*
#3046000
0"
#3060000
1*
#3066000
1"
#3080000
0*
0'
#3086000
0"
#3100000
1*
#3106000
1"
#3120000
0*
#3126000
0"
#3140000
1*
#3146000
1"
#3160000
0*
#3166000
0"
#3180000
1*
#3186000
1"
#3200000
0*
#3206000
0"
#3220000
1*
#3226000
1"
#3240000
0*
#3246000
0"
#3260000
1*
#3266000
1"
#3280000
0*
#3286000
0"
#3300000
1*
#3306000
1"
#3320000
0*
#3326000
0"
#3340000
1*
#3346000
1"
#3360000
0*
#3366000
0"
#3380000
1*
#3386000
1"
#3400000
0*
#3406000
0"
#3420000
1*
#3426000
1"
#3440000
0*
#3446000
0"
#3460000
1*
#3466000
1"
#3480000
0*
1'
#3486000
0"
#3500000
1*
#3506000
1"
#3520000
0*
#3526000
0"
#3540000
1*
#3546000
1"
#3560000
0*
#3566000
0"
#3580000
1*
#3586000
1"
#3600000
0*
#3606000
0"
#3620000
1*
#3626000
1"
#3640000
0*
#3646000
0"
#3660000
1*
#3666000
1"
#3680000
0*
#3686000
0"
#3700000
1*
#3706000
1"
#3720000
0*
#3726000
0"
#3740000
1*
#3746000
1"
#3760000
0*
#3766000
0"
#3780000
1*
#3786000
1"
#3800000
0*
#3806000
0"
#3820000
1*
#3826000
1"
#3840000
0*
#3846000
0"
#3860000
1*
#3866000
1"
#3880000
0*
0'
#3886000
0"
#3900000
1*
#3906000
1"
#3920000
0*
#3926000
0"
#3940000
1*
#3946000
1"
#3960000
0*
#3966000
0"
#3980000
1*
#3986000
1"
#4000000
0*
#4006000
0"
#4020000
1*
#4026000
1"
#4040000
0*
#4046000
0"
#4060000
1*
#4066000
1"
#4080000
0*
#4086000
0"
#4100000
1*
#4106000
1"
#4120000
0*
#4126000
0"
#4140000
1*
#4146000
1"
#4160000
0*
#4166000
0"
#4180000
1*
#4186000
1"
#4200000
0*
#4206000
0"
#4220000
1*
#4226000
1"
#4240000
0*
#4246000
0"
#4260000
1*
#4266000
1"
#4280000
0*
1'
#4286000
0"
#4300000
1*
#4306000
1"
#4320000
0*
#4326000
0"
#4340000
1*
#4346000
1"
#4360000
0*
#4366000
0"
#4380000
1*
#4386000
1"
#4400000
0*
#4406000
0"
#4420000
1*
#4426000
1"
#4440000
0*
#4446000
0"
#4460000
1*
#4466000
1"
#4480000
0*
#4486000
0"
#4500000
1*
#4506000
1"
#4520000
0*
#4526000
0"
#4540000
1*
#4546000
1"
#4560000
0*
#4566000
0"
#4580000
1*
#4586000
1"
#4600000
0*
#4606000
0"
#4620000
1*
#4626000
1"
#4640000
0*
#4646000
0"
#4660000
1*
#4666000
1"
#4680000
0*
0'
#4686000
0"
#4700000
1*
#4706000
1"
#4720000
0*
#4726000
0"
#4740000
1*
#4746000
1"
#4760000
0*
#4766000
0"
#4780000
1*
#4786000
1"
#4800000
0*
#4806000
0"
#4820000
1*
#4826000
1"
#4840000
0*
#4846000
0"
#4860000
1*
#4866000
1"
#4880000
0*
#4886000
0"
#4900000
1*
#4906000
1"
#4920000
0*
#4926000
0"
#4940000
1*
#4946000
1"
#4960000
0*
#4966000
0"
#4980000
1*
#4986000
1"
#5000000
0*
#5006000
0"
#5020000
1*
#5026000
1"
#5040000
0*
#5046000
0"
#5060000
1*
#5066000
1"
#5080000
0*
1'
#5086000
0"
#5100000
1*
#5106000
1"
#5120000
0*
#5126000
0"
#5140000
1*
#5146000
1"
#5160000
0*
#5166000
0"
#5180000
1*
#5186000
1"
#5200000
0*
#5206000
0"
#5220000
1*
#5226000
1"
#5240000
0*
#5246000
0"
#5260000
1*
#5266000
1"
#5280000
0*
#5286000
0"
#5300000
1*
#5306000
1"
#5320000
0*
#5326000
0"
#5340000
1*
#5346000
1"
#5360000
0*
#5366000
0"
#5380000
1*
#5386000
1"
#5400000
0*
#5406000
0"
#5420000
1*
#5426000
1"
#5440000
0*
#5446000
0"
#5460000
1*
#5466000
1"
#5480000
0*
0'
#5486000
0"
#5500000
1*
#5506000
1"
#5520000
0*
#5526000
0"
#5540000
1*
#5546000
1"
#5560000
0*
#5566000
0"
#5580000
1*
#5586000
1"
#5600000
0*
#5606000
0"
#5620000
1*
#5626000
1"
#5640000
0*
#5646000
0"
#5660000
1*
#5666000
1"
#5680000
0*
#5686000
0"
#5700000
1*
#5706000
1"
#5720000
0*
#5726000
0"
#5740000
1*
#5746000
1"
#5760000
0*
#5766000
0"
#5780000
1*
#5786000
1"
#5800000
0*
#5806000
0"
#5820000
1*
#5826000
1"
#5840000
0*
#5846000
0"
#5860000
1*
#5866000
1"
#5880000
0*
1'
#5886000
0"
#5900000
1*
#5906000
1"
#5920000
0*
#5926000
0"
#5940000
1*
#5946000
1"
#5960000
0*
#5966000
0"
#5980000
1*
#5986000
1"
#6000000
0*
#6006000
0"
#6020000
1*
#6026000
1"
#6040000
0*
#6046000
0"
#6060000
1*
#6066000
1"
#6080000
0*
#6086000
0"
#6100000
1*
#6106000
1"
#6120000
0*
#6126000
0"
#6140000
1*
#6146000
1"
#6160000
0*
#6166000
0"
#6180000
1*
#6186000
1"
#6200000
0*
#6206000
0"
#6220000
1*
#6226000
1"
#6240000
0*
#6246000
0"
#6260000
1*
#6266000
1"
#6280000
0*
1(
0'
#6286000
0"
#6300000
1*
#6306000
1"
#6320000
0*
#6326000
0"
#6340000
1*
#6346000
1"
#6360000
0*
#6366000
0"
#6380000
1*
#6386000
1"
#6400000
0*
#6406000
0"
#6420000
1*
#6426000
1"
#6440000
0*
#6446000
0"
#6460000
1*
#6466000
1"
#6480000
0*
#6486000
0"
#6500000
1*
#6506000
1"
#6520000
0*
#6526000
0"
#6540000
1*
#6546000
1"
#6560000
0*
#6566000
0"
#6580000
1*
#6586000
1"
#6600000
0*
#6606000
0"
#6620000
1*
#6626000
1"
#6640000
0*
#6646000
0"
#6660000
1*
#6666000
1"
#6680000
0*
1'
#6686000
0"
#6700000
1*
#6706000
1"
#6720000
0*
#6726000
0"
#6740000
1*
#6746000
1"
#6760000
0*
#6766000
0"
#6780000
1*
#6786000
1"
#6800000
0*
#6806000
0"
#6820000
1*
#6826000
1"
#6840000
0*
#6846000
0"
#6860000
1*
#6866000
1"
#6880000
0*
#6886000
0"
#6900000
1*
#6906000
1"
#6920000
0*
#6926000
0"
#6940000
1*
#6946000
1"
#6960000
0*
#6966000
0"
#6980000
1*
#6986000
1"
#7000000
0*
#7006000
0"
#7020000
1*
#7026000
1"
#7040000
0*
#7046000
0"
#7060000
1*
#7066000
1"
#7080000
0*
1&
0'
#7086000
0"
#7100000
1*
#7106000
1"
#7120000
0*
#7126000
0"
#7140000
1*
#7146000
1"
#7160000
0*
#7166000
0"
#7180000
1*
#7186000
1"
#7200000
0*
#7206000
0"
#7220000
1*
#7226000
1"
#7240000
0*
#7246000
0"
#7260000
1*
#7266000
1"
#7280000
0*
b10111110 )
b10111110 ,
0&
b10111110 -
