IMP_DAC_CTRL/DacCtrl.v
/**************************************
* Module: DacCtrl
* Date:2015-09-25  
* Author: saul     
*
* Description: 
* 
*  output P     32 steps    16 steps    8 step
* ------------------------------------------
* 8             1         1          1
* 7             0.9808      
* 6             0.9239    0.9239  
* 5             0.8315      
* 4             0.7071    0.7071     0.7071
* 3             0.5556      
* 2             0.3827    0.3827  
* 1             0.1951      
* 0             0         0          0
* 9             -0.1951     
* 10            -0.3827   -0.3827 
* 11            -0.5556     
* 12            -0.7071   -0.7071    -0.7071
* 13            -0.8315     
* 14            -0.9239   -0.9239 
* 15            -0.9808     
* 16            -1        -1         -1
* 
* The I/Q signals are ahead of the sinusoidal signal:
* 32 steps:1/32*1/2*360 = 5.625 deg
* 16 steps: = 1/16*1/2*360 = 11.25 deg
* 
***************************************/

module  DacCtrl(
CountEnable,
Clk,
Resetn,
StepNum,
P,
IP,
IN,
QP,
QN
);


//Inputs
input CountEnable;
input Clk;
input Resetn;
input StepNum;


//Outputs
//output wire P1,P2,P3,P4,P5; //Control signals for the DAC
output reg [16:0] P; //Control signals for the DAC
output wire IP,IN; // in-phase (I) reference clock
output reg QP; // quadrature (Q) reference clock
//output wire QP; // quadrature (Q) reference clock
output wire QN; 

reg [16:0] S32;
reg [16:0] S16;

reg [4:0] count;

// 5bit counter state machine
always @(posedge Clk, negedge Resetn)
begin
    if (Resetn == 0) begin
        count <= 0;
    end else begin
        count <= count + 1;    
    end    
end

// AMS VERSION 32 steps - 16 steps

//Intermediate signals 32 steps
always @(CountEnable, count)
begin
    if (CountEnable == 1) begin
        case(count)
            0:  S32 = 17'b0_0000_0000_0000_0001; //0 0V                
            1:  S32 = 17'b0_0000_0000_0000_0010;
            2:  S32 = 17'b0_0000_0000_0000_0100;
            3:  S32 = 17'b0_0000_0000_0000_1000;
            4:  S32 = 17'b0_0000_0000_0001_0000;
            5:  S32 = 17'b0_0000_0000_0010_0000;
            6:  S32 = 17'b0_0000_0000_0100_0000;
            7:  S32 = 17'b0_0000_0000_1000_0000;
            8:  S32 = 17'b0_0000_0001_0000_0000; //8 +1V
            9:  S32 = 17'b0_0000_0000_1000_0000;
            10: S32 = 17'b0_0000_0000_0100_0000;
            11: S32 = 17'b0_0000_0000_0010_0000;
            12: S32 = 17'b0_0000_0000_0001_0000;
            13: S32 = 17'b0_0000_0000_0000_1000;
            14: S32 = 17'b0_0000_0000_0000_0100;
            15: S32 = 17'b0_0000_0000_0000_0010;
            16: S32 = 17'b0_0000_0000_0000_0001;// 0V
            17: S32 = 17'b0_0000_0010_0000_0000; 
            18: S32 = 17'b0_0000_0100_0000_0000;
            19: S32 = 17'b0_0000_1000_0000_0000;
            20: S32 = 17'b0_0001_0000_0000_0000;
            21: S32 = 17'b0_0010_0000_0000_0000;
            22: S32 = 17'b0_0100_0000_0000_0000;
            23: S32 = 17'b0_1000_0000_0000_0000;            
            24: S32 = 17'b1_0000_0000_0000_0000; //16 -1V
            25: S32 = 17'b0_1000_0000_0000_0000;
            26: S32 = 17'b0_0100_0000_0000_0000;
            27: S32 = 17'b0_0010_0000_0000_0000;
            28: S32 = 17'b0_0001_0000_0000_0000;
            29: S32 = 17'b0_0000_1000_0000_0000;
            30: S32 = 17'b0_0000_0100_0000_0000;
            31: S32 = 17'b0_0000_0010_0000_0000;
            default: S32 = 17'b0_0000_0000_0000_0001; //0 0V
         endcase   
         
    end else begin
            S32 = 17'b0_0000_0000_0000_0001; //0 0V  
    end
end

//Intermediate signals 16 steps
always @(CountEnable, count)
begin
    if (CountEnable == 1) begin
        case(count)
            0:  S16 = 17'b0_0000_0000_0000_0001; //0 0V                
            1:  S16 = 17'b0_0000_0000_0000_0001;
            2:  S16 = 17'b0_0000_0000_0000_0100;
            3:  S16 = 17'b0_0000_0000_0000_0100;
            4:  S16 = 17'b0_0000_0000_0001_0000;
            5:  S16 = 17'b0_0000_0000_0001_0000;
            6:  S16 = 17'b0_0000_0000_0100_0000;
            7:  S16 = 17'b0_0000_0000_0100_0000;
            8:  S16 = 17'b0_0000_0001_0000_0000; //8 +1V
            9:  S16 = 17'b0_0000_0001_0000_0000;
            10: S16 = 17'b0_0000_0000_0100_0000;
            11: S16 = 17'b0_0000_0000_0100_0000;
            12: S16 = 17'b0_0000_0000_0001_0000;
            13: S16 = 17'b0_0000_0000_0001_0000;
            14: S16 = 17'b0_0000_0000_0000_0100;
            15: S16 = 17'b0_0000_0000_0000_0100;
            16: S16 = 17'b0_0000_0000_0000_0001;// 0V
            17: S16 = 17'b0_0000_0000_0000_0001; 
            18: S16 = 17'b0_0000_0100_0000_0000;
            19: S16 = 17'b0_0000_0100_0000_0000;
            20: S16 = 17'b0_0001_0000_0000_0000;
            21: S16 = 17'b0_0001_0000_0000_0000;
            22: S16 = 17'b0_0100_0000_0000_0000;
            23: S16 = 17'b0_0100_0000_0000_0000;            
            24: S16 = 17'b1_0000_0000_0000_0000; //16 -1V
            25: S16 = 17'b1_0000_0000_0000_0000;
            26: S16 = 17'b0_0100_0000_0000_0000;
            27: S16 = 17'b0_0100_0000_0000_0000;
            28: S16 = 17'b0_0001_0000_0000_0000;
            29: S16 = 17'b0_0001_0000_0000_0000;
            30: S16 = 17'b0_0000_0100_0000_0000;
            31: S16 = 17'b0_0000_0100_0000_0000;
            default: S16 = 17'b0_0000_0000_0000_0001; //0 0V
         endcase   
         
    end else begin
            S16 = 17'b0_0000_0000_0000_0001; //0 0V  
    end
end

always @(StepNum,S16,S32)
begin
    if (StepNum == 0) begin // 0 selects 32 steps, 1 selects 16 steps
        P = S32;
    end else begin
        P = S16;
    end
    
end

// I/Q Outputs
assign IP = ~count[4];
assign IN = ~IP;


always @(posedge count[3], negedge Resetn)
begin
    if (Resetn == 0) begin
        QP <= 0;         
    end else begin
        QP <= IP; 
    end    
end

assign QN = ~QP;

endmodule

IMP_DAC_CTRL/DacCtrl_tb.v
/**************************************
* Module: DacCtrl_tb
* Date:2015-09-26  
* Author: saul     
*
* Description: 
***************************************/
module  DacCtrl_tb(
);

//Nets to drive
reg CountEnable;
reg Clk;
reg Resetn;
reg StepNum;

//Output wires
wire [16:0] P; //Control signals for the DAC
wire IP,IN; // in-phase (I) reference clock
wire QP,QN; // quadrature (Q) reference clock

initial begin
    $dumpfile("DacCtrl.vcd");
    $dumpvars(0,my_DacCtrl);
    Clk = 0;
    CountEnable = 0;
    Resetn = 1;
       
    #2 Resetn = 0;
       StepNum = 0; // 32 steps 
    #20 Resetn = 1;
    #30 CountEnable = 1; 
    #500 StepNum = 1; // 16 steps   
    #500 CountEnable = 0;
    #50 $finish;
    
end


always begin
    #5 Clk = ~Clk;
end

DacCtrl  my_DacCtrl(
CountEnable,
Clk,
Resetn,
StepNum,
P,
IP,
IN,
QP,
QN
);


endmodule

IMP_DAC_CTRL/DacCtrl.vcd
$date
	Sat Sep 26 09:49:03 2015
$end
$version
	Icarus Verilog
$end
$timescale
	1s
$end
$scope module DacCtrl_tb $end
$scope module my_DacCtrl $end
$var wire 1 ! Clk $end
$var wire 1 " CountEnable $end
$var wire 1 # IN $end
$var wire 1 $ IP $end
$var wire 1 % QN $end
$var wire 1 & Resetn $end
$var wire 1 ' StepNum $end
$var reg 17 ( P [16:0] $end
$var reg 1 ) QP $end
$var reg 17 * S16 [16:0] $end
$var reg 17 + S32 [16:0] $end
$var reg 5 , count [4:0] $end
$upscope $end
$upscope $end
$enddefinitions $end
#0
$dumpvars
bx ,
b1 +
b1 *
x)
b1 (
x'
1&
x%
x$
x#
0"
0!
$end
#2
0#
1$
1%
0)
b0 ,
0'
0&
#5
1!
#10
0!
#15
1!
#20
0!
#22
1&
#25
b1 ,
1!
#30
0!
#35
b10 ,
1!
#40
0!
#45
b11 ,
1!
#50
0!
#52
b1000 (
b1000 +
b100 *
1"
#55
b10000 (
b10000 *
b10000 +
b100 ,
1!
#60
0!
#65
b100000 (
b100000 +
b101 ,
1!
#70
0!
#75
b1000000 (
b1000000 *
b1000000 +
b110 ,
1!
#80
0!
#85
b10000000 (
b10000000 +
b111 ,
1!
#90
0!
#95
0%
1)
b100000000 (
b100000000 *
b100000000 +
b1000 ,
1!
#100
0!
#105
b10000000 (
b10000000 +
b1001 ,
1!
#110
0!
#115
b1000000 (
b1000000 *
b1000000 +
b1010 ,
1!
#120
0!
#125
b100000 (
b100000 +
b1011 ,
1!
#130
0!
#135
b10000 (
b10000 *
b10000 +
b1100 ,
1!
#140
0!
#145
b1000 (
b1000 +
b1101 ,
1!
#150
0!
#155
b100 (
b100 *
b100 +
b1110 ,
1!
#160
0!
#165
b10 (
b10 +
b1111 ,
1!
#170
0!
#175
1#
b1 (
0$
b1 *
b1 +
b10000 ,
1!
#180
0!
#185
b1000000000 (
b1000000000 +
b10001 ,
1!
#190
0!
#195
b10000000000 (
b10000000000 *
b10000000000 +
b10010 ,
1!
#200
0!
#205
b100000000000 (
b100000000000 +
b10011 ,
1!
#210
0!
#215
b1000000000000 (
b1000000000000 *
b1000000000000 +
b10100 ,
1!
#220
0!
#225
b10000000000000 (
b10000000000000 +
b10101 ,
1!
#230
0!
#235
b100000000000000 (
b100000000000000 *
b100000000000000 +
b10110 ,
1!
#240
0!
#245
b1000000000000000 (
b1000000000000000 +
b10111 ,
1!
#250
0!
#255
1%
0)
b10000000000000000 (
b10000000000000000 *
b10000000000000000 +
b11000 ,
1!
#260
0!
#265
b1000000000000000 (
b1000000000000000 +
b11001 ,
1!
#270
0!
#275
b100000000000000 (
b100000000000000 *
b100000000000000 +
b11010 ,
1!
#280
0!
#285
b10000000000000 (
b10000000000000 +
b11011 ,
1!
#290
0!
#295
b1000000000000 (
b1000000000000 *
b1000000000000 +
b11100 ,
1!
#300
0!
#305
b100000000000 (
b100000000000 +
b11101 ,
1!
#310
0!
#315
b10000000000 (
b10000000000 *
b10000000000 +
b11110 ,
1!
#320
0!
#325
b1000000000 (
b1000000000 +
b11111 ,
1!
#330
0!
#335
0#
b1 (
1$
b1 *
b1 +
b0 ,
1!
#340
0!
#345
b10 (
b10 +
b1 ,
1!
#350
0!
#355
b100 (
b100 *
b100 +
b10 ,
1!
#360
0!
#365
b1000 (
b1000 +
b11 ,
1!
#370
0!
#375
b10000 (
b10000 *
b10000 +
b100 ,
1!
#380
0!
#385
b100000 (
b100000 +
b101 ,
1!
#390
0!
#395
b1000000 (
b1000000 *
b1000000 +
b110 ,
1!
#400
0!
#405
b10000000 (
b10000000 +
b111 ,
1!
#410
0!
#415
0%
1)
b100000000 (
b100000000 *
b100000000 +
b1000 ,
1!
#420
0!
#425
b10000000 (
b10000000 +
b1001 ,
1!
#430
0!
#435
b1000000 (
b1000000 *
b1000000 +
b1010 ,
1!
#440
0!
#445
b100000 (
b100000 +
b1011 ,
1!
#450
0!
#455
b10000 (
b10000 *
b10000 +
b1100 ,
1!
#460
0!
#465
b1000 (
b1000 +
b1101 ,
1!
#470
0!
#475
b100 (
b100 *
b100 +
b1110 ,
1!
#480
0!
#485
b10 (
b10 +
b1111 ,
1!
#490
0!
#495
1#
b1 (
0$
b1 *
b1 +
b10000 ,
1!
#500
0!
#502
1'
#505
b1000000000 +
b10001 ,
1!
#510
0!
#515
b10000000000 (
b10000000000 *
b10000000000 +
b10010 ,
1!
#520
0!
#525
b100000000000 +
b10011 ,
1!
#530
0!
#535
b1000000000000 (
b1000000000000 *
b1000000000000 +
b10100 ,
1!
#540
0!
#545
b10000000000000 +
b10101 ,
1!
#550
0!
#555
b100000000000000 (
b100000000000000 *
b100000000000000 +
b10110 ,
1!
#560
0!
#565
b1000000000000000 +
b10111 ,
1!
#570
0!
#575
1%
0)
b10000000000000000 (
b10000000000000000 *
b10000000000000000 +
b11000 ,
1!
#580
0!
#585
b1000000000000000 +
b11001 ,
1!
#590
0!
#595
b100000000000000 (
b100000000000000 *
b100000000000000 +
b11010 ,
1!
#600
0!
#605
b10000000000000 +
b11011 ,
1!
#610
0!
#615
b1000000000000 (
b1000000000000 *
b1000000000000 +
b11100 ,
1!
#620
0!
#625
b100000000000 +
b11101 ,
1!
#630
0!
#635
b10000000000 (
b10000000000 *
b10000000000 +
b11110 ,
1!
#640
0!
#645
b1000000000 +
b11111 ,
1!
#650
0!
#655
0#
b1 (
1$
b1 *
b1 +
b0 ,
1!
#660
0!
#665
b10 +
b1 ,
1!
#670
0!
#675
b100 (
b100 *
b100 +
b10 ,
1!
#680
0!
#685
b1000 +
b11 ,
1!
#690
0!
#695
b10000 (
b10000 *
b10000 +
b100 ,
1!
#700
0!
#705
b100000 +
b101 ,
1!
#710
0!
#715
b1000000 (
b1000000 *
b1000000 +
b110 ,
1!
#720
0!
#725
b10000000 +
b111 ,
1!
#730
0!
#735
0%
1)
b100000000 (
b100000000 *
b100000000 +
b1000 ,
1!
#740
0!
#745
b10000000 +
b1001 ,
1!
#750
0!
#755
b1000000 (
b1000000 *
b1000000 +
b1010 ,
1!
#760
0!
#765
b100000 +
b1011 ,
1!
#770
0!
#775
b10000 (
b10000 *
b10000 +
b1100 ,
1!
#780
0!
#785
b1000 +
b1101 ,
1!
#790
0!
#795
b100 (
b100 *
b100 +
b1110 ,
1!
#800
0!
#805
b10 +
b1111 ,
1!
#810
0!
#815
1#
b1 (
0$
b1 *
b1 +
b10000 ,
1!
#820
0!
#825
b1000000000 +
b10001 ,
1!
#830
0!
#835
b10000000000 (
b10000000000 *
b10000000000 +
b10010 ,
1!
#840
0!
#845
b100000000000 +
b10011 ,
1!
#850
0!
#855
b1000000000000 (
b1000000000000 *
b1000000000000 +
b10100 ,
1!
#860
0!
#865
b10000000000000 +
b10101 ,
1!
#870
0!
#875
b100000000000000 (
b100000000000000 *
b100000000000000 +
b10110 ,
1!
#880
0!
#885
b1000000000000000 +
b10111 ,
1!
#890
0!
#895
1%
0)
b10000000000000000 (
b10000000000000000 *
b10000000000000000 +
b11000 ,
1!
#900
0!
#905
b1000000000000000 +
b11001 ,
1!
#910
0!
#915
b100000000000000 (
b100000000000000 *
b100000000000000 +
b11010 ,
1!
#920
0!
#925
b10000000000000 +
b11011 ,
1!
#930
0!
#935
b1000000000000 (
b1000000000000 *
b1000000000000 +
b11100 ,
1!
#940
0!
#945
b100000000000 +
b11101 ,
1!
#950
0!
#952
b1 (
b1 *
b1 +
0"
#955
b11110 ,
1!
#960
0!
#965
b11111 ,
1!
#970
0!
#975
0#
1$
b0 ,
1!
#980
0!
#985
b1 ,
1!
#990
0!
#995
b10 ,
1!
