IMP_SPC2/spc2.v
/**************************************
* Module: spc2
* Date:2015-11-08  
* Author: saul     
*
* Description: Serial to Parallel converter used for configuring BIO IC V1
* This block uses 3 control lines: Cfg_in, Clk, and Resetn 
* Cfg_in is sampled at rising edge of Clk. After 14 bits, the data is latched to the paralell outputs
* 
* 
* Configuation word: F3,F2,F1,F0,    IQ,   GS3,GS2,GS1,GS0,  CE,   NS,    GD2,GD1,GD0
* F<3:0>    Frequency selection 0 - 15  (0 highest frequency (VCO freq), 15 lowest frequency)
* IQ        I = 0, Q = 1
* GS<3:0>   Signal Generator Gain [0000, 0001, 0011, 0111, 1111]
* CE        Signal Generator enable 
* NS        Signal Generator number of steps NS = 0 (32 steps), NS = 1 (16 steps)
* GD<2:0>   Demodulator Gain [100, 101, 111, 011] (NOTE: G[2] is active low logic!)
* FS        Filter Selection FS = 0 (fast), FS = 1 (slow)
* RE        Reserve pin
* 
***************************************/
module  spc2(
Cfg_in,
Clk,
Resetn,
F,
IQ,
GS,
CE,
NS,
GD,
FS,
RE
);

input Cfg_in, Clk, Resetn;

output reg[3:0] F;
output reg IQ;
output reg [3:0] GS;
output reg CE;
output reg NS;
output reg [2:0] GD;
output reg FS;
output reg RE;

reg [15:0] out; 
reg [4:0] count;

wire strobe;

/*
* Right Shift register with async. reset  
*/
always @(posedge Clk, negedge Resetn)
begin
    if (Resetn == 0) begin
        out <= 0;
        count <= 16;
    end else begin
        //Shift the data
        out[15] <= Cfg_in;
        out[14] <= out[15];
        out[13] <= out[14];
        out[12] <= out[13];
        out[11] <= out[12];
        out[10] <= out[11];
        out[9] <= out[10];
        out[8] <= out[9];
        out[7] <= out[8];
        out[6] <= out[7];
        out[5] <= out[6];
        out[4] <= out[5];
        out[3] <= out[4];
        out[2] <= out[3];
        out[1] <= out[2];
        out[0] <= out[1];
        
        //Decrement the counter
        count <= count - 1;
    end    
end

assign strobe = (!count) & (~Clk);

always @(posedge strobe, negedge Resetn)
begin
    if (Resetn == 0) begin
        F[3:0] <= 0;
        IQ <= 0;
        GS[3:0] <= 0;
        CE <= 0;
        NS <= 0;
        GD[2:0] <= 0;
        FS <= 0;
        RE <= 0;
    end else begin
        F[3:0] <= out[15:12];
        IQ <= out[11];
        GS[3:0] <= out[10:7];
        CE <= out[6];
        NS <= out[5];
        GD[2:0] <= out[4:2];
        FS <= out[1];
        RE <= out[0];
    end
end

endmodule

IMP_SPC2_TW/FPGA2/top.v
/*
* PapilioDuo top module of spc2
* top.v
*
*
*/

module  top(
Cfg_in,
Clk,
Resetn,
DIR_LEFT,
LED0,
LED1,
LED2,
LED3,
LED4,
LED5,
LED6,
LED7,
ARDUINO_RESET
);

input Cfg_in, Clk, Resetn, DIR_LEFT;

wire [3:0] F;
wire IQ;
wire [3:0] GS;
wire CE;
wire NS;
wire [2:0] GD;
wire FS;
wire RE;

output reg LED0;
output reg LED1;
output reg LED2;
output reg LED3;
output reg LED4;
output reg LED5;
output reg LED6;
output reg LED7;

output wire ARDUINO_RESET;

//behaviour
assign ARDUINO_RESET = 0;

always @(*) 
begin

    if (!DIR_LEFT) begin
        LED0 = RE;
        LED1 = FS;
        LED2 = GD[0];
        LED3 = GD[1];
        LED4 = GD[2];
        LED5 = NS;
        LED6 = CE;
        LED7 = GS[0];
    end else begin
        LED0 = GS[1];
        LED1 = GS[2];
        LED2 = GS[3];
        LED3 = IQ;
        LED4 = F[0];
        LED5 = F[1];
        LED6 = F[2];
        LED7 = F[3];    
    end

end


spc2 spc2_1(Cfg_in,Clk,Resetn,F,IQ,GS,CE,NS,GD,FS,RE);


endmodule

IMP_SPC2_TW/FPGA2/spc2_pap_tb.v
/**********************************************************************
* Module: spc1_tb
* Date:2015-05-02  
* Author: saul     
*
* Description: test bench for spc2
* 
* Configuation word: F3,F2,F1,F0,    IQ,   GS3,GS2,GS1,GS0,  CE, NS,  GD2,GD1,GD0
* F<3:0>    Frequency selection 0 - 15  (0 highest frequency (VCO freq), 15 lowest frequency)
* IQ        I = 0, Q = 1
* GS<3:0>   Signal Generator Gain [0000, 0001, 0011, 0111, 1111]
* CE        Signal Generator enable 
* NS        Signal Generator number of steps NS = 0 (32 steps), NS = 1 (16 steps)
* GD<2:0>   Demodulator Gain [100, 101, 111, 011] (NOTE: G[2] is active low logic!)
* FS        Filter Selection FS = 0 (fast), FS = 1 (slow)
* RE        Reserve pin
*  
***********************************************************************/

module  spc2_pap_tb(
);

//Lines to drive
//reg Clk, Resetn, Cfg_in, Strobe;
reg Clk, Resetn, Cfg_in, DIR_LEFT;


//Output signals

wire LED0;
wire LED1;
wire LED2;
wire LED3;
wire LED4;
wire LED5;
wire LED6;
wire LED7;
wire ARDUINO_RESET;

parameter [15:0] confWord  = 16'b1010_1_1011_0_1_001_0_1; //0x561
parameter [15:0] confWord2 = 16'b0101_0_0100_1_0_110_1_0; //0x657

reg [15:0] conf;
reg [15:0] conf2;


initial begin
    $dumpfile("top.vcd");
    $dumpvars(0,my_top);
    
    conf = confWord;
    conf2 = confWord2;
    
    Clk = 0;
    Resetn = 1;
    Cfg_in = 0;
    DIR_LEFT = 0;
//    Strobe = 0;
    
    #1 Resetn = 0;
    #2 Resetn = 1;
    #1 Cfg_in = conf[0];
    #10 Cfg_in = conf[1];
    #10 Cfg_in = conf[2];
    #10 Cfg_in = conf[3];
    #10 Cfg_in = conf[4];
    #10 Cfg_in = conf[5];
    #10 Cfg_in = conf[6];
    #10 Cfg_in = conf[7];
    #10 Cfg_in = conf[8];
    #10 Cfg_in = conf[9];
    #10 Cfg_in = conf[10];
    #10 Cfg_in = conf[11];
    #10 Cfg_in = conf[12];
    #10 Cfg_in = conf[13];    
    #10 Cfg_in = conf[14];
    #10 Cfg_in = conf[15];
    //Second word
    
    #60 Resetn = 0;
    #2 Resetn = 1;
    #1 Cfg_in = conf2[0];
    #10 Cfg_in = conf2[1];
    #10 Cfg_in = conf2[2];
    #10 Cfg_in = conf2[3];
    #10 Cfg_in = conf2[4];
    #10 Cfg_in = conf2[5];
    #10 Cfg_in = conf2[6];
    #10 Cfg_in = conf2[7];
    #10 Cfg_in = conf2[8];
    #10 Cfg_in = conf2[9];
    #10 Cfg_in = conf2[10];
    #10 Cfg_in = conf2[11];
    #10 Cfg_in = conf2[12];
    #10 Cfg_in = conf2[13];
    #10 Cfg_in = conf2[14];
    #10 Cfg_in = conf2[15];
    
  //  #5 Strobe = 1;
    #50 $finish;    
    
end

always begin
    #5 Clk = ~Clk;
end

//spc2 my_spc2(Cfg_in,Clk,Resetn,F,IQ,GS,CE,NS,GD,FS,RE);
top my_top(Cfg_in,Clk,Resetn,DIR_LEFT,LED0,LED1,LED2,LED3,LED4,LED5,LED6,LED7,ARDUINO_RESET);

endmodule

IMP_SPC2_TW/FPGA2/top.vcd
$date
	Thu Sep 15 14:09:11 2016
$end
$version
	Icarus Verilog
$end
$timescale
	1s
$end
$scope module spc2_pap_tb $end
$scope module my_top $end
$var wire 1 ! ARDUINO_RESET $end
$var wire 1 " CE $end
$var wire 1 # Cfg_in $end
$var wire 1 $ Clk $end
$var wire 1 % DIR_LEFT $end
$var wire 4 & F [3:0] $end
$var wire 1 ' FS $end
$var wire 3 ( GD [2:0] $end
$var wire 4 ) GS [3:0] $end
$var wire 1 * IQ $end
$var wire 1 + NS $end
$var wire 1 , RE $end
$var wire 1 - Resetn $end
$var reg 1 . LED0 $end
$var reg 1 / LED1 $end
$var reg 1 0 LED2 $end
$var reg 1 1 LED3 $end
$var reg 1 2 LED4 $end
$var reg 1 3 LED5 $end
$var reg 1 4 LED6 $end
$var reg 1 5 LED7 $end
$scope module spc2_1 $end
$var wire 1 # Cfg_in $end
$var wire 1 $ Clk $end
$var wire 1 - Resetn $end
$var wire 1 6 strobe $end
$var reg 1 7 CE $end
$var reg 4 8 F [3:0] $end
$var reg 1 9 FS $end
$var reg 3 : GD [2:0] $end
$var reg 4 ; GS [3:0] $end
$var reg 1 < IQ $end
$var reg 1 = NS $end
$var reg 1 > RE $end
$var reg 5 ? count [4:0] $end
$var reg 16 @ out [15:0] $end
$upscope $end
$upscope $end
$upscope $end
$enddefinitions $end
#0
$dumpvars
bx @
bx ?
x>
x=
x<
bx ;
bx :
x9
bx 8
x7
x6
x5
x4
x3
x2
x1
x0
x/
x.
1-
x,
x+
x*
bx )
bx (
x'
bx &
0%
0$
0#
x"
0!
$end
#1
05
04
03
02
01
00
0/
0.
06
0>
0,
09
0'
b0 :
b0 (
0=
0+
07
0"
b0 ;
b0 )
0<
0*
b0 8
b0 &
b10000 ?
b0 @
0-
#3
1-
#4
1#
#5
b1111 ?
b1000000000000000 @
1$
#10
0$
#14
0#
#15
b1110 ?
b100000000000000 @
1$
#20
0$
#24
1#
#25
b1101 ?
b1010000000000000 @
1$
#30
0$
#34
0#
#35
b1100 ?
b101000000000000 @
1$
#40
0$
#45
b1011 ?
b10100000000000 @
1$
#50
0$
#54
1#
#55
b1010 ?
b1001010000000000 @
1$
#60
0$
#64
0#
#65
b1001 ?
b100101000000000 @
1$
#70
0$
#74
1#
#75
b1000 ?
b1010010100000000 @
1$
#80
0$
#85
b111 ?
b1101001010000000 @
1$
#90
0$
#94
0#
#95
b110 ?
b110100101000000 @
1$
#100
0$
#104
1#
#105
b101 ?
b1011010010100000 @
1$
#110
0$
#115
b100 ?
b1101101001010000 @
1$
#120
0$
#124
0#
#125
b11 ?
b110110100101000 @
1$
#130
0$
#134
1#
#135
b10 ?
b1011011010010100 @
1$
#140
0$
#144
0#
#145
b1 ?
b101101101001010 @
1$
#150
0$
#154
1#
#155
b0 ?
b1010110110100101 @
1$
#160
15
13
10
1.
1>
1,
b1 :
b1 (
1=
1+
b1011 ;
b1011 )
1<
1*
b1010 8
b1010 &
16
0$
#165
b11111 ?
b1101011011010010 @
06
1$
#170
0$
#175
b11110 ?
b1110101101101001 @
1$
#180
0$
#185
b11101 ?
b1111010110110100 @
1$
#190
0$
#195
b11100 ?
b1111101011011010 @
1$
#200
0$
#205
b11011 ?
b1111110101101101 @
1$
#210
0$
#214
05
03
00
0.
0>
0,
b0 :
b0 (
0=
0+
b0 ;
b0 )
0<
0*
b0 8
b0 &
b10000 ?
b0 @
0-
#215
1$
#216
1-
#217
0#
#220
0$
#225
b1111 ?
b0 @
1$
#227
1#
#230
0$
#235
b1110 ?
b1000000000000000 @
1$
#237
0#
#240
0$
#245
b1101 ?
b100000000000000 @
1$
#247
1#
#250
0$
#255
b1100 ?
b1010000000000000 @
1$
#260
0$
#265
b1011 ?
b1101000000000000 @
1$
#267
0#
#270
0$
#275
b1010 ?
b110100000000000 @
1$
#277
1#
#280
0$
#285
b1001 ?
b1011010000000000 @
1$
#287
0#
#290
0$
#295
b1000 ?
b101101000000000 @
1$
#300
0$
#305
b111 ?
b10110100000000 @
1$
#307
1#
#310
0$
#315
b110 ?
b1001011010000000 @
1$
#317
0#
#320
0$
#325
b101 ?
b100101101000000 @
1$
#330
0$
#335
b100 ?
b10010110100000 @
1$
#337
1#
#340
0$
#345
b11 ?
b1001001011010000 @
1$
#347
0#
#350
0$
#355
b10 ?
b100100101101000 @
1$
#357
1#
#360
0$
#365
b1 ?
b1010010010110100 @
1$
#367
0#
#370
0$
#375
b0 ?
b101001001011010 @
1$
#380
14
12
11
1/
19
1'
b110 :
b110 (
17
1"
b100 ;
b100 )
b101 8
b101 &
16
0$
#385
b11111 ?
b10100100101101 @
06
1$
#390
0$
#395
b11110 ?
b1010010010110 @
1$
#400
0$
#405
b11101 ?
b101001001011 @
1$
#410
0$
#415
b11100 ?
b10100100101 @
1$
